{
  "id": "book_2453",
  "title": "我和姐妹花的激情岁月",
  "author": "未知",
  "cover": "",
  "description": "很快我就被分配到了令人羡慕的销售部，因为我们这个企业主要是化工原料的产品初加工，而且属于那种比较短缺的原料，所以市场基本上不用开拓，都是其他企业找上门来，一次拿下订单后，可能吃好几年，所以销售部门基本...",
  "sourceId": "jisge",
  "sourceName": "集书阁",
  "chapters": [
    {
      "id": "ch1",
      "title": "我和姐妹花的激情岁月",
      "index": 0,
      "url": "",
      "content": "你好，来源 \n这里先介绍一下陈清的基本情况，来源\n一个周末，想起好长时间没有给老家的父母亲打电话了，便向单位走去，毕竟单位的长途不要钱嘛。快走到销售部门的时候，我突然听到好像办公室里边有人，这么热的天，来源\n\n通过窗户偷偷一看，我吓了一大跳，来源\n可没有两三分钟，突然王厂长一声音大叫，原来他射精了，然后很快他便有气无力地停了下来，怎么这么快呀，真是个快枪手，而陈清好像还根本没有得到满足，她的小手开始不停地揉搓着自己的阴蒂和阴唇，来源\n当我将这个消息告诉陈清的时候，她竟然是非常的高兴，来源 \n当我和王厂长还有陈清即将登机时，突然王厂长的电话响了，原来是他儿子打来的电话，王厂长的老婆突然心脏病犯了，正送往医院急救中。王厂长接完了电话，来源\n\n到了南宁，来源\n\n告别了阿俊，我感觉两条腿已经不听指挥了，来源\n\n一觉醒来时，已经是晚上１０点多，原来我从中午喝完酒３点多到现在睡了有８个小时，我感觉自己的嗓子非常的干，想起来喝水，这时才发现自己竟然是躺在床上的，而且身上只穿了一件裤头，开灯一下，来源\n\n走进了卫生间，脱掉了三角裤头，打开淋浴器，刚准备冲，我突然发现，这个卫生间竟然是用一大块玻璃隔开的，就是人站在时边，房子里的人什么都能看清楚，怎么会是这样的呢，停顿了一下，我才想起，原来住起来的时候就是这样，只是刚才我喝得太多，来源\n\n出来后我对陈清说，这个卫生间我怎么总感觉有些奇怪呢，来源\n\n怎么是这样呢，实在不好意思，来源\n我继续地亲着她，陈清想挣扎，可挣扎不开，别，别，来源\n\n我的手不安非地乱摸着，来源\n\n也不知道什么时候，我们已经换成了６９式，我的舌头开始亲起了陈清的乳房，慢慢地亲向了她的阴蒂，而陈清则扭动着身体，来源\n\n而且有意无意地用牙齿在我的龟头上轻轻的刮过，来源\n过了一会儿，我们换成了正位，我趴在陈清的身上，开始了进攻，陈清用她潮热的阴道紧贴住我坚挺的鸡巴，微微地张开她了那浑圆修长的美腿，来源\n\n噢……噢……啊……对……对……用力……用力……你比我老公厉害多了，快用力，…顶住……用力……啊……唔……好样……啊……好大的鸡巴，比我老公厉害多了……来源\n激情过后，陈清突然哭了，你把我当成什么人了，怎么会这样呢，怎么会这样呢，我怎么向我老公交待呀。这时的我也完全清醒过来了，这才想到，陈清的王厂长的情人，来源\n吃完晚饭，我们直接就进了房间。陈清对我说，你转过身去，我要脱衣冲澡了。我一听忙说，\n别闹了，我要冲澡了，陈清再次笑着说道。我放了陈清，看着她脱下了内裤，走了浴室。浴室里传来了哗哗的水声。我也开始脱光了衣服，挺着那早起高高举起的鸡巴走进了浴室。干什么呀，来源\n\n然后用嘴巴紧紧地贴上了陈清的嘴巴。手指也伸向了陈清那神秘地，用手轻轻地扣着陈清那粉红色的肉缝，慢慢地那肉缝开张了，我的手指翻开陈清的小阴唇，来源\n\n很快我就感受到陈清阴道内温暖和压力了，我开始九浅一深地插入，卖力抽插着，来源\n\n呀……来源\n\n就这样，在广西旅游的日子里，我们聊了游山玩水，来源\n\n回到工厂后，王厂长非常的高兴，来源\n\n当然，来源 \n八月，到处热得要命，只有办公室还能凉快一些，陈清和王厂长外出办事去了，办公室就我一个人，正在办公室坐着看报纸，突然，来源\n\n我忙问，你找谁。没有等我讲完话，她竟然开口说话了，你是李哥吧，我是陈清的妹妹陈洁，早就听我姐提到过你了。哦，来源 \n我姐说让你帮我补课陈洁真是快人快语。嗯，有这码事，可我还没有什么思想准备。我姐说你是名牌大学毕业的高材生了，找你补课，肯定能考上大学我呵呵一笑。来源\n第一次进陈清家，真有一种家的感觉，不像我住的宿舍，来源 \n吃完晚饭，我便到陈洁的房间开始给她辅导功课了，没有想到的是，这个小妮子的基础是这样的差，也不知道她在学校都干什么的，基本上是一问三不知，我只能从头开始，来源\n\n才补了几天课，突然陈清接到了个从西藏打来的电话，就她老公在外出给藏民看病时因为路不好，出了车祸，现在生命垂危，让她赶快去。来源\n\n陈清走之后，我还是照样每天下班后给陈洁去补课。没有了陈清在家，陈洁在我面前开玩笑竟然更加肆无忌惮了，来源 \n这天补了一个多小时的课之后，我们开始休息，无意间我翻开了陈清的结婚照片，就对陈洁说，你看你姐和你姐夫，多么幸福的一对呀，可惜你姐夫却去了西藏。这时陈洁突然一声叹息。来源\n\n他们夫妻之间很少做那事的，就是做都是几分钟。没有想到这个小妮子竟然知道这些东西，而且对夫妻间的事情竟然都懂，是不是和别人做过呢。来源\n\n我一听，哈哈，果真这个小妮子不简单，从衣着打扮就知道肯定很骚了，来源\n\n我又故意说，我上高中时都摸过我女朋友的那个了，来源 \n才不是呢，是…陈洁又不说了，我知道，来源\n\n我又说，我在大学时都和我女友上过床了，你肯定不会超过我们吧。那也说不定吧。陈洁急忙说。我一听，马上说，你们高中时都上过床了吗，哈哈，我马上告诉你姐去。陈洁一听忙说，来源\n是陈清，终于看清了，来源\n\n我忙说你姐和你姐夫还真浪漫，竟然拍这个。这时陈洁的脸已经通红了，而且眼睛盯着电视一动不动，我知道她肯定是看入迷了，我忙说，来源\n\n我一听，呵呵，有门。忙说，来源\n\n我奋力地脱掉了自己的衣服，来源\n\n而这时的陈洁也没有闲着，她的一只手从我的大腿外侧伸过来抓住了鸡巴开始套弄，我的左手在陈洁的两个乳房上轮流揉着，来源 \n随着我中指在在她肉穴里刺激，陈洁的性欲不断地上涨，肉穴开始发热，来源 \n而我的鸡巴在陈洁的的套弄下非常的胀，恨不得马上插入陈洁的肉穴，我将陈洁抱到了陈清的床上，心想虽然没有在陈清的床上干过她，但这次终于在可以陈清的床上将她的妹妹就正法了。我分开了陈洁的双腿，来源\n\n陈洁的阴道里已经分泌出大量的淫水，随着我鸡巴的抽插，开始吱吱水响。我一边抽插着，一边问，我的鸡巴怎么样，比你男朋友的强吧。感到无比舒适的陈洁，来源\n\n比你姐的紧多了，噢！……来源 \n说完这句后，我突然有些后悔，来源\n\n我再次加大了抽插力度，每次都将龟头顶到了陈洁身体的最深处，突然陈洁大叫：哎哟……我死了……来源 \n我知道陈洁的高潮已经来临了，我也实现憋不住了，猛地抽出了鸡巴，对着陈洁洁白的身体，不顾一切地射出了全部的精液，我知道我不能射在陈洁的身体里边，万一弄怀孕了，那可不是好玩的。陈洁这时已经手足乱颤，两眼紧闭，来源"
    }
  ],
  "tags": [
    "其他"
  ]
}