{
  "id": "book_955",
  "title": "颤抖樱桃２之二（湿徒情缘）（2）",
  "author": "未知",
  "cover": "",
  "description": "颤抖樱桃２之湿徒情缘１正当小梦及雅仪两人着好衣装之时┅┅一道强力的气芒狂旋而出，目标正是小梦，情急之下┅┅“小梦啊！”雅仪一把推开了小梦，但雅仪不幸中了那劈山裂石的掌力┅┅但一切都太突然了，当小梦反应...",
  "sourceId": "jisge",
  "sourceName": "集书阁",
  "chapters": [
    {
      "id": "ch1",
      "title": "颤抖樱桃２之二（湿徒情缘）（2）",
      "index": 0,
      "url": "",
      "content": "正当小梦及雅仪两人着好衣装之时┅┅“小梦啊！”“仪姐啊┅┅”小梦急忙抱住雅仪，大声地叫着∶“仪姐，来源\n就在雅仪断气的同一刹那，两条人影如鬼魅般出现，一人形同颧罗，背上架着一把巨型镰刀，形似颧罗的首先开口∶““┅┅”另一人则开口道∶“生何欢喜，死何畏惧，留神来，～～”\n“┅┅为什么？”小梦低声地说，““来源\n语暴起““面如书生的开口∶“话一停，白镰音便抽起背上的镰刀，一一挡下了小梦的攻势，小梦见一击不成，便跳到白镰音的背后∶“二齐双华！”小梦使用“七形天式”“你没机会了，来源\n镰刀从头上劈斩而过，正当小梦危急之时┅┅一道气芒夹带沙尘，以排山倒海之势狂啸而来，硬生生地把巨镰震开白镰音虎口一麻，同时连退数步，震道∶“好厉害的功力！”\n一股袭人的杀气，将浓烟渐渐消散，一条雄伟的人影，沙尘起，雪花落，来源\n冰冷途，来源\n“来者何人？”持扇书生问道，雄伟身影默默不语，望着雅仪淡淡的遗笑，及受伤的小梦，剑眉深蹙，指着白镰音及持扇书生大吼∶“白镰音，孟都服，其音量之大，连地上的小石都跳动不已，白镰音两人心头一震，知道极端将至，彼此眼神一对，白镰音的“破浪旋斩”加上孟都服的“百扇光刀流”如迅雷般攻向武剑官，“孟都服尚未听完，“┅┅的关系┅┅”武剑官抽出了长剑，剑锋还不断滴着鲜血，来源\n“┅┅”\n““来源\n“小梦宛然一笑，双手圈上武剑官的脖子，吻上了武剑官那英挺的鼻子，脸泛红晕地说∶“┅┅＝＝夜空黑幕，寂寂冷夜，另一方面，武剑官明白一切将会实现，为了小梦，来源\n必然的结局，最后的一切，在武剑官的治疗之下，小梦的脸色开始好转，“┅┅啊┅┅师父┅┅你┅┅的┅┅好┅┅好粗大┅┅插┅┅得┅┅小┅┅梦┅┅的┅┅洞洞┅┅舒┅┅服┅┅死了┅┅再┅┅来┅┅我┅还┅┅要┅┅师父的┅┅大┅┅大┅┅肉┅┅棒┅┅把我┅┅的┅┅小梦不断地娇喘，同时把屁股往下一压，两人不断重复着几种不同的体位，让武剑官雄伟的骄傲开拓着小梦年轻的花圃，两人皆沉醉在巫山云雾，翻云覆雨之乐，但任何事总有尾声的时候，武剑官感觉到急流将至，连忙抽出分身，让小梦含哺着，“哇啊！┅┅┅┅”天谴大叫，同时一股白浊的液体如洪水般从武剑官的分身中射出，小梦紧闭着嘴，不让任何一滴精液漏出，分身毫无止境，不断地喷射着，治疗结束，武剑官百年功力已转移至小梦的体内，天谴对小梦说∶““天命？”“不用怀疑，历代剑官世家的传人皆有此命运，小梦不解地问∶“做法？扭转？“小梦徒弟，现在你去儒天，找一名外号叫“白色皇衣”小梦问道:““““紧张紧张紧张，到底武剑官向小梦说什么惊人的事情？谜般的高人“来源\n一阵悦耳的箫声在荒郊出现，引起三对带杀的眼神，来源"
    }
  ],
  "tags": [
    "其他"
  ]
}