{
  "id": "book_341",
  "title": "西游艳记",
  "author": "未知",
  "cover": "",
  "description": "返回长篇情色小说\n\t\t\t西游艳记 - 集书阁",
  "sourceId": "jisge",
  "sourceName": "集书阁",
  "chapters": [
    {
      "id": "content_53da7f3192c957f199365cef25b5e94d_1",
      "title": "内容简介",
      "index": 0,
      "url": "/content_53da7f3192c957f199365cef25b5e94d_1.html",
      "content": "本书描写了主人公唐小玄穿越到《\n京城唐家的四少爷，是个不务正业的浪荡公子，穿越了时空，来到《西游记》\n驻京部队的军区司令，"
    },
    {
      "id": "content_53da7f3192c957f199365cef25b5e94d_10",
      "title": "第八章 忽悠黄风怪",
      "index": 1,
      "url": "/content_53da7f3192c957f199365cef25b5e94d_10.html",
      "content": "孙悟空一看猪八戒在那偷懒睡觉，顿时大怒：“这个呆子！让他去前路化斋，他倒好，\n孙悟空扔了行李担，跳上前去，伸手就抓住了猪八戒的一只耳朵使劲一扯，骂道：“呆子，\n“啊？\n猪八戒虽然疼得龇牙咧嘴，竟然还在迷糊中问道，待睁眼看时，赶紧伸手握住孙悟空扯着他耳朵的手，试图减少一些孙悟空手上的力量，讪讪道：“哎……猴哥，\n“你还有脸问师父？刚才我们是怎么说的？要你到前面去探路，顺便化缘，\n“\n唐小玄冷冷地呼唤一声，吓得猪八戒赶紧跪在白龙马前，\n“八戒，师父命你前面探路化缘，\n唐小玄声音平静，话里却充满着威严，他正拿着现代的领导作风到西游世界里演练呢！当领导的，不能随便生气，\n“师父，\n猪八戒微微抬头，一对大耳朵扇动着，\n孙悟空气得抓耳挠腮，掣出金箍棒就要打，\n唐小玄说完，\n“哎……\n猪八戒竟然挤出了几滴眼泪，快速爬起来，一把将唐小玄的腿抱住，哭道：“师父，俺老猪既然听了菩萨的教诲，\n猪八戒竟然哭得涕泪交流，让唐小玄看得也有些奇怪，\n“\n“好吧，这次八戒你确实犯错了，师父也不能揪住你的小辫子不放，这样吧，你暂时还是留下来，\n唐小玄故意拖上了声音，\n“从现在起，至少一个月内，\n唐小玄向悟空一招手，说道：“悟空，我们两个到前面去，\n“是，\n见唐小玄上了白龙马，\n唐小玄下马，孙悟空接了疆绳，八戒歇了行李，\n唐小玄拄着九环锡杖，\n唐小玄不敢高言，轻轻叫了一声：“施主，\n那老者一骨碌跳了起来，忙敛衣襟，出门还礼道：“长老，失迎。\n唐小玄道：“贫僧是东土大唐和尚，奉圣旨上雷音寺拜佛求经。\n唐小玄这话，可是学着西游记里唐僧的话说的，而且说得一字不差，\n那老头摆手摇头道：“\n唐小玄口中不语，意下沉吟：“菩萨指道西去，怎么此老说往东行？\n腼腆难言，半晌不答。\n原来这老者看到了唐小玄身后的猪八戒，顿时吓得全身直抖，老者道：“刚才……刚才就是那个妖怪……来到我家门前，\n“老人家不须害怕，\n“\n这老头将三人请进家门，然猪八戒刚才把人家老头吓着了，只好听从悟空的话，\n等那少年搬来凳子时，唐小玄这才明白，\n此时天色渐晚，三人与老者坐在桌前，晚风吹来，渐渐凉爽，少年又送来了斋饭，\n“老人家刚才说西行的经难取，\n唐小玄恭敬地问道，此时八戒已经吃了一碗饭了，那少年急忙帮八戒装饭，然看到八戒的嘴脸时，他吓了一跳，退出老远，\n“呃……\n老者见少年害怕，连忙安慰道，这才歉然地向唐小玄道：“\n“\n“那就好、\n唐小玄和孙悟空各吃了两碗，八戒已经吃了十几大碗，\n“你这个呆子，吃这么多了还要吃？也得替人家主人留点饭吧；”孙悟空看不过去了，伸手就要扭猪八戒的耳朵，吓得猪八戒忽地跳起身，躲得远远，嘴里却道：“猴哥，我老猪就是吃得多了一些，你们又不是不知道，我自从跟了师父，\n“哈哈，\n唐小玄见猪八戒如此委屈，\n老者虽然对于八戒惊人的食量异常惊讶，还是笑道：“\n唐小玄和孙悟空都道：“\n八戒虽然还想吃，\n送唐小玄哈哈一笑道：“老人家也太小看我们师徒了！放心吧，我们出家人不走回头路，既然决定西行取经，取不到真经，\n孙悟空一挑拇指，赞道：“师父果然佛性坚定，\n“\n唐小玄催促着白龙马，八戒连忙挑起行李担子，悟空继续探路，行不多远，\n这座高山，看起来十分险峻。唐小玄马到临崖，斜挑宝铠观看，只见那高的是山，\n唐小玄早被刮得下了龙马，用手遮面，八戒叫道：“师父，风大，\n唐小玄一听，差点笑出声来，八戒这话，听起来特别像一句江湖黑话：\n“\n“\n“\n猪八戒奇怪道，唐小玄虽然也从西游记中听说过，却没有真正见过，听得孙悟空这么说，\n他让过风头，至风尾处，果然伸手一抓，放到鼻前闻了闻，说道：“\n“\n猪八戒把头拱在行李担子里面，撅起肥硕的大屁股，\n“\n在那虎离唐小玄还有两、\n“\n又是一声虎啸声，震得山间树木落叶纷纷，\n猪八戒听得风声已停，而面前只是一只老虎时，忽然一骨碌爬了起来，高声叫道：“好你个瞎眼虎，竟然不认得你家爷爷，我们是东土大唐御弟三藏之弟子，奉旨上西方拜佛求经者。你如果早早避开，远远滚蛋，我和师兄就饶了你的性命，\n虎怪根本不答话，直接扑向八戒，伸出爪子就抓了过去，猪八戒也不含糊，闪身躲过，举起钉耙往头就是一下。那虎怪手里没有武器，\n“师父，\n孙悟空说话间，纵身下了山坡，唐小玄知道这是虎怪的调虎离山之计，想要张口唤住孙悟空的时候，那性急的猴子早已经掣出金箍棒，一棒向虎怪头上打去！\n一道青烟闪过，\n“不好，\n孙悟空这才想起，自己本来应该在师父身边保护的，\n“\n孙悟空气得猴牙紧咬，四下里忙着寻找唐小玄，八戒过了一会儿才爬上山坡，惊讶道：“\n“你这呆子还问什么？\n他们奔入山中，穿岗越岭，行不多时，只见那石崖之下耸出一座洞府。两人定步观瞻，果然凶险，但见那迭障尖峰，回峦古道。青松翠竹依依，绿柳碧梧冉冉。\n孙悟空整一整衣服，束一束虎裙，掣棒撞至那门前。只见那门上有六个大字，乃“\n唐小玄被捉住后，被直接送进妖洞中，他的本事虽然比唐僧强得多，可跟这些妖怪还是没法比，\n“\n那妖怪听到唐小玄叫唤，撇下了虎先锋，\n唐小玄认真观察这妖怪，只见这妖怪虽然化作了人形，脑袋却是一副黄毛貂鼠模样，不过走过来时却还自有一番大王风度；他浑身金盔金甲，金盔上飘舞着山雉尾的盔缨，\n“黄风怪，\n“\n这黄风怪曾经捉到过无数的人，每一个来到这妖洞中之后，都是吓得魂飞魄散，甚至有直接吓傻了的也丝毫不奇怪。\n“\n唐小玄阴着脸，双目中露出蔑视的光，冷笑一声，续道：“黄风怪，你也是一洞之主，被小妖们称为大王，难道还会怕我这个柔弱的和尚会逃跑吗？\n“\n黄风怪修行千年，还真就没怕过谁，只是对灵吉菩萨，\n虎先锋想要阻拦时，\n他径直来到黄风怪的虎皮交椅前，\n“黄风怪，我讲一个故事给你们听吧，你们慢慢听下去，\n唐小玄咳嗽一声，坐直了身体，\n唐小玄的话说到这里的时候，黄风怪和虎先锋都露出了得意的神色，\n“\n虎先锋抬起虎爪，\n“\n唐小玄就按照西游记里的情节，把黄风怪和虎先锋的命运，一点一点讲了下去。\n唐小玄收住自己的故事，\n“虎先锋，你带上五十个小妖，\n然话刚出口就觉得有些不对，这不是特意在按照唐小玄的吩咐去做事了吗？\n“\n本来雄赳赳，气昂昂的虎先锋，被唐小玄的一番话说得背部一阵阵发凉，双目中也露出恐惧之色，\n“\n黄风怪的目光突然亮了起来，他的语气也渐渐狠厉，逼视着虎先锋，\n黄风怪回头看了唐小玄一眼，他对唐小玄的话半信半疑，\n“大王，\n黄风怪见虎先锋这么消极怠工，本想催促一下，奈何自己也是被唐小玄的唬弄弄得心中没底，\n望着虎先锋终于带着小妖出去的身影，黄风怪心里总有一种不妙的感觉，他说不清这感觉来自哪里，只是觉得这情形特别诡异。手里端着的酒杯，酒已经洒了出来，黄风怪愣愣地望着神情笃定的唐小玄，心里却在盼望着，唐小玄说的故事一定不要发生！因为一旦发生的话，不知道唐小玄后面讲出来的故事，\n黄风洞外，小妖们一阵喊杀声，虎先锋那震天的虎吼声也清晰地传来，孙悟空和猪八戒的叫骂声、虎先锋的对答，竟然跟唐小玄刚才讲的“\n“黄风怪，贫僧可是要面见如来佛祖的，如来佛祖的法力……不需要我告诉你吧？灵吉菩萨虽然厉害，可也只是佛祖座下的一个菩萨而已，你害怕灵吉菩萨，\n“\n黄风怪转动着眼珠，思索着说道，\n“哈哈，贫僧也就是这么说说而已，\n唐小玄刚说到这里，\n“\n黄风怪的心猛地一抽，金盔上的雉尾一甩，颤抖起来，\n黄风怪气愤之下，\n“\n“\n“大王，虎……\n小妖结结巴巴地好不容易把话说完，\n“\n黄风怪惊讶地瞪起了眼睛，\n“\n“\n黄风怪再次颓然坐倒，\n请续看《西游艳记》"
    },
    {
      "id": "content_53da7f3192c957f199365cef25b5e94d_11",
      "title": "第二集",
      "index": 2,
      "url": "/content_53da7f3192c957f199365cef25b5e94d_11.html",
      "content": "从现代穿越到西游记的唐小玄，这会来到流沙河，"
    },
    {
      "id": "content_53da7f3192c957f199365cef25b5e94d_12",
      "title": "第一章 善良妖怪",
      "index": 3,
      "url": "/content_53da7f3192c957f199365cef25b5e94d_12.html",
      "content": "“好，贫僧就接着讲。话说，孙悟空打死虎先锋之后，黄风怪，\n唐小玄口若悬河，尤其是讲起他熟悉的西游记故事，\n“\n“嗯，当然讲完了，\n“\n黄风怪的心里受到莫大的震撼。自己是黄毛貂鼠成精这件事，眼前这个唐僧肯定不可能知道，可是，他讲起故事的时候，\n沉默了半晌，黄风怪叹息一声。\n黄风怪小心地问道：“圣僧，你既然去西天取经……\n黄风怪惴惴不安地望着唐小玄，\n“\n唐小玄眯起眼睛，\n“\n“\n“\n“贫僧一个出家之人，倒并不需要你黄风大王给我什么便利之处，只是，这金身之事自然是由如来佛祖做主，\n“\n黄风怪连连点头，继续道：“圣僧说得对，\n黄风怪那热切的目光看得唐小玄也觉得心中有些不忍，\n“其实……\n唐小玄沉吟着说道。“\n黄风怪立刻站了起来，\n“\n“\n黄风怪点头哈腰，一副恭谨模样，\n“聪明！如来佛祖有慧眼，你的过去、未来佛祖都知道。如果我跟佛祖说了你的名字之后，他老人家睁开慧眼一看，哟！\n黄风怪受宠若惊，惶恐道：“\n黄风怪这么一会儿由小王变成了小怪，\n“\n唐小玄赞许道：“如果你能够从此行善积德，斋戒布施，如来佛祖赐你金身的可能性就高了许多。啧啧，\n“\n黄风怪也得意地笑了，回应道：“\n黄风怪巴结地涎着脸，\n“\n唐小玄本想吃点肉，\n“\n“呵呵，黄风怪，\n小妖还在犹豫，黄风怪立刻扯着嗓子骂道：“你们浑蛋！圣僧的话也敢不听？\n唐小玄却是脸一沉道：“黄风怪，佛家讲究戒妄言，\n“啊……圣僧教训的是，小怪太不检点了，该打、\n黄风怪立刻惶恐地弓着身子，\n“\n“师父啊，\n猪八戒努力睁大他的小眼睛，\n“\n黄风怪平日里颐指气使、威风八面，怎曾听过这种话？他立刻瞪大眼睛，\n“\n“哼，\n“\n黄风怪低头拱手向猪八戒道歉，态度颇为虔诚，让孙悟空看得愣在当场，眨着火眼金睛，\n“啊……哈哈，黄风怪好可爱，我不会怪你的，\n猪八戒被黄风怪的道歉弄得一时手足无措，想要伸手拉他一下时，又窘迫地收回手。\n“\n“\n黄风怪眼巴巴地望着唐小玄，\n“黄风怪，其实我也觉得跟你挺投缘的……\n唐小玄立刻回绝了，这种事还是不要了，有自己和三个徒弟，就足以笑傲群妖，再加上黄风怪，\n“\n“哎？\n孙悟空的心一软，\n“是啊、是啊，黄风怪，我师父虽然慈悲为怀，\n猪八戒这话虽然说得有些白了，\n“悟空、八戒！你们两个也太不像话了，什么后台、前台的？我答应了黄风怪要在佛祖面前美言几句，\n“师父说得对，\n孙悟空立刻附和道。猪八戒恶狠狠地瞪了孙悟空一眼，\n猪八戒涎着脸，\n唐小玄觉得非常舒服，面前的三个家伙的本事比自己都高得离谱，\n“\n唐小玄转移话题道，老围绕这个话题，\n“啊……\n黄风怪顿时汗如雨下，\n“\n“\n“不说话，\n唐小玄恶狠狠地瞪了猪八戒一眼，\n见猪八戒虽然慑于师父的淫威不敢再说什么，\n三人正在争执间，小妖们来报：“\n“好、\n黄风怪毕恭毕敬地率领众小妖将唐小玄师徒送出八百里黄风岭，临别之前哭着向唐小玄道：“\n黄风怪扑上来抱住了唐小玄的大腿，\n“哎……\n唐小玄连忙用眼色示意孙悟空和猪八戒，赶紧把这个黏乎乎的家伙拉起来，\n孙悟空和猪八戒两人，一个是真正的机灵鬼，另一个则是看似傻乎乎，其实精明无比。两人立刻会意，伸手就把黄风怪拉了起来，劝慰了半天，黄风怪这才依依不舍而去。\n光阴迅速，\n“悟空，\n唐小玄端坐在白龙马上，\n孙悟空早已经拔身在空中，手搭凉篷，用火眼金睛向对岸望了过去，望了半天才跳下来，并来到唐小玄马前道：“师父、师父！这条河好宽、好宽！到对岸足有八百里，上游和下游根本看不到边！\n唐小玄一听，他当然知道无论是什么样的灾难都能够过去，便挑了挑眉毛道：“\n“哎呀，师父，我说的是师父您过不去啊，我老孙只需将腰扭上一扭就过去了，\n“是啊、\n猪八戒摇晃着胖脑袋，\n“哼……\n唐小玄的记性当然不错，他忽然想起，既然是八百里，那应该就是流沙河了！\n“啊？\n猪八戒惊讶道，孙悟空也是睁大一双猴眼，仔细地打量着唐小玄，有些难以置信。孙悟空本来要顺着这条大河巡逻一回，\n“\n“\n悟空这回不得不信了，因为前面黄风怪削尖了脑袋想要当唐小玄的徒弟，唐小玄坚决不允，\n“沙悟净？哈哈，好，既然有我们的师弟，\n猪八戒连日来只负责挑担子，如今肩膀上已经磨出水泡来，他搓着肩膀上的红痕，疼得直咧着他的长嘴，\n“\n孙悟空本就是那种唯恐天下不乱的个性，听得猪八戒的建议，他立刻跳起来，\n“好，你们玩玩倒是可以，\n唐小玄成为唐僧之后，\n“\n沙和尚果然就在水下，感觉流沙河里的水被搅得晃荡起来的时候，沙和尚早就大怒。他抄起禅杖，\n孙悟空悠哉地收了金箍棒，\n他的猴爪一伸，随手一划，\n“\n唐小玄弄好坐垫，\n“嗯嗯，师父，\n孙悟空似乎不大会表达他的看法，他觉得原来迂腐的唐僧越来越开明，可无法表达清楚，\n“悟空，还是你来帮助我练功吧，\n唐小玄笑道。\n“好，师父，\n孙悟空属于那种勤劳而大条的性格，对脾气的人，他就是奉上心肝也在所不惜；不对脾气的，说打就打，\n孙悟空站在唐小玄身侧将功力运起时，唐小玄这才发现，\n“\n唐小玄立刻感受到孙悟空双手上如潮\n“来源 　用。”\n唐小玄这罪可受得大了，孙悟空的功力太强，\n唐小玄极力收敛心神，用道家的功法将孙悟空输送过来的刚猛灵力缓缓转化着。孙悟空倒也不是莽撞之人，\n这种帮助练功的方式如果说是拔苗助长是有些夸张，可也算得上是快速提升了，\n其实孙悟空对于唐小玄的功力提升也是异常热心，他恨不得让唐小玄立刻能够变身为妖仙之流，这样西天取经之路就会轻松简单得多，毕竟带着一个凡人行路，\n“妖怪！俺老猪今天要让你吃我一顿钉钯宴，\n猪八戒扛着钉钯与沙和尚对面而立，两人都飘浮在空中，沙和尚是浮在水柱之上，\n沙和尚赤发黑睛，豹头环眼，\n沙和尚双手握紧他的禅杖，\n猪八戒万分郁闷，\n猪八戒一卷袖子，露出白嫩嫩的胳膊，挺了挺如大锅似圆圆白白的大肚子说：“\n猪八戒奋起功力举起钉钯时，竟然带着轰隆隆的风雷之声，这天蓬元帅自然也不是吃素的，\n“\n沙和尚气冲牛斗，挥杖迎了上来，两人你来我往，叮叮当当，战在一处。顿时流沙河上，\n两人都曾是上界神仙，法力高强，斗在一起的时候直杀得天昏地暗，\n唐小玄入定之后，不知道修炼了多少时日，\n“\n沙和尚挥杖迎击孙悟空的金箍棒时，却不料这金箍棒竟然沉重无比，棒杖相交，沙和尚的双臂差点就瘫了，\n“逃了？\n“\n猪八戒摊摊手，"
    },
    {
      "id": "content_53da7f3192c957f199365cef25b5e94d_13",
      "title": "第二章 凡心大动",
      "index": 4,
      "url": "/content_53da7f3192c957f199365cef25b5e94d_13.html",
      "content": "“\n孙悟空一把揪住猪八戒的一只大耳朵，\n“\n猪八戒一路叫着痛，但来到唐小玄面前的时候却有精神了起来：“师父啊，老猪正要拿住沙师弟的时候，猴哥却横插一棒把沙师弟吓跑了，\n“呵呵，\n“\n孙悟空眨着一双亮亮的火眼金睛，抓耳挠腮道。刚才把沙和尚惊走了，孙悟空也确实有些抱歉，他不好意思道：“好吧，老孙就使一个聚音成线的法术，\n孙悟空念动咒语，果然聚音成线，那声音之线飘飘渺渺、丝丝缕缕地向着流沙河里钻入：“沙悟净，东土大唐取经的和尚到来了，\n“\n又是一道水柱升起，沙和尚小心地握着手中宝杖，道：“\n沙和尚瞪起环眼，打量着孙悟空和猪八戒两人，心中怀疑：\n“\n“孙悟空……猪悟能……\n沙和尚重复着这三个名字，觉得像是观音菩萨取的法名，\n“\n孙悟空立刻想起当时收伏小白龙时的情景，他来到唐小玄身旁，\n“\n沙和尚瞪大了一双环眼，直勾勾地盯着孙悟空手中的通关牒文，浑身积蓄着的力量慢慢放松了下来，手中的宝杖也由高高举着变成向下提着，惊呼道：“\n沙和尚撇了宝杖，一道乌光向着唐小玄而去，“扑通”一声跪倒在地：“\n“\n唐小玄让孙悟空用戒刀为沙和尚剃度，\n猪八戒得意极了，\n孙悟空忙着替沙和尚剃度，没有表示意见，唐小玄当然明白猪八戒的小心眼，\n猪八戒顿时喜得合不拢嘴，见终于把行李担子送了出去，\n“\n孙悟空望着流沙河汹涌的急浪，\n“大师兄，如果说让我沙悟净独自渡河的话，当然简单，可是如果让我带着师父一个凡人我却没辙了。\n沙和尚挑着担子讪讪地说道。\n“\n孙悟空跳跃着来到流沙河边，拾起一根树枝随手扔进流沙河里，只见一个漩涡过去，\n猪八戒说到这里时，\n“什么？等……\n唐小玄点点头，正要说话时，忽然空中一个声音道：“奉菩萨法旨，\n唐小玄得意地瞥了一眼三个徒弟，\n“阿弥陀佛，\n唐小玄端起一副有道高僧的架子，\n“不必多言，\n唐小玄小心地登上法船，坐于上面，果然稳似轻舟。左有八戒扶持，右有悟净捧托，孙悟空在后面牵了龙马半云半雾相跟，\n如飞似箭，不多时，身登彼岸，得脱洪波，又不拖泥带水，幸喜脚干手燥，清净无为，师徒们脚踏实地。那木叉按下祥云收了葫芦，只见那骷髅一解化作九股阴风，寂然不见，沙和尚脖颈间却自然形成一串念珠，\n木叉辞行而去，师徒四人再次上路，\n猪八戒虽然只负责牵马，可他身子肥胖，走路也颇费劲的，\n悟空再次扯住八戒的耳朵，瞪眼道：“呆子，\n“猴哥啊，你只知道你走路轻省，那里管别人会不会累？自过了流沙河，沙师弟爬山过岭，身挑着重担，也是很累啊！\n猪八戒的脑袋果然好用，立刻拉了沙僧来做同盟。“嘻嘻，\n孙悟空放开手向前一指：“\n他催马前行，片刻间就冲进松林中，来到那宅院前。\n孙悟空见那大门敞开着就要进去，唐小玄思量着道：“\n八戒拴了马，斜倚墙根，\n等了好久没人出来，悟空性急，早就按捺不住，跳起身入门内张看。\n唐小玄怕孙悟空闯祸，急急跟上前来，一眼就看到那副对联，唐小玄脑海里忽然一亮，立刻明白了，这个宅院并不是寻常居民的宅院，“开了外挂”\n唐小玄一听这台词，\n“\n唐小玄单手合十，神色恭谨，\n其实他一眼就看到了妇人的模样，只见她穿一件织金官绿伫丝袄，上罩着浅红比甲，系一条结彩鹅黄锦绣裙，穿着高底花鞋。\n“\n妇人发出一阵浪笑，丰腴的身体即使掩在衣衫中，魅力也透衫而出，特别是胸前一对高耸之物更是活泼泼地跳跃着，惹人遐思。“\n这妇人上前一把拉住唐小玄的僧袍衣袖，\n根本连看都不敢看这妇人一眼，可这妇人身上带着的馨香仍然毫无阻滞地侵入唐小玄鼻端，让他觉得心里痒痒的，\n“\n随着三女的齐声答应，\n那妇人将自己的凳子搬得离唐小玄近了些，故意在唐小玄身上挨挨擦擦，娇声道：“我是丁亥年三月初言酉时生。故夫比我年大三岁，我今年四十五岁。大女儿名真真，今年二十岁；次女名爱爱，今年十八岁；三小女名怜怜，今年十六岁，皆不曾许配人家。虽小妇人丑陋，却幸小女皆有几分颜色，女工针织，无所不会。因先夫无子，即把她们当儿子看养，\n这一番话说来，\n“\n八戒半天没听到师父的回答，悄悄一拉唐小玄的衣袖，\n唐小玄摆出一副生气模样，喝斥道：“你这个孽畜！我们是出家人，岂以富贵动心、\n那妇人用胳膊碰了碰唐小玄的胳膊，温腻滑润的感觉让饥渴的唐小玄也不由得心里一荡。那妇人媚眼如丝道：“\n这话简直就是依着西游记的台词说的，\n那妇人故意挺了挺她那波涛汹涌的胸部，娇笑道：“长老请坐，等我把在家人的好处说与你听。怎见得？\n唐小玄低眉垂目道：“女菩萨，你在家人享荣华，受富贵，有吃有穿，儿女团圆，果然是好。\n那妇人听了这话，\n“哎……女菩萨，\n唐小玄被噎得一时不知道说什么好，沉吟了一下，回头向悟空道：“\n孙悟空是何等样人？早就看透这个女子并非寻常女子，因此也立刻推诿道：“\n孙悟空把猪八戒往前一推，\n八戒摇晃着猪脑袋，不好意思地说道：“猴哥啊，不该这么陷害人啊，这事情……\n他一双小眼睛，\n唐小玄察颜观色，哪里还不知道八戒的心事？他却故意说道：“\n“师父！\n沙僧跟了唐小玄，\n那妇人一双美丽的黑眼珠滴溜溜乱转，见他们师徒四人互相推诿，没一个人留下，她忽然抽身就往屏风后走去，把里面的小门关上，\n猪八戒的眼睛直直望着妇人消失的方向，叹息一声，\n八戒的双手一摊，又抚上他那圆鼓鼓的大肚子，\n猪八戒左右张望着，试图找悟空和沙僧帮他说话。悟净果然附和道：“\n其实这话也正好合了八戒的心意，\n孙悟空凑到猪八戒面前，\n猪八戒扭过头去，偷望着悟空和唐小玄，嘟囔道：“话虽然是这样说，可是……我要脱俗再还俗，休妻再娶妻！\n他不自然地望着悟空和唐小玄，\n唐小玄不动声色地望着猪八戒在这里丢丑，\n沙僧惊讶道：“\n悟空插嘴道：“是啊，你还不知他呢，他本是乌斯藏高老庄高太公的女婿。因被老孙降了，他也曾受菩萨戒行，没及奈何，被我捉来做个和尚，所以弃了前妻，投师父往西拜佛。他想是离别得久了，又想起那个勾当，听见这个勾当，断然又有此心。呆子，\n悟空说着话，\n“\n猪八戒故作拼命挣扎着，转身恨恨道：“\n唐小玄心里跟明镜似的，看着猪八戒远去，也不说话。\n沙僧点点头，唐小玄一把拉住悟空道：“\n说着，\n这会儿反正菩萨们不在眼前，\n“哈哈，师父放心，\n猪八戒赶着白龙马出了院门，有草的地方不去，只是向着这院子的后门而去。那妇人正与三个女儿在后院赏菊，远远地望见猪八戒赶着马过来，\n妇人的目光闪烁，\n“\n那妇人露出一脸美黯的娇笑，伸出她柔美的纤手在八戒的手上摩娑着，眼睛里完全是一副丈母娘看女婿的模样：“小长老，你们跟着你那顽固师父实在太委屈了，你那师父也真是的，放着如此好事不做，\n说罢，\n猪八戒立刻慌了手脚，然想要伸手扶住妇人时，还是缩回了手，这事情实在不大方便，八戒说道：“娘，你不知道啊，我师父他们是奉了唐王的旨意要到西天取经的，不敢违命。刚才在大厅上，\n猪八戒这一番表白，\n那妇人端详一下八戒，笑道：“我不会嫌弃长老的，我家中没有一个主事的男人，\n八戒一听有机会，立刻道：“娘啊，你就告诉你女儿，\n“"
    },
    {
      "id": "content_53da7f3192c957f199365cef25b5e94d_14",
      "title": "第三章 三级妖仙",
      "index": 5,
      "url": "/content_53da7f3192c957f199365cef25b5e94d_14.html",
      "content": "八戒想要挺起胸膛，却把鼓胀的大肚子挺了出来，他只好拍扪胸口道：“我老猪虽然长得丑，勤紧有些功。若言千顷地，不用使牛耕。只消一顿钯，布种及时生，没雨能求雨，无风会唤风。房舍若嫌矮，起上二三层。地下不扫扫一扫，阴沟不通通一通。家长里短诸般事，\n八戒说得唾沫横飞，\n“哦……小长老既然能够做得如此家事，这可太好了！\n那妇人笑语嫣然，\n“商量？我跟他们商量什么？他们又不是我的父母亲戚，\n“哦？小长老既然如此说可太好了！那我就与女儿们商量商量，\n妇人转身关上后院的门，猪八戒知道事情有望，顿时大喜，\n悟空将这一切听了个清清楚楚，他立刻飞回前厅，\n“哦？\n“哈哈，\n悟空顿时笑得直打跌，\n“\n唐小玄兴致勃勃地听完那对话，\n八戒来到前厅，将马拴了，来到唐小玄面前，唐小玄望着他缩头缩脑的样子道：“八戒，\n悟空刚要说话，唐小玄连忙用眼色止住，\n“既然无处放马，\n唐小玄说完又闭上眼睛，\n过不多时，忽然吱呀一声，\n那三个女子排立厅中，朝上礼拜。果然也生得标致，一个个蛾眉横翠，粉面生春，妖娆倾国色，窈窕动人心，花钿显现多娇态，绣带飘摇迥绝尘。半含笑处樱桃绽，缓步行时兰麝喷。\n唐小玄继续合掌低头，孙大圣佯佯不睬，沙僧转背回身，只有猪八戒目不转睛，淫心紊乱，色胆纵横，悄语低声道：“\n那妇人笑盈盈地说道：“\n“啊……兄弟，你不要逗哥哥我了，\n悟空早就忍耐不住，立刻跳了起来道：“还计议什么？你在后门处早就说合妥当，\n八戒故作推诿道：“不行、\n唐小玄忍着笑，\n悟空笑道：“呆子，\n他一只手揪着八戒，一只手扯住妇人道：“亲家母，\n猪八戒初时只是故作矜持，\n一壁厢又吩咐庖丁排筵设宴，\n那八戒跟着丈母行入里面，\n猪八戒道：“娘，\n那妇人道：“\n八戒道：“\n磕磕撞撞，转弯抹角，\n那妇人道：“女婿，你师兄说今朝是天恩上吉日，就把你招进来了。却只是仓卒间，不曾请得个阴阳，\n八戒道：“娘说得是，你请上坐，等我也拜几拜，既当拜堂，又当谢亲，\n那妇人娇笑道：“\n满堂中银烛辉煌，猪八戒朝上礼拜，\n那妇人受礼完毕，笑道：“正是这些疑难。我要把大女儿配你，\n八戒犹豫了一下，\n那妇人立刻沉下了脸，\n八戒依言接了那方大红手帕，顶在头上，顿时闻到了手帕上的馨香，心中更是奇痒难搔，\n那妇人叫：“\n只听得环佩响亮，兰麝馨香，\n那妇人帮他揭了盖头道：“乖女婿，不是我女儿乖滑，\n那妇人道：“好女婿呀！这等没大没小，连丈母娘也都要了！\n八戒此时已经被四菩萨的脂粉阵迷得晕了头，闻言道：“好！好！好！\n那妇人转进房里，只取出一件递给八戒。猪八戒便脱下青锦布直裰，取过衫就穿在身上，还未系上带子，就跌倒在地，原来是几条绳将他肥胖的身子紧紧绑住了，令他顿时疼痛难忍，惨叫连声，\n唐小玄、\n唐小玄昨晚睡得踏实，此时睁开眼睛，抬头观看，哪里有什么大厦高堂，也没有了雕梁画栋，一个个都睡在松柏林中。唐小玄连忙叫醒二人，沙僧瞪大环眼，\n孙大圣心中明白，微微地笑道：“\n“大师兄，\n沙僧惊疑道。“\n孙悟空笑道：“\n“\n沙僧忽然敲敲脑门，\n“沙师弟，你明白了吧？昨晚其实是菩萨幻化成四个女人，故意显灵点化我们的，哈哈，\n孙悟空大笑，\n“呵呵，\n“\n唐小玄顺着悟空手指的方向望了过去，只见那后边古柏树上，飘飘荡荡的挂着一张简帖。沙僧急去取来给师父看时，却是八句颂子云：“\n三人正研究这张简帖时，\n唐小玄当然听得出来这是八戒在喊叫，他连忙吩咐孙悟空道：“悟空，\n“\n猪八戒叹息一声，\n“色字头上一把刀，\n“什么？\n猪八戒将脑袋向地下钻去，\n“\n“\n猪八戒穿好了衣服，\n沙僧挑着担子，见八戒落成如此狼狈的模样，凑过来笑道：“二师兄，\n唐小玄觉得有点晕，\n唐小玄用马鞭猛敲一下沙僧的头，喝斥道：“\n唐小玄觉得敲这一下的感觉超好，沙和尚的本事，自己就是有一百个唐小玄绑起来也不是人家的对手，\n八戒听得沙僧道歉，顿时挺起胸膛……不，应该说是挺起他的大肚子，牵着白龙马，昂然而行，一路高歌：“\n唱的居然是闽南味的十八摸！\n“师父，\n悟空一直在唐小玄身边飞来飞去，抬眼看时，\n“啊？\n唐小玄忽然想起他学过的定身法，立刻念动咒语，向那只鹿一指。\n“哈哈，师父，\n“哈哈，悟空，快去抓住，\n“\n沙僧一时有些转不过弯来，\n猪八戒的脑子转得相当快，立刻大声道：“好，\n说着，\n“猴哥，\n猪八戒别看眼睛小，这种事情上立刻就反应过来，他拉过孙悟空，\n孙悟空总是笑容满面，听得八戒如此说，当然乐得省事。孙悟空接过马缰，\n“啊？真的啊，\n“二师兄，不要发愣了，\n沙僧碰了碰猪八戒的胳膊，开始操刀宰杀这头鹿，八戒也连忙上前帮忙，忙了半天，\n沙僧和八戒都吃惯了肉食，当然并不排斥这东西，可他们一路上看唐小玄吃的总是斋饭，\n“二师兄，要吃肉也要师父先吃才行啊，\n“\n猪八戒的脑海里浮现出唐小玄手里抓着两块大大的鹿骨头，\n又等了一会儿，鹿肉总算是煮熟了。猪八戒和沙僧自从皈依佛门，还真就没吃过一次肉，早馋得受不了了，他们立刻窜出时间结界，跑到唐小玄高卧着的大树下，\n“\n唐小玄一看猪八戒满脸灰土的模样，不由得露出微笑，被他拉得踉踉跄跄，\n他殷勤万分地用一根干净的木棍叉起一块足有三、四两重的鹿肉，\n“\n三人里，只有孙悟空见过唐小玄吃肉，另外两人对于唐小玄吃肉时的情景根本无法想象。此时见唐小玄手里树枝上叉着那块热气腾腾的鹿肉，两人都张大嘴巴，一副羡慕模样，\n“\n唐小玄感叹一声，其实他心中何尝不知道八戒和沙僧的那点小心眼？唐小玄将那块鹿肉送到嘴边，吹了口气，一口咬了下去。“\n唐小玄敏感地听到两声吐出长气的声音，他眼睛一斜，就知道是八戒和沙僧这两人，\n既然唐小玄咬了第一口，八戒和沙僧两人哪里还会客气？\n“去！坐到一边，\n孙悟空两手一展，\n悟空先递给唐小玄一块肉，这才叉了两块肉，一蹦就来到八戒和沙僧面前，火眼金睛滴溜溜转动着，见两人伸手要接，孙悟空却将手中的鹿肉猛然往上一举，\n“\n“大师兄，\n“好，\n孙悟空收起金箍棒，来到唐小玄面前，将手一伸，锅里就飞起一块鹿肉，同时另有一根树枝也飞了过来，\n唐小玄对于孙悟空相当放心，别看孙悟空表面上好动活泼，\n唐小玄对孙悟空一竖大拇指：“悟空，你考虑得很周到，\n“\n孙悟空快活地吃着鹿肉，\n孙悟空快活地对唐小玄眨眨眼睛，唐小玄续道：“酒肉穿肠过，佛祖心中留……\n“是啊、是啊，\n“\n唐小玄威严地扫视一眼，见八戒与沙僧都点头，顿时觉得意气风发，忽然打了一个饱嗝，肚子里泛上来的味道正是那鹿肉的美味。唐小玄苦笑道：“\n坐在石头上，\n“\n猪八戒一连吃了七、八块鹿肉，至少也吃了六、七斤了，可还是没饱，又到锅里去捞，结果捞了半天，里面已经一块也没有了。他失望地撇撇嘴，叹息一声，摸着肚子道：“肚子啊肚子，好不容易有肉吃，却无法将你喂饱，\n刚说到这里，忽然意识到不对，连忙煞住话头，四下里望了望，悟空正靠在一块石头上睡觉，\n唐小玄进入了舒畅无比的功态中，只觉得四周灵气正慢慢加快速度向着他身体里面涌去。经过孙悟空长期改造，唐小玄这副身体已经相当强悍，\n聚集成实质般的灵力，在唐小玄的身体内缓缓流动着，越聚越多，\n唐小玄感受最深的是下丹田处存储着的那颗金丹。当时悟空让他吃了金丹之后，由于无法完全吸收金丹中内含的能量，唐小玄只吸收了其中一部分，其余则是由孙悟空强行帮他存储在下丹田中。\n唐小玄觉得可以“看”\n孙悟空已经跑了过来，不敢打扰唐小玄此时的变化，\n“\n孙悟空得意道：“\n“\n他们三人都是高级妖仙，对于这种程度的修炼当然熟悉，看到唐小玄如今的变化，"
    },
    {
      "id": "content_53da7f3192c957f199365cef25b5e94d_24",
      "title": "第四章 御弟哥哥",
      "index": 6,
      "url": "/content_53da7f3192c957f199365cef25b5e94d_24.html",
      "content": "唐小玄舔了舔自己已经略微干燥的嘴唇，道：“我想，\n说着话，\n她的嘴唇已经要贴近唐小玄的下颔了，\n唐小玄强自镇定下来，可是声音已经不稳了：“公主，\n他明明知道百花羞要做什么，\n刚才还是圣僧，\n唐小玄最擅长从女人的口中获知女人心中的想法，\n“\n百花羞不再言语，\n在佛门之中，\n本来唐僧是个肉体凡胎，只会诵经念文，根本不运动。可是唐小玄不一样，\n百花羞一直长困洞中，见到的男人非妖即怪，哪里见过什么真男人？今天看到雄健的唐小玄，双眼带色、\n她本来就对唐小玄心有所属，当下更是难以抑制心中的情欲，双手在唐小玄的胸膛上乱摸，\n可是他依旧没有出手，\n唐小玄不停呼出长长的气，\n唐小玄依旧不闻不问，任由百花羞如此纠缠。百花羞的淫欲大起，一只手在唐小玄的身上到处乱摸，另外一只手伸过来牵住唐小玄的手，\n唐小玄是个经验老道的色狼，\n他用指甲在她的乳头上轻轻刮弄着，百花羞的情绪激荡，已经全然不顾自己的公主形象。\n“\n唐小玄笑了笑，道：“\n“捏、\n可是唐小玄就要她自己说出来，依旧问道：“\n“\n唐小玄的手忽然用力，双手齐出，\n手跟乳房相互安抚，\n唐小玄看到自己的手掌与百花羞的乳房间迸发出一种乳白色的汁液，\n在唐小玄的揉捏之下，她的乳房膨大得连唐小玄的手都无法握住，唐小玄当下心中也是性欲高涨，\n他的嘴巴在她的另外一只乳房上撕咬着，好象恨不得将她的乳房整个咬下来。“用力……\n百花羞此时再也没有羞耻之心，\n唐小玄一边在用力搓揉，\n百花羞做娇羞之状，道：“御弟哥哥，\n她从小到大，几乎没有见过男人的阴茎长什么样子，\n百花羞将唐小玄的裤子脱下，\n百花羞看着唐小玄胯下的男根已经雄壮而起，犹如一条神龙般，\n百花羞虽然不知这是何物，但光看就令自己垂涎欲滴了，在唐小玄的引诱之下，她将红唇凑过去，\n嘴中一片湿黏，又是一片温热，百花羞一下子将唐小玄的男根齐根含入，\n“快活吗？\n百花羞在吞吐之时，\n唐小玄吐纳自如，\n百花羞的香舌灵巧，一边吞吐，\n这个女人的“吸精大法”居然非常有效，果然是个天生的荡妇淫娃。唐小玄在她非常灵动的口交之下，\n百花羞乐在其中，嘴上功夫还没有停下来，\n百花羞还不解其意，\n唐小玄摇头，道：“床上不好，\n其实他只是想找个借口，\n百花羞信以为真，就在地上躺了下来，唐小玄急不可耐，连忙以“69”\n而唐小玄则用手扒开她那紧紧闭合的小穴，\n在唐小玄三两下的抚摸之后，百花羞的阴蒂已经微微凸起，\n再舔，\n唐小玄忙道：“\n话语间，他的食指也滑了进去，里面是一片湿漉漉的软肉，\n“\n百花羞的声音已经越来越大，再也禁不住自己身体内性欲的袭击，大声呼喊出来，本来被她含在嘴里的唐小玄的阴茎也滑了出来，\n“\n唐小玄的双指已经探入百花羞的玉穴深处，\n他的手指很快地摸到洞穴上一颗肉球，\n唐小玄的手指在这个肉球上不断抚弄着，不断搓动着，\n这是女人身上最为敏感的地方，懂得这种事的男人都将此处称作女人的“\n这一点对于处女来说自然是更加致命。百花羞的身子不断拱动着，将唐小玄的身体托上托下，满身的汗水将她的身子全都浸透了，她的头发在她的呻吟声中盖住了脸，\n“御弟哥哥……\n百花羞的脸色已经由红润变成苍白，看来快要高潮了。唐小玄的经验很足，也已经看出高潮前的征兆，一下子将百花羞的两腿分开，\n唐小玄手上移动的速度更快了，蜜穴中发出“噗哧噗哧”的声响。\n可是唐小玄却全无顾忌，\n百花羞整个人感觉都快休克了，大声呼救：“御弟哥哥，\n唐小玄知道她想表达的意思是“我要高潮了”可是她不知道怎么形容这种感觉。在这种时候高潮，\n“哥哥，\n她的话还未说完，\n百花羞的身体抽搐两下，顿时恢复平静，口中粗气直喘，柔声道：“御弟哥哥，你……\n唐小玄虽然还没有射精、还没有达到高潮，不过他没有继续在此间沉沦下去，从她的身上坐起来，坐在她那两只肥硕的大奶子上，\n“哥哥，\n百花羞的双目被她的秀发遮住，只留了一张润泽的红唇在外面，\n唐小玄用自己的阴茎在百花羞的奶子上面搓了两下，将龟头上遗留的一点精液擦拭干净，才道：“公主妹妹，\n他早就知道自己的衣服被放在哪里、那颗内丹舍利放在哪里，于是在口袋里面摸索片刻之后，那颗内丹就出现在他的手中，他将内丹拿着放在她的红唇之上，轻声道：“公主妹妹，\n百花羞默然不语，听话地将这颗内丹含进嘴里，用自己的唾液将这颗内丹浸润一遍，然后朱唇轻启，道：“\n唐小玄看着她那红如蜜桃的双唇，\n他本来想将整个内丹吃下去，只留一点口水让百花羞吃，但是转念一想，自己现在不过是个三级小仙，修为还大大不足，这颗内丹舍利是历经千锤百炼而成，\n百花羞吞下之后，才将自己遮住眼睛的头发分开，\n唐小玄眼下还骑在百花羞的身上，不知百花羞要说什么，只道：“\n百花羞抿了抿自己的嘴唇，\n还要？真是一个骚性奇强的女人，看起来好似本本分分、纤尘不染，实则天生奇骚，不过唐小玄可不愿意让她轻易地满足，只道：“\n唐小玄如今已经在百花羞的面前露出真身，也不必拘泥，\n两人一番云雨之后，各自穿上衣服，唐小玄敛了敛衣角，\n百花羞想了想，道：“\n唐小玄知道这是内丹起了作用，\n“\n唐小玄眼珠子转了转，\n可是为了不让白骨精看到自己跟百花羞的关系，以免两人心生不合，于是越过二层，\n推开四层的门，里面依旧是雾蒙蒙状态，没有一点浑沌初开的迹象。而百花羞更是看得纳罕，道：“御弟哥哥，这是什么地方，怎么迷蒙的一片，\n“你先在此稍息片刻，\n说罢，唐小玄盘膝而坐，双掌上下相叠，双目阖起，\n上一次，\n唐小玄登时神清气爽，感觉一下子精神大振，张开嘴长长地吐出一口浊气，那浊气奇臭无比，一旁的百花羞闻到连忙用自己的手扇了扇，\n唐小玄现在感觉自己的境界又有了质的变化，顿觉欣喜异常，也顾不得一边百花羞的反应。但见他双掌平放相抵，缓缓地左右拉开，\n随着唐小玄意念的转动，这个本来浑沌未明的第四层一下子就现出一道光亮，光亮慢慢将浑沌的雾气驱散，\n只不过这空间是原始状态，没有任何一物点缀，唐小玄再次心念闪动，很快地就出现一条大川，一带银河，水中倒映星光。\n这正是破晓之境，让人看了犹如坠入梦中，\n“\n可正当她这句话说完，\n唐小玄体内的浊气刚才从口中吐了出来，\n唐小玄嗅了嗅鼻子，伸出手来，隔着薄纱在百花羞的菊花上用食指捅了捅，\n唐小玄将百花羞一把抱起来，\n只是，\n唐小玄还没有来得及回答，八戒就抢着道：“\n悟空立刻喝止了，道：“呆子，你休要乱说，\n当然，这句话八戒也不过是在心里说说而已，可不敢说出口，\n唐小玄见三位爱徒都对此感到不解，\n悟空跟唐小玄虽然不算是一路货色，但是大同小异，只要好好地指导就可以，而八戒虽然有时候也会有脾气、有情绪，但是只消给他一点甜头，\n事情解释完之后，大家也都心安了，只不过八戒却一夜无眠，因为这位宝象国公主实在长得貌比天仙、秀外慧中，\n自从因为调戏嫦娥被贬下界之后，八戒除了那个高老庄的小女儿之外，\n可是八戒虽然形态是猪，但却并非真的是猪，也是个完整的男人，有着男人的情欲，看到这么漂亮的公主哪里能够克制得住。\n好漫长的一夜。一夜过去之后，八戒本来就很大的眼眶上更是加上一层厚厚的黑眼圈，唐小玄虽然知道这是什么原因造成，\n八戒不敢说出实情，只是偷偷望了一眼坐在唐小玄身前的百花羞，道：“没事，\n唐小玄立刻道：“哦哦，\n数日之后，师徒四众行到一处山脚之下，面前有一个水塘，水塘正好挡住去路，按说河也不宽，怎么会没有桥呢？而放眼望去也不见一人，走了这么几日之后，已经快到宝象国了，\n语毕个翻身就跳到一棵大树之上，"
    },
    {
      "id": "content_53da7f3192c957f199365cef25b5e94d_25",
      "title": "第五章 烫手山芋",
      "index": 7,
      "url": "/content_53da7f3192c957f199365cef25b5e94d_25.html",
      "content": "看到孙悟空这么紧张，八戒跟沙僧都戒备起来，纷纷拿起自己的武器挡在唐小玄的面前，危难关头，\n百花羞吓得要命，搂住唐小玄的腰，\n过了许久，在树上查看情势的孙悟空才从树上一跃而下，叹了一口气，\n悟空斥道：“\n猪八戒经常被悟空欺负，现在自己找到话头，\n悟空抓了抓自己的猴腮，沉吟着道：“\n猪八戒见状，赶紧在唐小玄的面前告状，道：“师父，你看大师兄就知道吓唬我们自己人，\n这个时候就是唐小玄发言的时候了，在西游记中，路经此处似乎确实没有妖怪，\n悟空一听到紧箍咒三个字，\n悟空虽然不拘一格，不拘泥于世俗，但却是个识大体的人，听唐小玄如此一说，就停下手，\n他顿了顿话音，道：“\n唐小玄听到“\n悟空道：“\n唐小玄本来想说“据你目测那妖怪法力如何，\n悟空一拂手，道：“据我所看，不过尔尔，只要能找到她，\n这句话说完的时候，八戒已经钻进了树丛之中，\n唐小玄故作正色，道：“没事的，\n八戒走后，三人加上公主等了片刻，见八戒迟迟未归，\n莫非那八戒真的被那妖精的美色所迷，中了妖精的奸计，\n要真是这样可就糟了，师徒四人共同完成取经大业，\n于是乎，唐小玄命悟空去看个究竟：“悟空，八戒去了老半天，\n他又嘱咐沙僧道：“\n沙僧还没来得及说“好”只听见树丛中传来了一阵“喀拉喀拉”\n听到这个声音，悟空就笑了起来，\n原来这“喀拉喀拉”的声音正是猪八戒的钉耙在地上拖动的声音。果不其然，\n八戒一脸土色，满面灰尘。\n悟空见八戒灰头土脸，上下乱蹦，哈哈大笑道：“八戒，我当你去了多时未回，\n八戒将钉耙跟狐狸一撒手丢在地上，道：“\n唐小玄一听，满面笑靥展开，道：“八戒可真是识得大体，\n八戒听到唐小玄夸奖自己，心花怒放，道：“师父，\n这一次他没有在狐狸精的身上寻到快活，只好对着百花羞抛了个媚眼，道：“公主，\n百花羞虽然在那奎木狼的洞中待了十三年，见过各式各样的妖怪，可还真没有看到过八戒这种相貌奇丑的，只是怯怯地看着八戒，\n八戒见百花羞这种貌美女人都承认自己是个能干的人，连忙用手指挖了挖自己的大鼻孔，\n距离这道路三、五里开外果然有一条用木头搭成的独木桥，\n唐小玄还没有来得及搀扶百花羞，八戒就连忙过来献殷勤，扶起百花羞的胳膊肘，道：“公主，就让老猪我扶你过河吧，\n百花羞这么近地看到八戒的长鼻大耳，一阵恶心，\n沙僧也笑了起来，道：“\n八戒撇了撇嘴，\n唐小玄是这个小团队的领导，他必须要将每个人都处理好，\n于是唐小玄偷偷地按了按百花羞的手，\n听到这句话，八戒一下子来了劲，看了一眼悟空跟沙僧，\n他又猥琐地对着百花羞笑了笑，道：“公主，师父说得对，\n百花羞虽然一万个不愿意，但现在已经是唐小玄的人了，被唐小玄完全征服，只好听唐小玄的话，\n过了这座桥之后，距离前面的宝象国就不远了，宝象国的宫殿轮廓已经在望，几个人加快脚程，\n这宝象国虽然是个小国，\n其实他自然并不是真的在欣赏美景，\n唐小玄心想，倘若自己真的在这宝象国之中跟百花羞结成夫妻，\n可无奈自己是个出家之人，不能沾染荤腥，看着大块的肉食，\n幸好，这边的素食也是相当丰富，\n等到酒宴将歇之时，国王深感其恩，对唐小玄道：“圣僧，\n国王道：“哦？什么东西，你不妨说出来，只要我有的，\n八戒嗅了嗅鼻子，环视一周，但见这宫廷之上，一片琳琅满目、玉雕金琢，极尽奢华，于是八戒狮子大开口地道：“\n国王先是动容，然后接着面色和善地道：“\n唐小玄立刻阻止国王，\n他指了指八戒，道：“\n八戒见师父这么一说，觉得很是沮丧，\n国王经唐小玄这么一说，也是幽幽一笑，道：“\n他双掌相合，道：“\n唐小玄急忙还礼，\n正在此时，忽然大殿左侧屏风后面传来了一阵嘻笑之声，\n唐小玄侧目而望，发现在屏风之后躲藏着三两个女子，\n唐小玄一看就猜测是宫中其他公主，\n国王见状，解释道，“这几个丫头乃是百花姑娘的姐妹，长年待在宫中，没有见过什么世面，\n“不打紧的，国王果然好福气，\n国王将自己手边的金杯端起来，道：“这最后一杯酒，就由朕敬圣僧，希望圣僧明早上路，\n其实唐小玄很想喝几口这宝象国中特有的美酒，\n这茶虽然不太苦，但是喝在嘴中却没有什么味道，唐小玄是闭着眼睛、\n国王早就看出百花羞眼中对于唐小玄的爱慕之情，\n这话说起来好象是自己招待不周似地，\n国王从自己那非常奢丽的椅子上面站了起来，道：“诸位带着小女赶了两百余里路来敝国，想必已经累了，\n唐小玄道，“陛下不必亲为，\n国王知道百花羞跟自己有很多话说，\n虽然说自己女儿的贞洁之身给了一个和尚，但这和尚毕竟一表人才、相貌堂堂，\n唐小玄一行人还是跟往常一样，住在一个屋子里，屋子中金碧辉煌、\n最受不了这种氛围的是沙僧。\n“师父，\n沙僧建议道，\n唐小玄能够了解沙僧的心思，\n沙僧应了一句，就急匆匆地走了出去。八戒此时已经在床上躺了下来，\n悟空在一边替唐小玄铺好了床之后，就要唐小玄上床休息，唐小玄却道：“\n虽然说自己对百花羞也有一点情意，也对此间繁华有些贪恋，不过若是在这个地方停下脚那可不行，天上还有个如来佛祖看着呢！\n算了，还是去困妖神塔之中看看吧。一念至此，他就转过头看了一眼悟空，悟空已经在床上躺下来休息，看样子也已经睡着了，\n看来只好自己布置时间结界了。\n他的意识渐渐地遁入虚空之中，来到困妖神塔里。困妖神塔之中如今还关着一个白骨精，白骨精的功力从理论上来说，比自己精深很多。如今白骨精已经是自己的胯下之臣，\n想到这，\n八戒在床上虽然一直躺着，可是并没有睡着，见周身没有什么动静，就慢慢从床上爬了起来，对着唐小玄唤了一声“师父”见唐小玄没有应声，又叫了声“师父”依旧没有回音，\n八戒再转过首去看了看悟空，\n他一走出屋子，就驾起了一朵白云，腾云直上，来到月宫之中，不过这一次可不是来调戏嫦娥，上一次因为猥亵嫦娥，自己已经落得这般模样，就算是死，\n只好去问嫦娥了，\n“\n八戒慌忙解释道：“你千万不要误会，\n嫦娥不解，道：“\n八戒沉吟半晌，道：“\n嫦娥的眉黛轻蹙，\n他好象怕嫦娥误会，又接着道：“我只是跟他借点东西，\n嫦娥一收衣袖，\n八戒用自己粗糙的大手抓了抓鼻子，\n这句话说完，见嫦娥不再理会自己，\n“月老就在广寒宫之北，\n八戒双手拱起，\n说着话，\n等到八戒走后，嫦娥也摇首叹息道：“\n八戒走出来之后，\n虽然他本性好色，对各种漂亮的女子有染指之心，可是自己心中最爱、最思念的依旧是那个一衣带雪、纤尘不染、\n正在八戒最为惆怅之时，月老的宫殿已经出现在视野中，八戒纵身跳下去，落地稳住身形，\n月老正忙着帮地上那些眷侣情人搭配红线呢！八戒走了进来，\n“老头，\n听到背后有人这么一吼，月老一惊，差点将手中的红线搭错了，转过身来一顿足，本来想发火，一看是八戒，就转怒为喜，道：“\n八戒摸了摸自己的长耳朵，嘟囔着道：“我跟随那唐僧取经，闲着无聊，\n月老将手中的红线放下，\n八戒舔了舔嘴巴，左右看了两眼，道：“\n八戒直直地道：“\n月老直摇头，道：“\n八戒冷笑道：“\n月老只是一个司掌姻缘的小神，论法力远在八戒之下，知道若是八戒硬来的话，\n八戒被月老这么一说，\n月老追问道：“"
    },
    {
      "id": "content_53da7f3192c957f199365cef25b5e94d_26",
      "title": "第六章 八戒色女",
      "index": 8,
      "url": "/content_53da7f3192c957f199365cef25b5e94d_26.html",
      "content": "八戒有点不耐烦了，\n月老知道自己拗不过八戒，只好叹了一口气，道：“天蓬元帅，我今日给你丹药，可是倘若你做了什么苟且之事，东窗事发，\n八戒催促道：“是了是了，你拿来便是，出了什么事，自然由我担当。\n听到八戒这么一说，\n八戒的眼睛发出亮光，一把将瓶子夺了过来，将瓶底朝天，准备倒出来一大把丹药。可是倒了半天也只不过倒出一粒思情丹，撇了撇嘴，道：“\n月老只希望这猪八戒快走，\n八戒伸出手在月老的肩膀上拍了两下，悠悠地道：“月老，\n八戒一个腾身就从宫中跃了出去，\n月老看了看自己怀中的瓷瓶，\n八戒推开门，看悟空跟唐小玄都还没有醒过来，偷偷地笑了笑，\n八戒还不知其然，只得左右环视一周，很快地锣声更近，等了片刻，\n这黄裳人不是别人，\n八戒见国王来了，\n八戒一想，师父正在房中念经，\n国王道：“\n八戒推动唐小玄身子的时候，唐小玄只觉得有一种感应传到心中，不由得内心一震。以前外面有任何的变化，\n“\n白骨精风骚成性，刚将自己身上的衣物除去，赤身裸体地站在唐小玄面前，像个黏虫一样地黏着唐小玄，道：“圣僧哥哥，\n唐小玄虽然也想跟白骨精缠绵一番，不过正事要紧，\n“\n唐小玄将话说得很直，\n白骨精本来就是一个天生的骚女，话说得再直，\n“那你可要快点噢，\n白骨精却不感其痛，反而讪讪地道：“哎哟，你好坏，哥哥，\n唐小玄内心的感应越发强烈起来，知道不能再耽误，连忙将白骨精推开，道：“\n八戒急急地道：“\n唐小玄连忙敛了敛衣服，\n“深夜造访，\n“\n国王道：“敝国有个陋俗，\n唐小玄早就知道这个国王并不是请吃宵夜，\n国王微微侧首，\n“悟空、八戒，你们先去吧，\n这领路的亲卫笑而不语，过了片刻，\n听到“佳人”二字，八戒登时喜上眉梢，追问道：“\n八戒喜不自禁，道：“\n这话说出来，\n悟空在一边听着只是暗笑。这个呆子明明心潮澎湃，偏偏还要装出一副虔佛之态。而至于悟空，对于什么佳人丝毫不来电，\n“圣僧，\n国王想了半天，\n“\n国王长长地吸了口气，道：“圣僧与小女之间的事情，朕已听小女说过。\n唐小玄故作沉吟，道：“既然陛下你已知道其中详情，那你也该知道，\n从感性的角度来说，能够成为宝象国的驸马那是何等的风光，可是自己偏偏跟唐僧合体，唐僧是圣僧，是取西经的领头羊，\n虽然荣华富贵令人垂涎，\n更何况，\n在这里当个驸马，那自己的逍遥路也算是走到尽头，权衡之下，\n但是听到唐小玄如此一说，国王就有点怨了，双眉连线，道：“圣僧虽然是力求救人，但是男女之事亦不能当假，\n“\n吃了鱼，\n“如此甚好，圣僧稍候，\n这句话，\n唐小玄可不愿意跟这个国王闹翻，\n这下好了，干了一个百花羞，\n听竹轩坐落在一片竹林之中，\n听竹轩之中传来丝竹之声，\n八戒心生向往，从林边到听竹轩基本上是一路飘过去，可是悟空却觉得这音律乃是靡靡之音，\n到了近处，\n这亭轩之中除了这两个弄琴拔丝的女子之外，\n两个公主见到八戒虔诚的样子，\n八戒“啊”了两声，就在一张石凳上坐了下来。而亭轩外的悟空看亭轩内的腐朽气息，只是摇着自己的猴头，道：“八戒，\n悟空并不喜欢这种氛围，\n倒是八戒早就想将悟空支开了，所以连连道：“好的，猴哥，\n等到悟空走后，\n他口中虽说的是“\n“师父，你对我这位宝贝妹妹如此说话，\n八戒虽然色心大起，但是嘴上还不敢有所表露，连忙解释道，“\n回答八戒的还是这位红公主，\n八戒拊掌赞道：“好名字、\n八戒这下哑然了，他不像唐小玄满腹文采，\n听到这话，\n笑声方罢，这位一直缄默无言的青绿终于开口了，问道：“\n说起自己的来历跟身世，那八戒昂首拍胸，\n“哦？\n“那可不是吹牛皮的，虽然我因为……\n“那你有什么本事？\n青绿一边说话，\n八戒左右前后看了看，\n青绿用玉手敲击着下颌，道：“\n八戒虽然下界为猪妖，\n青绿嘟着嘴，道：“嗯……我听说天上有专门看管打雷闪电的，有专门看管刮风下雨的，我一直都想看看雷神长什么样，你不如让他现身，\n八戒大喝一声，\n八戒的法力纵然不比悟空，但是在天上也是可以排上名的，他也懂得千里传音之法，他用手附在嘴巴周围，\n其实八戒在被打落凡间之前虽然很好色，却跟其他的天神处得不错，人际关系相当好。雷震子听到八戒这么一召唤，\n“\n“也没有什么要紧的事，只是下凡多年未曾蒙面，\n“天蓬元帅，听说你与那去西天的和尚一道取经，\n雷震子之所以肯出面，不仅是因为八戒曾是昔日的天蓬元帅，\n看得这赤红跟青绿真是瞠目结舌，\n这一盏茶的工夫，\n“\n两人抢着道：“\n“好，\n八戒又问道：“\n“想，\n哪个凡人不想成为天上的神仙呢？虽然神仙也有神仙的苦，可是这却是凡人所无法看到的，凡人看到的只是神仙的法术、\n八戒的眼睛从这赤红和青绿两人身上扫过，\n赤红跟青绿两人听到这话，对望一眼，\n八戒悠悠地道：“我当年下界之时，从天上带来很多的丹药与法宝，这其中就有一、两样可助你们成神，\n这话将这两位公主哄得满脸红光，\n“\n八戒看着两人因为兴奋而起伏不定的酥胸，忍不住吞下一口口水，道：“\n其实八戒哪有什么成神的狗屁丹药，\n丹药只有一粒，这却有两位美人，\n八戒沉思片刻之后，想到一个好法子，就道：“不过丹药只有一粒，可是这丹药乃天赐之物，药性极强，我将它一分为二，你们每人吞服下其中的一半，\n两人不假多想，\n过了片刻，\n“\n两人感觉吃完之后没有丝毫变化，\n八戒一下子也慌了神，只有扯谎，道：“你们暂且不要着急，这药力的发挥需要时间，\n再说唐小玄也在等，\n听到父皇跟自己说唐小玄想要见自己，百花羞自然万分幸喜，在铜镜前面精心打扮一番之后，\n唐小玄一见到百花羞，\n“\n百花羞轻启朱唇，\n唐小玄咽下一口口水道：“也没什么，只是思念成切，\n唐小玄当然想要，自己裤裆里的那根神龙已经翘得相当难受，不过自己可不敢随意乱说话，虽然周遭无人，但是天上还有神仙，\n“\n进了困妖神塔，那就是唐小玄的天下了，上一次跟百花羞苟合，\n他觉得自己龟头上已经有点黏黏的了，\n一进来困妖神塔，\n“御弟哥哥，我等不及了，你……\n唐小玄将自己的肉棒掏出来，一只手举着肉棒，另外一只手按住百花羞的头发，道：“\n虽然百花羞还不知道什么是“\n唐小玄最喜欢百花羞的口交了，\n百花羞不停吞吐着，速度越来越快，\n他伸出手来，\n百花羞一副意犹未尽的样子，红润的脸上充满淫欲，讷讷地道：“"
    },
    {
      "id": "content_53da7f3192c957f199365cef25b5e94d_27",
      "title": "第七章 遇见嫦娥",
      "index": 9,
      "url": "/content_53da7f3192c957f199365cef25b5e94d_27.html",
      "content": "唐小玄用肉棒在她的左右脸颊上抽了两下，道：“来，\n百花羞虽然以前没有做过这种事情，但似乎有这方面的奇才。\n蛋蛋并不是男人特别敏感的地方，但是让一个女人吸食自己的蛋蛋，\n百花羞真是个性欲旺盛的女人，\n那奶子在百花羞身体强烈的抖动之下，一上一下地撞击着，发出“\n唐小玄的腰部前后用力，稍稍地弯下身来，用双手捏着两只奶子上的乳头，\n唐小玄低眉看着百花羞那一脸淫荡的样子，忽然放下手来，奶子弹了回去，撞在肌肤上，发出沉闷的“啪”\n唐小玄更加兴奋了，用双手扯着百花羞的头发，道：“\n骂出“骚货”\n唐小玄本来有一种很厉害的“\n“\n还百花羞，\n唐小玄挺着肉棒，“噗嗤”\n在唐小玄三番五次攻击之下，百花羞已经全身上下都在拱动了，\n唐小玄的腰身一前一后地发力，动作越来越快。\n“\n唐小玄在百花羞的淫叫之下，\n“\n“啊啊，不行了，哥哥，我、我……\n百花羞感觉撞击的小腹中气胀，\n“叫，骚货，\n性爱之中，\n“啪嗒、\n“\n随着百花羞那长长的哀鸣声，唐小玄只觉得一股暖潮将自己的阴茎彻底裹住，喷洒出来，虽然两人紧紧地贴合在一起，\n而唐小玄也用自己的最后一顶，夹带着暖潮的热量，冲击撞上那微微有点开口的子宫，\n“\n几声低微的响声之后，唐小玄的抽动也慢慢停歇下来，长长地呼出一口气，\n百花羞获得高潮之后，全身一阵瘫软，\n唐小玄微微张开双眼，呻吟了一声，道：“公主妹妹，\n唐小玄赤裸着身子在百花羞的旁边坐着，\n自己明明决定抛弃将百花羞，当是一个烫手山芋一般，但是最后还是缠到一起，\n百花羞见唐小玄在一边沉默不语，就缓缓地爬起身子将衣服穿好，趴在唐小玄的背上，\n唐小玄干咳了一声，\n百花羞眨着眼睛，道：“你说吧，\n“我问你，\n唐小玄说这话的时候，\n百花羞眼睛睁得大大的，道：“想，当然想了，我做梦都想，神仙逍遥自在，佛祖法力无边，\n唐小玄故意露出一副惘然之态，\n唐小玄又接着道：“但是，倘若我在此处做了驸马的话，以后上天一定会怪罪我贪恋人间美色，说不定会派天神将我们硬生生地拆散，更有甚者，也许还会将我打入十八层地狱之中，\n“所以，我想我一定要去西天完成取经的任务，届时，\n唐小玄的双目中拼命地挤出一丝眼泪，望着百花羞道：“\n百花羞单手掩面，眼中的泪水已经顺着脸颊流了下来，直摇着头，哽咽道：“可是此去西天，路途遥远，我怎知你何时才能回来，\n唐小玄现在只恨不得两巴掌掴在这个痴情女的脸上，可无奈自己并不能这么做，他笑了笑，\n“你说的也不无道理，只是，\n“\n唐小玄暗笑着，擦干百花羞脸上的泪痕，\n“怎么还不行呢，\n八戒还没有找到理由敷衍，忽然天上一声惊雷响起，雷声隆隆，\n很快，\n“\n难道是自己的事情被玉帝知道了？\n“\n“不可，玉帝让我同你一同去凌霄宝殿，\n八戒知道十之八九是事情被告发到玉帝那去了，\n没有法子，\n“\n“你莫急，\n两人沿着南天门一路直入凌霄宝殿。\n这个死月老居然在背后出卖我。八戒越想越气，本来是想用那思情丹挑起两位公主的情欲，自己好偷欢一场，谁知鱼还没有吃到，\n八戒随着雷震子进了凌霄宝殿，见玉帝一脸阴沉，情知大事不好，可是自己已经身在宝殿之上，\n“\n“\n八戒虽然知道是什么事情，但依旧明知故问，道：“\n玉帝也不急，就将月老召到面前，对月老道：“你且将这畜生的罪状说一说，\n“\n玉帝叹了口气，道：“昔年你贪恋女色，戏弄嫦娥，已经被罚下界转生为猪貌，\n八戒觉得自己全身都软掉，既不敢言语，\n“\n玉帝话音刚落，就上来两个人将八戒左右夹住，\n“\n这句话说完，太白金星就从队列里走了出来，手持玉笏，禀玉帝道：“\n玉帝觉得太白金星所言有理，沉思半晌，道：“\n最后领命的居然是月老，月老沉声道：“玉帝，\n玉帝道：“但你已年迈，不宜长途奔行，\n月老却道：“无妨，\n不等玉帝拒绝，月老接着道，“\n玉帝咂了咂嘴，\n这话说出来众皆哗然，原来玉帝也担心自己不能长久在自己的宝座上，\n“凡事皆有天命，冥冥自有天定，盈虚盛衰，\n说完这句话，月老就走了出去。八戒看着月老走出去，\n再说唐小玄一行人从赤红、青绿两公主口中得知八戒被雷公叫去天上，异常焦急。\n三个人出了宫门之后，唐小玄向悟空求问：“悟空，\n悟空虽然有命世之才，但并不通晓占卜算术，不能事事料定，当下也无法解答唐小玄，就道：“\n悟空虽然是齐天大圣有通天之能，但也不可乱了天规，\n唐小玄闻言，\n悟空道：“师父，八戒这是触犯天条，怕就是我佛如来也认为八戒要遭受惩罚，\n悟空沉吟了片刻，\n唐小玄“嗯”了一声，\n悟空也觉得现在是团结一心的时候，\n沙僧也道：“师父说得对，二师兄虽然为人轻浮，\n既然如此，那就上天。唐小玄也早就想上天看看，\n唐小玄现在已经修炼成三级小仙，虽然还没有三个徒弟的本事，\n只见那南天门碧沉沉，琉璃早就；明晃晃，宝玉妆成。\n先说话的还是悟空，\n“师父，\n悟空走在唐小玄的面前，在前面引路。\n唐小玄跟在悟空的后面一句话也不说，\n唐小玄三人一路沿着遣云宫、紫砂宫、\n凌霄宝殿中的真容唐小玄还没有见到，就被凌霄殿前面的两名侍卫挡住，唐小玄愣了愣，刚准备说几句客气话，\n这话对于唐小玄来说还算不得什么，毕竟自己现在修为低微，不能与这些人相提并论，受了一点气也能够忍受。\n“\n另外一名护卫显然识相一些，连忙迎上笑颜，\n悟空是个顽劣的猴子，哪里听得下这些话，只是急急地嚷嚷道：“\n“\n话音甫落，只听身后传来一声十分低沉的声音，这声音听来貌似从很远的地方传过来，\n唐小玄的那反应可别提有多快了，\n佛祖之大，大如天，\n等到唐小玄定下心神来一看，发现自己周身已经围满一圈人，\n显见如来已经透过月老的口知晓此间的事情。\n“\n如来的手掌微微一指，\n唐小玄还不明所以，未及说话，如来接着道：“你们师徒四人同心协力方能过九九八十一难，取得真经、\n所有人面面相觑，还不知道出了啥事。第一个站起来的是玉帝，玉帝在众人身上扫视一圈，\n这话虽然看起来是问大家的，\n唐小玄站起身来，对着玉帝拜了拜，道：“\n他对玉帝拜了拜，\n太白金星看起来一副德高望重的样子，\n玉帝双目微阖，道：“天蓬若是不杀，难以服众，日后必定还有同为者，\n见八戒跪在地上，身上被绑着捆仙绳，悟空立刻冲过去将八戒扛在背上，左手负人，\n众仙震怒，纷纷掏出法宝，想要跟悟空斗个高下。这个时候，沙僧也不甘示弱，\n唐小玄见势，\n唐小玄用自己的胳膊挡住悟空冲动的举动，对着面前的玉帝，道：“各位天神且莫动手，\n这话刚说完，玉帝将手一扬，\n唐小玄听到玉帝的话，先是怔了怔，才回过神来。\n若是动起手来，这师徒四人一定会吃大亏，这也就是为什么悟空在取经前跟取经后有所差别的原因。\n就在这种双军对阵的紧张氛围之中，忽然传来一声天籁之音，声音细弱游丝、缠绵不绝，\n昔日后羿以强弓射日，被后世练箭的人尊奉为“羽仙”\n嫦娥的容貌之美是出了名的，\n嫦娥自天上飘飘而落，在中间落地站稳，\n就算谁的面子都不给，嫦娥的面子可不能不给。嫦娥仙子来这里，自然有事情要说，\n嫦娥站在人群之中，仿佛鹤立鸡群一般，"
    },
    {
      "id": "content_53da7f3192c957f199365cef25b5e94d_37",
      "title": "第八章 腹中胎",
      "index": 10,
      "url": "/content_53da7f3192c957f199365cef25b5e94d_37.html",
      "content": "唐小玄道：“没错，就是红孩儿，\n悟空机灵得很，就照着唐小玄的吩咐应了声：“好，\n红孩儿马上哭声连连：“师父，我本是山下平常人家的孩子，\n悟空故意点了点头：“\n悟空手中金箍棒横空一挥，\n红孩儿蹲坐在地上，\n悟空想也不想：“\n说着就走了过去，用右手拉住红孩儿的左手，\n可谁知悟空忽然就用另一只手如电掣般挥过来，但闻“咯咯”两声，\n红孩儿满面垂泪，\n悟空冷笑两声：“我的儿，你以为你变作个凄零孩童，孙爷爷我就不认得你了吗？不过今日我不杀你，\n红孩儿知道自己再装下去也没用，\n看过西游记的人都知道，不论是妖是仙、是魔是佛，一旦被锁住琵琶骨，修为就会为零，法术全无。这个时候八戒也将南海的观音菩萨请来，观音菩萨收了红孩儿，\n师徒几个人继续西行，\n唐小玄又运用自己未卜先知的本事，让悟空带领着八戒跟沙僧直入国中，设法叫出了国王，\n所以如来见唐小玄一众这么简单的过了三关，心中有些不悦，\n唐小玄四众过了这车迟国之后，唐小玄就开始精心想下面的计划，\n特别是像唐小玄如此清秀俊丽的男人，到了女儿国岂不是像个宝一样？\n几个人在车迟国除妖之后，刚出城门还没有半日，\n收服红孩儿之后，不是才与观音菩萨作别吗？怎么才过了把月的时间这菩萨又来了？\n“师父，\n“\n不过唐小玄可不敢妄自想得太多，\n“菩萨大驾光临，\n唐小玄虽然已经感觉出观音菩萨今天来必定是有什么要事，\n“唐玄奘我且问你，你最近数月擒住红孩儿、收服黑水妖、杀死三魔怪不过是举手之劳，\n观音菩萨就算佛法通天，\n唐小玄现在本领在观音面前只能算是低微，只有走了过去，站在观音的莲花台前双手合拢道：“\n观音菩萨道：“\n这三个徒弟连忙跑过来，将唐小玄扶了起来，不断摇着唐小玄的肩膀，可惜唐小玄却不省人事，好像是死了一般全无生气。悟空抬起头来，怒视着观音菩萨道：“菩萨，您这是做什么，我师父从不做伤天害理之事，为人慈悲为怀，\n观音菩萨见悟空动怒了，也不悚惧，只是不急不慢的道：“\n悟空将手一甩道：“为何要说不知道，知道就是知道，\n观音有点生气了：“\n悟空追问道：“这又怎么个说法，\n观音菩萨悠悠道：“不论是天上地下，凡是能够知天意者，必定会大减阳寿的。他知一事就少活一年，他这一路想必已预料了七、\n“\n“是是是，菩萨您说得不错。\n悟空跟唐小玄是亦师亦友，将唐小玄当做自己的知己，不管是谁只要是伤了唐小玄，\n观音走后过了许久，唐小玄才悠悠醒转过来。见到唐小玄醒了，几个徒弟都是乐不可支，\n唐小玄只记得自己见到观音菩萨手掌一挥，\n悟空叹了口气，咂着嘴道：“师父，\n唐小玄点头道：“\n“\n唐小玄道：“我们是一路降妖除魔走来的，而且走得似乎并不太吃力，\n悟空扼腕道：“是了，\n看来观音没有说假话，果然将唐小玄的记忆洗去一段，致使唐小玄以后难以再“未卜先知”，\n唐小玄低头沉吟片刻：“悟空，你可有什么好法子，\n唐小玄也不想难为悟空，\n唐小玄看到前面立着一座碑，就吩咐八戒道：“八戒，\n八戒用手挖了挖自己的鼻子道：“师父，\n唐小玄目光看向悟空，悟空连忙摇手道：“师父，八戒好歹当过几天元帅看过几篇文书，\n唐小玄本来是想偷濑坐在马上不下来，\n那三个大字下面还有一行小字，\n不过唐小玄的记忆被观音洗，现在对于女儿国是一点印象也没有，\n八戒对这种事情最感兴趣，马上来了劲头：“\n唐小玄指着这碑文道：“你们看，她们正求男子入赘他们国中呢？\n八戒急忙上来看了两眼碑文，\n唐小玄遮着眼睛看向远方：“\n他现在修为五级，算是个中仙，\n“师父，\n说着，\n“这个呆子一听到“女人”\n唐小玄从某种意义上来说，跟八戒也是一路人，听悟空这么说八戒，唐小玄不知怎觉得悟空有指桑骂槐之嫌，心中很是别扭，只好道：“悟空，我们还是赶路去吧，看这荒原苍茫辽阔，\n“\n悟空一边拥着唐小玄攀到马上，\n沙僧老老实实的，也不计较悟空话中的别个用意，只是应了一声，\n唐小玄多么机警的一个人，见悟空将沙僧支开，\n悟空在马股上面轻轻打了一下，\n“悟空，\n唐小玄听悟空如此一问，马上道：“\n“法子倒是有，\n悟空沉吟着：“\n唐小玄只想知道是什么法子，\n悟空哂了咂嘴：“师父，\n“\n“传说在天地未分、浑沌未开之时，这世界上就已经有了两股力量了。一股力量是上面的女娲及她的子民部众，还有一股就是下面的玄阴跟他的手下弟子。\n悟空的故事讲到这里，唐小玄似乎领悟一点什么，\n悟空点了点头道：“\n唐小玄一边欣喜不已，一边又道：“那悟空，\n悟空沉吟半晌：“这就有点难了。首先师父必须要找到至少五个修为在七级以上的大妖，而且必须要是女妖，然后师父要跟她们行男女之事，\n唐小玄故作正经的道：“难道只有这一种法子，\n其实唐小玄担心的倒不是跟女妖做那种事，\n这一路上光以修为而论，\n“师父啊，我跟你说，\n还要同时一并跟五个七级女妖一起做那种事？唐小玄只感觉自己的头晕乎乎的，\n第一：难以同时找到那么多的女妖，就算是用困妖神塔来收，也要收很久，而又很难保证那些女妖可以在困妖神塔中不出什么乱子，一直存活下去；第二：自己必须要有很强壮的身体跟强悍的修为，上次只吸收白骨精一个人的元魂跟修为，就将唐小玄累个半死了，而这次居然要同时跟五个，难度之大可想而已，\n集合以上三点，\n唐小玄只有长长的叹了口气，唏嘘道：“看来这种事只能是命中注定讲求缘分，\n悟空笑了笑，道：“师父，我跟你说了，\n唐小玄领会悟空的意思之后，\n从太阳还未冒出的地平线的时候开始走，\n“\n八戒搓了搓自己的鼻子道：“若是我八戒一个人的话，\n“\n孙悟空也已经看到了，\n八戒于是就扯着嗓子喊道：“\n连叫了好几声之后，柳荫里才“咿咿呀呀”\n到了近处，唐小玄才看出来撑船的居然是一个老女人，穿着粗布衣服，手上皮厚筋硬，\n“\n悟空看这摆渡的是个老女人，就觉得很奇怪。“\n“艄公怎么不在，\n过河之后，沙僧从包袱里面掏出几文钱，递给这个老女人。唐小玄一路奔忙，此时终于找到一个安身之所，当下觉得口渴，\n八戒也是口渴难当，马上拿着钵盂冲到岸边，\n一天三餐几乎天天都吃这个，有时候还要饿着肚子，这是唐小玄对于西游之旅最大的不满，\n可是这顿馒头还没有吃完，八戒就忽然张开大嘴，将嘴里的馒头吐了出来，用手按住腹部，大声呻吟道：“哎呀，我的妈呀，\n请续看《"
    },
    {
      "id": "content_53da7f3192c957f199365cef25b5e94d_38",
      "title": "第五集",
      "index": 11,
      "url": "/content_53da7f3192c957f199365cef25b5e94d_38.html",
      "content": "【\n女儿国女王欲要招赘唐小玄，而当他们相见时，唐小玄会如何服侍未经人事的女王，\n被观音夺去西游记诸般劫难记忆的唐小玄，又被迫回去面对取经劫难，可三个神通广大的徒弟都被妖怪抓走，"
    },
    {
      "id": "content_53da7f3192c957f199365cef25b5e94d_39",
      "title": "第一章 求亲",
      "index": 12,
      "url": "/content_53da7f3192c957f199365cef25b5e94d_39.html",
      "content": "悟空警觉性比较高，以为这个老妇是个妖怪，马上拉住老妇的手，\n接着，唐小玄的头上也是大汗淋漓，涔涔而落，一只手按着桌子，一只手按着肚子，\n“既然跟你没有关系，\n老妇好似想起什么似的道：“哎呀，师父们啊，\n这老妇一拍大腿：“那就是了，\n悟空还不明所以：“大男人生什么娃娃，\n这老妇解释道：“我们这小国叫做女儿国，国中都是女人，\n“\n唐小玄腹痛难忍，表情扭曲变形，支吾着道：“妈的，\n一时情急，唐小玄就说出了脏话来，\n悟空听这个老妇解释了一番，心中顾虑顿时消减，大笑道：“师父、\n“\n“是啊，悟空，你快问问这个老人家，\n话说了一半，\n其实若是观音菩萨不将唐小玄关于西游记的记忆消去，\n“老人家，你就快跟我说说，\n悟空见八戒跟唐小玄痛疼难耐，\n这个老妇脸上露出难色，沉吟道：“\n“\n唐小玄整个人都蹲了下来：“快去街上买点堕胎药吧，\n“\n“\n悟空点头道：“既是如此，\n悟空刚要走，那个老妇就拉住悟空：“但是小师父你可不知道，前些年这个解阳山被一个道人霸占了，那道人自称什么如意真仙，凡是想求得泉水，就必须要有花红表礼，\n唐小玄一边叫疼，\n“不打紧的，老人家，我自有我的法子，\n悟空知道跟这种没有见过世面的老妇没什么好计较，只道一声：“\n这可让老妇看得眼睛都直了，她哪里见过这等奇事？还以为唐小玄几个是神仙下凡，\n唐小玄真是无语，想到自己来这一趟西游中，\n再说悟空去了那南街的山上之后，很快就见到那个老道；\n红孩儿因为阻唐小玄的西行之路，被观音菩萨抓去当善财童子，所以这如意真仙对孙悟空一直怀恨在心，见到孙悟空来了，\n可他毕竟只是地上的一个修道者，哪里比得过孙悟空？几个回合之后，真仙便败下阵来，\n哪知悟空去落胎泉前打水时，\n两个打了一阵之后，如意真仙自知不敌又化阵风逃跑了，悟空眼下的要事是赶紧弄点泉水回去，\n可谁知此时那个真仙又回来了，\n“你这个死老道，\n“你害了我的外甥，\n“\n悟空真的怒了，可是一时也寻不到个好法子。这老道不跟自己动手，只阻止自己取水，\n想到这里，\n唐小玄跟八戒两人见到唐小玄回来了，马上急急问道：“水呢？\n“大师兄，不如这样，我老沙跟你一起去，你跟那个老道周旋之时，\n悟空马上问那个老妇，道：“你们家可有吊桶？我一时不慎，\n“\n这个老妇一连说了七、八个有字，很快就将家里的吊桶拿来，\n于是悟空拿着水桶，带着沙和尚，再度奔赴解阳山。依照计策，孙悟空将老道喊出来，\n“你这个助纣为虐的小道人，\n这小道童虽然跟着如意真仙学了一点法术，但是跟沙僧比起来那是一个天上、\n沙僧将水打上来，提着水大声冲着在半空中跟真仙斗法的悟空道：“\n听到沙僧这么一说，悟空就心定了，\n“啪”的一声，真仙的肩膀就挨了悟空一棒子。悟空的棒子是多么重，谁挨上一棒都受不了，\n悟空落下来，站在老道的面前，用大拇指朝着自己一指：“俺老孙要是使尽全力的话，你这条小命早就玩完了！老孙看在昔日结拜大哥牛魔王的分上，今日暂且饶恕你一命，往后不论是谁来打水，\n如意真仙知道自己打不过孙悟空，\n再说那沙僧带着一桶水回来之后，\n唐小玄眨着眼睛，\n“\n唐小玄用衣袖擦了擦嘴，\n“\n“\n唐小玄因为这个老妇才侥幸逃过生娃娃的命运，\n“\n沙僧虽然见唐小玄的肚子不疼了，可是脸色还是惨白，\n一旁的八戒可急了，\n沙僧闻言，\n“\n“\n沙僧又替八戒舀了一钵盂，八戒拿过来，\n沙僧依着八戒的话，\n一边的老妇见状，\n猪八戒感觉喝得还不太尽兴，就道：“\n这老妇闻言劝诫道：“你不能再喝了，\n他又很快转口道：“\n老妇应了一声，\n“悟空啊，那个如意仙人呢？\n“\n老妇此时已经拿着馒头走了进来，将馒头放在桌子上。八戒第一个冲过去吃馒头；悟空这来回几趟，又跟那个真仙斗了半天，也觉得有些饥饿，可正准备弄了馒头来吃时，老妇却忽然拉住他的衣服，道：“小师父，\n“\n“\n“\n这老妇喜不自禁，\n唐小玄一行吃过饭之后，就在这村里住了一夜。次日天明，师徒们谢了老妇，\n师徒四人一路西进，\n唐小玄在马上指着城墙：“悟空，\n这话虽然是对悟空说的，其实是对八戒说的。\n三个徒弟闻言谨遵严命，很快四众就进了城。行至东街口，街上的人都是长裙短袄、粉面油头，\n唐小玄看得直流口水，\n须臾间，\n八戒本来是怕自己露出真面目会将这些女人们吓着，在进城之前就一直用大袖子掩着脸，此时见道路被这些女人们堵住，只好现出真面容来，口中乱嚷道：“我是只猪公，\n他一边说话，还一边摇着自己那两片蒲扇般的大耳朵，\n于是女人们便让开路来不敢上前，\n这些女人虽然都是古代的装扮，且多数都是素面朝天，但是这些女人都天生姣好、面容俏丽、体段丰腴，真是万分的养眼。一行人前进着，\n这三个字写得工工整整，八戒也能认得，指着这三个字笑道：“\n唐小玄从马上跳下来，\n这种女人或许不是最美的，\n八戒跟唐小玄两人都怔了半晌，唐小玄才回过神来，上前跟那女官作礼。女官虽然比较强悍，但终究是个女的，见到唐小玄一众心中自也欢喜，忙在前面引路，\n将食宿安排好之后，女驿臣整了整衣冠，\n黄门官即时上奏女王，女王降旨将驿臣传到大殿上，\n驿臣马上回道：“微臣在驿，接到东土大唐王御弟唐三藏，\n这女王虽是一朝之君，可终究是个女人，从未见过男人，闻得驿臣的奏言满心欢喜，对文武百官道：“寡人夜里做了个梦，梦见金屏生彩艳、玉镜展光明，\n众位女官还不明所以，就纷纷道：“\n女王悠悠回答道：“东土男人乃唐朝御弟，我国自浑沌开辟之时，各朝各代的帝王都不曾见到一个男人到此，今天唐王御弟出现，我想是上天所赐。寡人愿意用我们一国的财富招赘御弟为王，我甘愿为后，\n众位女官听了女王此话，\n这时那位驿臣又奏道：“主公所言甚是，只不过御弟三徒弟长得凶恶、不成相貌，\n驿臣答道：“御弟相貌堂堂，丰姿英俊，诚为天朝上国的好男儿；\n女王想也不想就道：“既然是这样，\n众位女官马上拍马屁齐声道：“主公所言极当，臣等钦此钦遵，只是匹配之事无媒不成，\n女王心中异常欢愉，\n唐小玄虽然知道，可是却没有答话，一边的八戒笑道：“\n唐小玄心中就别提有多高兴了。我操，\n八戒看到唐小玄不说话，只是口水直流，就问道：“师父，\n唐小玄这才回过神来：“哦哦，没事没事，为师觉得这里的素斋不错，\n八戒傻傻的点点头：“\n他动了动自己的大鼻子道：“\n实情本来就是这样，但唐小玄却故意板起脸：“胡闹，为师乃是出家之人，\n可唐小玄还要假正经：“悟空，你说假若那个女王不肯放我西行，却要强逼成亲，\n唐小玄还要追问道：“\n悟空神秘的笑了笑：“\n几个人正说话间，两个女官就来到大厅之中，\n来源   ，却别有一种成熟女人的风韵在里面。\n太师见唐小玄相貌轩昂，心中暗喜道：我国真是太有福气了，\n唐小玄早就知道喜从何来，\n太师躬身道：“此处乃是西梁女儿国，\n八戒在一边身体直拱，拱到了唐小玄的面前，冲着太师莞尔一笑，讪讪道：“\n话说到这里，\n八戒就心想：就算自己相貌丑陋配不上女王，\n可谁知这太师却接着道：“女王说了，你们这取经大任不可废也，\n八戒喉咙里直哼：“我也是男人，你们不是缺男人吗？怎么独独就要我师父一个，\n悟空跳了过来，\n八戒瞪了悟空一眼：“去你的，\n悟空却鼓掌道：“如此甚好，"
    },
    {
      "id": "content_53da7f3192c957f199365cef25b5e94d_40",
      "title": "第二章 女王",
      "index": 13,
      "url": "/content_53da7f3192c957f199365cef25b5e94d_40.html",
      "content": "太师闻言，只是摇摇头道：“长老，你别往心里去。依我说啊，你虽是个男身，\n悟空在八戒的猪脑袋上敲了敲，\n悟空一来知晓唐小玄心中的那么点意思，一一来他自己心中也有个计策，便回道：“依老孙我说，师父你就在这里安身立命也好，\n唐小玄心中犹如吃了蜂蜜一样甜，冲着悟空挤了挤眼睛，意思是说：\n太师听唐小玄这么一说，马上接着他的话道：“圣僧不必多虑，女王早已帮你们把取经之路安排好了，只要你留下，即刻就能给三位高足倒换关文，\n唐小玄心中高兴得已经不想再装下去了，看了一眼悟空，\n八戒情知这事跟自己已经沾不上边，就拍拍自己的大肚子：“\n太师对八戒一礼到地：“有有有，众位稍候，\n说完话，太师跟其他随同官员就欢天喜地赶紧走出，\n既然这件事已经搞定，今晚必定会有场床上大戏要上演，那唐小玄也就没什么心急的了，故意对悟空道：“悟空啊，你这样搞真是弄杀我了！我就算是死，\n“\n悟空解释道：“我们要是不答应招赘的请求，她们便不肯给我们倒换关文，不放我们去西行，搞不好还会心生歹念将我们杀了。若到那时，\n听悟空这么一说，\n皇帝不急太监急，八戒又抢着问道：“那师父进宫之后，\n悟空咳嗽了一声：“没事没事，师父道行高深、\n这种无耻的话，\n太师得了喜事之后，不等宣召就直入朝门，站在白玉阶前奏道：“主公啊，\n女王闻言，卷起珠帘从龙床上下来，樱唇轻启露出银齿，\n太师回奏道：“臣等去了驿站，拜见御弟之后就说起求亲的事情。御弟本来还有推托之辞，幸亏他那个大徒弟十分慷慨，答应微臣愿意留下他的师父与主为夫，完婚称帝。只需要倒换关文之后，\n女王笑道：“\n太师奏道：“\n众位女官钦遵王命，打扫宫殿、\n唐小玄本就等得急不可耐，听到女王来了的消息，\n女王从车銮中卷帘下来，喊了一声：“\n唐小玄在一旁眼睛则都看花掉了，只见六龙喷彩、双凤生祥，馥郁异香蔼、氤氲瑞气开。金龙玉佩多官拥，宝髻云鬟众女排，鸳鸯章扇遮鸾驾，翡翠珠帘影凤钗。笙歌音美，弦管声谐，\n唐小玄哪见过这种景象？就算他穿越之前是个纨绔子弟，每天过得十分豪奢，\n太师指着唐小玄道：“\n女王闪着凤目，蹙着娥眉仔细观看，见唐小玄果然是仪表非凡、\n唐小玄这次听到女王的呼声，还未及答话，便看到女王的面容，\n唐小玄几乎已经看得怔住了，而一边的八戒早就忍不住口水直流、心头乱颤，\n女王走近前来，\n“\n女王拉着唐小玄的手，两个人双双对对一并上了车銮。唐小玄现在已经鬼迷心窍，\n车銮缓缓而行，\n沙僧马上急道：“二师兄，\n八戒也不听沙僧的话，继续说道：“我去将白龙马牵着，找个地方卖了，\n说到哀伤处，八戒还哭哭啼啼道：“\n悟空笑着道：“你这个呆子，\n八戒本来是蹲在地上哭泣的，\n悟空虽然情知唐小玄这一去难免要破色戒，不过取经的大路却不能在这个地方停歇下来，\n不等沙僧跟悟空两个人应话，八戒就拖着个大钉耙，\n“\n悟空取笑八戒道。幻势沙僧不知道悟空究竟有什么解救师父的法子，就问道：“大师兄啊，你说你送自有法子，到底是什么法子啊？\n悟空摆了摆手：“沙师弟莫急，古言道：“车到山前必有路‘，我们只消去吃顿饱饭，\n沙僧很信任悟空，知道悟空的本事通天，每次闯过劫难都要依靠悟空，听他说的如此肯定，\n“沙师弟，\n悟空说着，\n沙僧却还傻傻的站在那里，双手合十，面朝西边道：“大慈大悲的观世音菩萨啊，\n唐小玄会不会平安归来呢？\n女王带着唐小玄一路直奔自己的寝宫，\n女王来了兴趣道：“\n唐小玄知道这个女王并不是个急性子，只有耐着脾气解释道：“大徒弟孙悟空，祖贯东胜神州傲来国人氏，\n这女王看来是个好奇的女性，事事都觉得新奇，\n看了半天，女王终于看完了，就又问道：“\n既然女王不急，\n原来如此，\n这一次，\n“御弟哥哥，你在那驿馆之中吃的粗茶淡饭，一定难以果腹吧？\n女王忽然道。这个女王虽然看起来非常成熟娇媚，说起话来却像是个小孩子一般，\n唐小玄眼珠子转了转，\n女王也没有什么心机，\n她轻声叫唤了一声，就有个侍女走进来，\n等到侍女离开之后，女王才伸出手来，\n唐小玄乘势抓住了女王的两只手：“不可怜。女王陛下，贫僧我有一养生之道，不论是风吹日晒、霜打雨侵，都不会伤害皮肤，能够保持皮肤亮丽、\n这女王本来就对诸般事情有好奇心，听唐小玄这么一说，马上问道：“是什么养生之道，\n唐小玄却徐徐地道：“\n可是这女王却急道：“为什么要等一会儿才告诉我，\n耻女王不知其意，\n女王看了看唐小玄的手，手中不知何时出现一颗药丸，大感惊奇。原来刚才唐小玄让女王看门的时候，手里施了一个小小的法术，\n这个药丸可不是无凭而生，而是当时悟空在降服车迟国的三个妖怪时，\n于是，\n“\n唐小玄想也不想就道：“此物名为养生丸，\n唐小玄将药丸放在女王的手里，\n这谎也太扯了，拿到现代，就算是再傻的女人恐怕都不会上这个当吧！\n“\n“那当然，贫僧以……\n女王点了点头，\n唐小玄看得不由得吞了口口水，\n菜摆了一桌之后，这些女孩子才对唐小玄跟女王两人行了礼，\n然而虽他嘴里说的是“你请用”，其实自己已经先下筷子了，\n女王并太饿，只是看着唐小玄吃了很久，\n说完句诂，\n女王忽然觉得这圣僧有点让人不舒服，便看看自己手中的药丸道：“\n“\n女王吃下这颗药丸之后，脸上顿时现出一种红润的色泽，她舔了舔嘴唇，醉眼迷离：“\n唐小玄知道是药丸起作用了，就试探着道：“\n“我好热啊……我……\n“\n“\n把持不住的女王这时也顾不得唐小玄了，纤纤玉手已经扯着自己的腰带。只不过这位女王一直以来都被别人伺候着，从来没有自己穿过一次衣服，\n“\n女王娇唤道：“你……你帮人家解开衣服吧，\n唐小玄知道自己装正经已经装得差不多了，就道：“\n这一咬咬得唐小玄全身一麻，\n唐小玄虽然跟唐僧合体之后，唐僧所知的东西他也都知道了，可是唐僧是个守本分、\n妈的，谁他妈的将衣服系得这么紧，\n女王在唐小玄的耳朵上、脖子上吮吸了几口之后，见唐小玄还没有将自己的衣服解下来，\n“\n“\n解不开衣服，唐小玄的心情也糟糕的很，没好气的道：“我已经在解了，\n“哥哥，\n“哥哥，\n女王现在浑身燥热，下体已经淫水横流，\n唐小玄连忙朝着那桌子上看过去，\n唐小玄又举起剪刀，\n唐小玄也是急得满头大汗：“\n“你直接将妹妹的胯下那部分剪开，不就……不就可以插入哥哥……\n女王抚摸着自己的下体，下体淫水直往外流，\n唐小玄咂了咂嘴，\n唐小玄感叹着，也不用什么剪刀了，凭借着手上的力气，"
    }
  ],
  "tags": [
    "西游",
    "神话"
  ]
}