{
  "id": "book_3470",
  "title": "淫乱大家庭（2）",
  "author": "未知",
  "cover": "",
  "description": "淫乱大家庭（６）外头下着大雨，刚回到家的琼琳撑着伞却湿了一身，正在前庭擦去身上的水珠。“真要命，这场雨简直要把人吞没┅┅啧！弄得我一身都湿了。”“不赶快换干衣服会感冒。”她拎着滴水的裙摆走进房间，脱去...",
  "sourceId": "jisge",
  "sourceName": "集书阁",
  "chapters": [
    {
      "id": "ch1",
      "title": "淫乱大家庭（2）",
      "index": 0,
      "url": "",
      "content": "“真要命，这场雨简直要把人吞没┅┅啧！“来源\n“我说琼琳妹子，每家都有难念的经，“林太太，“唉呀！亏你们住在一个屋沿下，“呃┅┅“你可别怪我说人闲人闲语，““是啊！我告诉你┅┅”林太太四下张望，““林太太，“琼琳呀，你也太后知后觉了，那天我和修水电的阿全还有小王，去她那打牌当着我的面，“““啊！来源\n“当她意识到乱伦这字眼，脑间瞬即飘过爷爷兴奋时的表情，让她感到极度的昏眩，维持这种违反世俗道德的行为，但那个老淫魔却象永远得不到满足似的，在她年轻成熟的肉体上尽其发泄兽欲，但有关遗产之事却支字不提，真所谓姜是老的辣，自从她数次跟老鬼云雨缠绵之后，那个死鬼丈夫都不再碰她，“琼琳抚着下体，想着想着肉缝湿滑了起来，花蕊的深处骚痒难耐，透过裤缝手指搓揉着丰满的阴唇，渴望获得高潮的淫念，“妈，你身体不舒服吗？”“呃┅┅没┅┅没事┅┅我很好。”琼琳吓得头皮发麻，“我看你很难过的样子，“是啊！我┅┅我很好，“\n恩，那就好。”小刚说罢带上门离去。\n“糟了，全身的狂热欲火瞬间熄灭，琼琳花容失色的呆立原处，““心里忐忑不安的猜测，羞赦于身为母亲的淫态却让儿子撞见，来源\n““暂时让你坐立难安，不需多久就让儿子的东西来填满你吧┅┅”琼琳缓缓收拾好胯下翻开的底裤，“““啊┅┅住呼吸，母亲泛红着双颊、骚首弄姿的风情万种，让人难以忍受的想要夺门而入。\n“嗯┅┅好儿子┅┅快┅┅快入妈的穴┅┅来源\n“啊┅┅妈妈┅┅“嗯┅┅嗯┅┅小刚┅┅用力┅┅““两人隔着一扇门，互相痴迷的幻想着彼此的肉体，小刚精门一开，热烫的阳精很快的射了出来，午后绽放出阳光，经过早上放浪的泄过之后，“这个时候会是谁在里面。”她轻推未关紧的门扉，“她不禁再度想起林太太的话，这使她更好奇的探个究竟，丽英的背影玲珑有致，曲线柔美，丽英穿着浴袍全身香喷喷的走出浴室，“““你就是杨老师吧！“刚沐浴过的丽英看来更添娇媚，进门的男子高壮英挺，““是的，唉！““杨老师你请用茶。”“呃┅┅杨老师，这次来拜访是不是我家友恭又做了什么事？”“是┅┅是的，“““行为上的偏差┅┅？“呃┅┅我发现友恭经常在上课期间对女老师自渎，““““是的，对了！友恭在生活周记这么写着。”丽英在生活感言一栏念着∶“女人的乳房及臀部，丽英不禁当场错愕，但对友恭此等行为她是可以理解的，即使是自己的母亲他也┅┅只是友恭把这些事写成生活感言，使她突然坐立不安，面前的杨老师也着急的想看我的反应吧！““杨┅┅杨老师，“““不，“或许是自己一味的沉溺淫欲的满足，不曾真正的关心过他，友恭这孩子一向较同龄的早熟┅┅她骤然抬起头，“我┅┅“夫人，““是的，也许你在他心目中高高在上的尊严受到动摇吧！所以友恭藉着不当的行为，“原来是这样┅┅”“那么，““杨老┅┅“我早听说这附近的男人跟你的事，今天有幸一亲芳泽的话┅┅嘿嘿┅┅“你┅┅“夫人，“杨老师┅┅“我快晋升主任了，“不┅┅“呵呵┅┅来源\n“夫人，你的丈夫早就不行了，“杨老师┅┅““不┅┅不行啊┅┅来源\n“你的奶子好美呀！“住┅┅住手┅┅““不要啊┅┅杨永泽解开丽英腰间的带子，将里面一丝不挂的肉体绽放出来，“哼┅┅你如果不答应，来源\n“我┅┅我明白了，“哼哼┅┅夫人，你果然识时务┅┅”见丽英闭起眼不再反抗，他右手复在丽英的性器上猛烈的揉弄，一旁的琼琳早已抉堤般色欲高涨，胸口剧烈的起伏，此时杨永择整个头埋在丽英双腿之间，“夫人，“啊┅┅丽英按捺不住花蕊坦裎在男人眼前的羞耻感，臀部左右闪避，杨永泽索性托起她的肥臀，让整个阴户紧贴嘴巴，竖直舌尖进进出出肉穴，丽英虽和许多男人交欢过，“啊┅┅啊┅┅同为女人琼琳官能上感同身受，这样的舌奸 入，““给┅┅给我┅┅快┅┅“嗯┅┅“夫人，““杨永泽胯下之物比刚刚更大，肉棒周边浮起青筋，景象甚是骇人。丽英见状脸色泛绿，这么粗大的鸡巴还是第一次看到，“可┅┅可是┅┅“你别怕，来源\n“啊┅┅“你忍着点，\n我这根肉棍可是征服不少女人的。”\n“来源\n“““别大声嚷嚷，来源\n“贱女人，“嗯┅┅喔┅┅既然认定我是婊子，“骚货，张开你的腿，琼琳恍惚地张开双腿，褪到膝盖的内裤被撑开，男人的手勾住她的腰间，“呜┅┅穴内一阵充满，肉壁紧紧的包覆闯进来的鸡巴，“喔┅┅大鸡巴老师┅┅用力┅用力干我┅┅我的小穴痒死了┅┅“啊┅┅好深┅┅老师你顶到人家花心了┅┅“夫人┅┅““你放心┅┅来源\n“你┅┅你挺会插穴的┅┅喔┅┅我会被你插翻┅┅““你说的对┅┅我是个骚货┅┅干我┅┅琼琳忍住压低声浪，狂乱的情绪早已弄得一身热汗，男人近似疯狂的抽插，来源\n“喔┅┅喔┅┅“嗯┅┅喔┅┅“杨┅┅“我┅┅也要射┅┅\n“没┅┅杨永泽壑然起身，此时身后的男人亦使劲的抓着琼琳双乳，“大鸡巴哥哥┅┅“淫乱的女人┅┅“啊┅┅射┅┅不知过了多久，琼琳缓缓地睁开双眼，无神的看着大厅地板上的那对男女，杨永泽疲累的瘫在丽英身上，痿缩的阴茎流出少许的精液，她突然心头一震，那男人┅┅她倏地回头，那男人还在，“淫乱大家庭（琼琳简直不敢相信自己的眼睛，这个男人赤裸裸的躺在眼前，怎么也想不到方才使自己成为淫乱荡妇的不是别人，竟是唯一的儿子—一阵突如其来的羞耻罪恶感让她不安起来，“这孩子难道一直对我的身体┅┅”看着亲生儿子沉沉的睡着，一脸满足幸福的表情，那宽阔的肩膀、厚实的胸膛使她着迷起来，如果他只是陌生的男人自己一定无法拒绝他，“我是个淫荡的母亲┅┅来源\n““这是个完美的理由，同时，皮肤还留着男人独特的体味，一幕幕高潮不止的快感浮现，琼琳不禁回味儿子的肉棒带来长久饥渴的满足感，眼神不经意的望着昏睡中的小刚，“真┅┅瞬间，“来源\n“来源\n手心传来热烫的温度，右手不禁搓揉起根部，脑子却一片混乱，体内女人原始的欲望不断涌起，小刚紫红的龟头冒出青筋，子宫肉壁一阵抽 ，琼琳开始感到口干舌燥，““来源\n“琼琳看着小刚，“不┅┅“我们终究是母子，心里虽这么想，“嗯┅┅来源\n晚饭时刻，他已经不只一次的偷瞄自己，似乎想从她脸上看出，被奸淫后的母亲会有着什么样的反应，琼琳极力的掩饰内心起伏不定的情绪，压抑肉芽骚浪充血变硬的不伦反应，就当一切都没发生过。在这无声的攻防战中，“妈，来源\n“呃┅┅大┅┅“来源\n““没关系啦！“琼琳在心里哭泣，这孩子非要这样折磨妈妈吗？来源\n““哎，丈夫竟也帮小刚说话，琼琳心里有数，“来源\n“““来源\n“这孩子可能打算即使我不答应，“来源\n“丽英一听小刚提起这事，倏地面色泛白，“““呃┅┅是┅┅“““丽英怯怯的低着头若有所思，她或许在担心早上在客厅性交的事东窗事发吧！琼琳不由得疑惑小刚的动机，晚饭后，走进房间，“““恩。”““喔，丈夫完全不明就里的说着，如果让他知道妻子和儿子发生性关系，琼琳像失去灵魂般的躯体，往小刚的房间踱去，她轻轻推开小刚房门，“也许是我想太多了，“她边猜测边走进房间坐在床沿，来源\n“啊┅┅嗯┅┅用力┅┅喔┅┅“达令┅┅好舒服┅┅来源\n“琼琳面对突如其来的状况有些恼羞成怒，男人粗暴地将阳具塞进女人的嘴里，并命令她用力吸，来源\n“妈！”“来源\n“妈，你找这个吗？”“小刚不但没这么做，反而不发一语的贴近琼琳让她坐在床上，象抱着爱人般自身后拥着她，来源\n“妈，“呃┅┅你┅┅这孩子┅┅怎么可以看这种电视┅┅我┅┅“电视上的男人正让女人舔着肉棒，深红色粗大的阴茎泛着亮光，琼琳一时不知该以什么态度面对小刚的问题，““妈快看，女人缓缓地解开上衣卸下鹅黄色的胸罩，露出一对豪乳，“妈，“来源\n“妈，“不┅┅不可以┅┅““住┅┅住手┅┅“我已经不是小孩子了，为什么不能和你要好？”“小小刚┅┅我们不能这样┅┅这是不对的┅┅”小刚解开琼琳睡衣钮扣，“妈，“来源\n“妈，“来源\n这孩子当真要侵犯自己┅┅“来吧！“喔┅┅小刚听到母亲发出呻吟，心里不禁得意计谋得逞，淑倩从衣柜悄悄地走出，随后爬上床脱去衣物，“唔┅┅琼琳感到双唇被灼烧，“大伯母，来源\n“另一方面，“不┅┅不┅┅淑倩快停┅┅““这一惊非同小可，“你┅┅“是啊！“小┅┅“妈，来源\n“什┅┅“大伯母原来你也这么需要，来源\n“来源\n“““对呀！面对这天大的巨变，眼看淑倩说得有凭有据，“妈，“来源\n““┅┅”\n“妈，“┅┅”\n琼琳倔强的压抑自己火热的欲望，她心里正懊恼不已，母亲高贵的尊严及荡妇之间的分野，使她旁徨。小刚褪下母亲的睡裤，蓬松艳丽的阴毛尽收眼底，他第一次这么看着母亲的下体，儿子毫不修饰的盯着自己的秘密花园，琼琳羞涩的并住双腿，小刚双手费力的分开雪白的大腿，““经过和淑倩的数次交欢，“不┅┅“哼┅┅好痒┅┅来源\n“大伯母，来源\n“喔┅┅大伯母快舔┅┅湿黏的蜜汁骚味刺鼻，年轻女孩的芳香让人心神荡漾，淑倩因能淫虐这个平时端庄贤淑的大伯母早已淫态百出，“淑倩蹙紧眉头，琼琳能体会那种骚痒的地狱，每当午夜梦回对着丈夫打鼾的背影，她是多么的渴望被满足。基于感同身受琼琳伸出香舌，滑进淑倩的肉缝┅┅“喔┅┅好舒服┅┅“嗯┅┅“呜┅┅“大伯母┅┅舔的好┅┅“好┅┅来源\n“喔喔┅┅“好，要干进妈妈的洞了。”\n小刚一挺腰，““喔┅┅妈妈┅┅我好舒服┅┅“乖儿子┅┅快抽动┅┅“妈┅┅琼琳终于卸下武装，一心一意的期望儿子大肉棒的滋润。小刚得到母亲的鼓励，“来源\n“没想到琼琳跟自己的儿子┅┅“大嫂这等骚样┅┅金生捏着裤裆，平时，他就经常注视琼琳成熟妩媚的身段，虽然是大嫂，“用力┅┅插进来┅┅“床因剧烈的摇晃发出“咯、小刚拉开琼琳的双腿，好让自己更深入母亲的体内，下体也因互相的撞击发出““小┅┅小鬼┅┅来源\n此时的琼琳已是十足的淫兽，两手分别玩弄两个乳头，头发散乱的披在床上，“好孩子┅┅用力插进来┅┅妈妈的洞┅┅以以后只给你玩┅┅“不只这样┅┅我还要所有的男人┅┅“好好只要你喜欢┅┅就算要妈到大街上被男人玩弄┅┅“真的吗┅┅我喜欢看你┅┅被强奸┅┅“乖孩子┅┅“喔┅┅妈┅┅“嗯┅┅没关系┅┅都都射进来┅┅小刚扑向琼琳，浓烈的精液在母亲阴道全数倾泄，，纷纷达到高潮。门外的金生仿佛大开眼界，硬挺的肉棒快要爆炸似的，不得不解放出来套弄。\n“喔┅┅真好┅┅淑倩疯狂的上下晃动，两股之间粗大的阴茎送进拉出，胸前的乳房也上下跳动着，“激烈的震动吵醒小刚，“哼┅┅啊啊┅┅““我，我不管┅┅“小┅┅小鬼┅┅我和你妈┅┅“当┅┅“讨┅┅来源\n““插我┅┅唔┅┅“啊啊┅┅“床上两人则发出原始的嘶喊，“喔喔喔┅┅“啊┅┅哼┅┅“在淑倩淫乱的扭动屁股之后，小刚虚弱的看着身旁白淅的肉体，透过门缝金生的阳具仍醒着，床上琼琳面对房门这头，看在他的眼里宛如一头淫浪的名器，虽侧卧仍展现硕大美丽弧线的乳峰、纤细柔软的腰、丰满的下体洋溢着黑亮的耻毛┅┅金生见机不可失，“刚才如厕还未洗净的双手粗野的搓揉琼琳的乳房，白淅柔软的乳峰随着手掌的压迫变形，金生感动的快要掉下眼泪，“你的肉洞吧！”\n金生邪恶的搓揉阴茎，马眼渗出腥臭的液体，““来源\n“好┅┅好爽┅┅“来源\n“金┅┅金生┅┅来源\n“喔┅┅你┅┅金生你┅┅“大嫂┅┅行行好┅┅每次看到你┅┅扭着屁股我┅┅我早┅┅“你┅┅这禽兽┅┅竟敢┅┅““金生┅┅放开我┅┅“嘿┅┅嘿嫂子你何尝不想┅┅和我痛快的打一炮┅┅琼琳百口莫辩，身为母亲既然跟亲生儿子性交，何况是让丈夫的亲弟弟奸淫呢？““你你饶了我吧┅┅“放┅┅放心吧┅┅这孩子连妈妈都插过了┅┅借我用一下┅┅来源\n““琼琳再度陷入淫靡的时空，金生粗硬的鸡巴和儿子的完全不同，金生插穴的同时伸出魔掌，搔弄淑倩鲜嫩的肉缝，“大嫂┅┅你真行┅┅儿子的 都被你┅┅“喔┅┅“不┅┅“你真坏┅┅金生拔出肉棒，缓缓的下压，“喔喔┅┅“来源\n“小┅┅小鬼┅┅你又想插翻骚姐姐┅┅“好好个淫乱的侄女┅┅三伯的鸡巴好好的┅┅另一边的琼琳在儿子身上使力的扭动细腰，坐姿使鸡巴更深的顶到子宫，坚挺的豪乳也上下跳动，“嗯┅┅小刚┅┅“啊┅┅干、小刚梦见被一大堆女人围绕着，她们赤裸着身体，“小刚隐隐的听到妈妈的呻吟，“妈┅┅喔┅┅原来不是梦┅┅三伯抓紧淑倩的腰，象是行刑般入着她的穴，小刚突然明白整个情形，一定是方才太大声引狼入室，身上的母亲也许已经跟他性交了，他不禁燃起妒火，“啊啊┅┅““啊┅┅唔┅┅“哼喔┅┅“用┅┅“三┅┅三伯你┅┅怎么是你┅┅来源\n“好┅┅好侄女┅┅谁教你的身体┅┅这┅┅你┅┅”\n“没┅┅“太好了┅┅你爸爸生了┅┅一个好女儿┅┅“来源\n“唔唔┅┅啊┅┅“啊┅┅啊┅┅小刚再度将浓浓的阳精注入母亲的子宫，热烫的精液使子宫趐淋，琼琳在儿子身上得到前所未有的快感，“唔┅┅骚浪侄女┅┅三伯┅┅“金生无数的精子在侄女肉洞里倾泄出来，淑倩歇斯底里的揪着床单，““房里一遍狼籍，床单凌乱的皱折中湿了一大片，四人瘫在彼此的身上，来源\n洗完澡来到晒衣间，妈正在晾衣服，象恶作剧般，“坏┅┅坏小孩，“来源\n“““““““坏小孩┅┅只要你喜欢，妈都听你的，““如果这件事被别人知道，““你不担心吗？”妈略带担忧的表情让我爱怜起来，“妈微微一震，“这┅┅“这有什么不好？“你┅┅你这孩子┅┅“\n如果爸爸也跟其他人性交呢？”\n“这┅┅我┅┅““乱┅┅来源\n““这┅┅来源\n““我变本加厉的翻起上衣拉下奶罩，“来源\n““我撩起妈妈的裙子，从股沟后方触摸内裤隆起微湿的部位，妈软绵绵地靠在我的胸前，鼻息沉重起来，手指的压力使内裤陷入肉缝，妈不安的骚动，““坏孩子，妈帮我解开拉炼，小弟弟已经膨胀，““妈迫不及待，我不敢怠慢，“啊┅┅“深一点┅┅来源\n早上阳光炽热，不消一会儿已经汗流浃背，“小┅┅小刚┅┅妈受不了了┅┅“妈┅┅快要被你插死了┅┅“妈┅┅“妈靠着晒衣架娇喘着，““你老是射进来，“那就生下来，“小鬼头，没想到我生了一个这么好色的儿子，连妈妈、女儿都要玩。”走廊传来脚步声，之后，我决心把妈妈好好调教一番，时常跟着她到菜市场，在人潮拥挤的地方抚摸她的肥臀，有好几次在公共汽车上脱去她的内裤，将中指插进肉穴，或者在百货公司的电梯里脱去她的奶罩，来源\n过了不久，妈妈宛然是个成熟的荡妇，除了更妩媚动人之外，爸爸似乎也发觉母亲的改变，““我跟你这么多年了，什么时候享过福，不过就是多几件衣服、““是又怎么样，老娘也不用你一分一毫，这样争吵的画面，““““““要不是你，“这么说┅┅“讨┅┅“嘿┅┅嘿┅┅不过妈有我就可以了，“其实，这大半个月妈妈对我百依百顺的，亦母亦妻的与我享受鱼水之欢，虽然已三十好几，但经过丰富性生活的调息，和以前相比早已判若两人。现在不仅懂得打扮，星期六的晚上，难得家里的女人聚在一块打牌，妈妈、二伯母、三伯母和淑倩姐凑一桌。来源\n““大┅┅大嫂，我不行了，““对┅┅对嘛，大嫂够海量，““我也干，敬妈和二位伯母┅┅来源\n我随后适时的加入，“小┅┅言语之间三伯母丽英解开几颗衣扣，““谁说我醉了┅┅““呃┅┅“我帮你把衣服脱了。”我拉起三伯母的上衣，很快的脱去，她立刻成了半裸的状态，淡绿色的奶罩托着丰满的奶子。右边的二伯母见状也迟顿的脱去衬衫，““哪┅┅““来源\n“嗳呀┅┅你怎么捏伯母的胸部┅┅“嘿嘿┅┅“““死小鬼┅┅你再┅┅再摸摸看┅┅“算了算了，““““谁怕谁，来源\n““好┅┅好吧┅┅四个女人当中，妈的身体成熟丰腴有肉，最属淫色艳丽。二伯母的乳房弧线美丽，尤其下体浓密的阴毛深处令人拔枪就想上。三伯母的身体白淅中透红，富挑逗性的粉红色乳头，“这样不公平，小┅┅“二伯母和三伯母看到我下面坚挺的阴茎，“小┅┅“根本不┅┅“好了，“呃┅┅““不┅┅小刚你先检查二伯母吧！”两人互相推卸，我冷不防就搂起三伯母，来源\n“来源\n许久，“嗯┅┅“““““那┅┅那里不行┅┅来源\n“喔┅┅小刚┅┅你怎么┅┅“我让你摸的好趐淋┅┅“大┅┅“妈缓缓接近我们，俯身吸吮起我的鸡巴，二伯母更吃惊的瞪大眼睛，“淑┅┅淑倩┅┅“妈，“你是不是醉傻了，“妈，“什┅┅什么┅┅住手┅┅你喝醉了┅┅”淑倩姐不顾二伯母的反对，细长的手指捏着乳头，“啊┅┅淑倩┅┅妈很快的把我的小弟弟吹的更硬更大，来源\n“坏小孩，靠在肩上的三伯母微皱眉头，“““那┅┅那我不弄了，免得你不舒服。”“不┅┅“三伯母你怎么了？“我┅┅痒┅┅痒死了┅┅快点┅┅“痒？你哪儿痒？“小鬼头┅┅你戏弄┅┅三伯母┅┅我┅┅啊┅┅“啊，三伯母仿佛遭受电击，身子微微一震，眼框滚着泪水，此时阴洞里天鹅绒般的肉壁早已骚痒蚀骨，“啊啊┅┅我┅┅“这个浪货吧！”\n妈妈手指在龟头上搓揉的很趐麻，马眼渗出些许液体，塞进嘴里抽弄起来。\n“唔┅┅“我两手扶着妈的后脑，不停的往胯下推近推出，这等奸淫母亲浪唇的景观，对二伯母来说，如同强烈的催情剂，谁料，一旁的三伯母象是一头发情的母狗，把我一推握着硬 对准洞口，腰一沉马上坐股吞棍，“来源\n“喔喔┅┅“三伯母┅┅你的穴┅┅很好插┅┅早就想这么玩你┅┅“死小鬼┅┅这么舒服┅┅你早说三伯母┅┅“唔┅┅你伯父┅┅从来┅┅没┅┅““啊啊┅┅““嗯┅┅“嗯┅┅哼┅┅淑倩┅┅喔┅┅你的舌头┅┅“啊啊┅┅“啊┅┅痒啊┅┅乖女儿┅┅“妈，你的肉穴湿透了。”“放┅┅放过我吧┅┅““喔喔┅┅羞死人了┅┅妈卧倒在沙发上，来源\n“喔┅┅“啊啊┅┅干死我了┅┅她一阵抽\n“啊┅┅小鬼┅┅你┅┅你偷袭姐姐┅┅”“嗯嗯┅┅喔┅┅好大的鸡巴┅┅好舒服┅┅”妈放弃自慰，这样抽插约莫二百下，淑倩姐越发狂乱，俯身吸吮妈美丽性感的脚趾，三个女人纠缠一起，“喔┅┅喔┅┅小刚┅┅““啊啊┅┅露华┅┅“哼┅┅哼┅┅喔┅┅“““嗯┅┅哼┅┅转向淫戏中的二伯母，她感到大腿被张开，粗大深紫色的龟头已经顶住穴口。\n“啊┅┅不┅┅不行┅┅小┅┅“““二伯母别担心，你女儿都试过了，“不┅┅不行啊┅┅我从没看过┅┅小孩子的这么大┅┅“啊┅┅啊┅┅““啊啊┅┅“小┅┅“露华我儿子的家伙很受用吧？”二伯母紧绷的眉头逐渐舒解，“喔┅┅嗯┅┅你慢慢插┅┅插得我心都疼了┅┅”来源\n“嗯┅┅喔┅┅好舒服┅┅干我┅┅用力┅┅“骚穴痒死了┅┅快┅┅来源\n“啊啊┅┅太舒服了┅┅“喔┅┅淑倩你舔得大伯母痒死了┅┅嗯┅┅“顿时，也许是纵欲过度，妈担心我的身体，时常去市场买不少补品回来，一再叮咛要我好好蓄精养锐。““““放心，““但是妈妈我就便宜他了，老是在吃饭的时候毛手毛脚的，““““坏东西，“唉呀，““当然啦！”妈妈听我这么说，“来源\n“真的，“““““你这孩子┅┅当心三伯剥你的皮。”淫乱大家庭（今天是个美好的日子。来源\n怒，如果她闭口不提金生是否也会让这秘密隐藏下去？\n长女千惠是个完全继承自己泄色体的美人胚子，无论样貌、万一被这两个女儿发现父母不伦的情事，来源\n“如┅┅如果，她无法将丈夫跟女儿性交的画面组合，以母亲的身分女儿干净的身体绝不能交给丈夫，““呃┅┅““喔┅┅来源\n“啊！“在┅┅“爸、““丽英勉强的堆起笑脸，眼睛直直地盯着千惠勾着丈夫脖子的手，“好了好了，别像小孩子一样撒娇，太阳很大赶快回家去了。”母亲出乎意料的冷淡，“呵呵┅┅好吧！回到家再说。”来源\n“妈，“看你还赖不赖床。”说完继续把头埋进股间，猛然地含弄儿子粗大的肉棒。“喔┅┅妈┅┅好┅┅“这才乖，赶快去刷牙洗脸，妈得去厨房张罗去了，要不然待会儿千惠两姊妹回到家可得饿肚子了！”“对呀！“那么久不见，““啊┅┅痛起来了！”他艰难的走出房间，露华端着刚洗好的衣物向这边走来。“小刚，现在才起床啊！”“小┅┅小刚，你在做┅┅做什么！”衣物像雪花散落一地。露华显得不明就已，““傻┅┅傻瓜，这里是走廊啊！“我管不了这么多了！”“小┅┅“二伯母┅┅你那里让我用一下，借我消消火，一会儿就好┅┅”“啊┅┅真┅┅真要命┅┅”光天化日下遭受奸淫，“喔┅┅他担心露华失神浪叫出来，一手遮盖她的嘴，两人光着下体像狗般交媾，露华雪白的大腿在阳光的照射下，““唔┅┅唔┅┅”来源\n““好啦别说了，快把裤子穿好，“还是二伯母最好。”“都被你那个了，还那么贫嘴，““好哇！小鬼不安好心，“妈妈已经是我的女人了，只要我说她一定肯的。”“““唉唉！““来源\n相反地，他深信性交才是征服女人的方法。从他眼见母亲跟爷爷的奸情开始，父母至上的尊严逐渐崩溃，来源\n小刚更象着了魔般，直直地盯住千惠承继自三伯母的丰胸柳腰，当然，午餐之后，所有人聚集在客厅，““““还有社团活动也很精彩呦！”（这个狐（说到勾引男人我才不会输她们┅┅）““““呵呵┅┅他一定┅┅”来源\n““老色鬼”不禁偷偷的瞄向女儿，淑倩正一脸迷朦暧 、眼光闪烁，（难┅┅（不可能的，（（我不会看错的┅┅）淑倩的攻势奏效，火旺内心反复的矛盾起来，他不露痕迹的悄悄移动眼球，淑倩的两腿象是恩惠般的加大距离，少女芬芳美妙的隆起部位隐藏在大腿尽头，（啊┅┅（真不象话┅┅这番情景淑倩看在眼里觉得甚是有趣，爸爸终于把自己当成女人看待了。随着手部的律动，右乳的衣衫变形扭曲，还有一个人，来源\n原本觉得有趣，淑倩逼真的演出却使她胯间的体温也慢慢的升高，琼琳差点失声惊叫，（啊┅┅是爸爸┅┅）爷爷左手巧妙的透过右手掖下偷袭，（（爷爷皱起双眼，似笑非笑的颤动嘴角，就象战胜的士兵感到优越般，（喔┅┅来源\n（妈的┅┅（啊┅┅看到黑黑的地方了┅┅）淑倩见到爸爸笨拙的掩饰，不禁窃喜，不仅回馈双膝间更大的距离，更拉起裙摆露出一截雪白的大腿，（爸爸快看吧！女儿那里都为你湿了┅┅（（被发现了吗？）心头一惊，抬起头看着四周，所有人的表情显得有些错愕，每个人皆瞪大着眼，但这些摄人的视线并非看自己，（啊┅┅这┅┅这┅┅）火旺不敢相信的看着眼前令人震撼的画面。正当自己坠入女儿裙底的春色中，大嫂在众目睽睽之下俯在爸爸大腿上含弄着他的阳具，而爸爸的手竟也攀在大嫂的乳峰上┅┅客厅一片鸦雀无声┅┅“喔┅┅喔┅┅“啊┅┅“琼琳┅┅老家伙┅┅你们┅┅“大嫂┅┅这┅┅“真┅┅““琼琳！“啊┅┅“妈，你多久没跟爸爸好过了？你看，“呸！“不只是我，“你┅┅你说什么？”“淑倩，你不是想要你爸爸的那根大鸡巴吗？过去给他舔一舔吧！”“爸爸，让女儿给你消消火吧！”淑倩拉开爸爸的裤裆，“淑┅┅淑倩┅┅你┅┅你在做什么┅┅啊┅┅”肉棒感受到女儿嘴唇柔软的包围，来源\n““火旺┅┅啊┅┅露华┅┅怎么你也┅┅？谁┅┅来源\n他回头看看老婆，不知何时小刚已站在丽英背后，掀起她的上衣握着双乳，“妈！你们┅┅“母亲柔软硕大的乳房，在小刚的搓揉紧握下扭曲变形，来源\n“女儿┅┅“这┅┅“千惠姐，三伯母已经是我的女人了，“呸！无耻！你┅┅“““唔┅┅爷爷、金生、琼琳自成一个小团体，“喔喔┅┅“顿时，客听浪声四起，“来源\n（这死鬼┅┅看他那副德性┅┅跟我做的时候从来不曾这样┅┅）奶奶回想过去夫妻间的鱼水之欢，水乳交融的激荡情景，那仿佛如一世纪般遥不可及┅┅看看自己，她心有未甘的抚着胸部，脸庞突然拂来男人的鼻息，尚未搞清楚两片嘴唇已被紧紧的贴住。“唔┅┅唔┅┅”被孔武有力的双臂环绕，奶奶身子无力的虚软下来，““小刚见机不可失，解开奶奶上衣钮扣，“奶奶你的奶子好美呀！”来源\n（（这┅┅这孩子的家伙好硬┅┅好烫啊┅┅）奶奶贪婪的握住年轻的肉棒，““来源\n“啊┅┅”大势抵定，奶奶身子一震，“喔喔┅┅“哼┅┅哼┅┅“好奶奶┅┅孙子┅┅会插得你舒服死的┅┅”“奸奶奶的好孙子┅┅快┅┅“好┅┅“快┅┅快一点┅┅把你整只塞进来┅┅快 烂我的骚穴┅┅”小刚第一次见奶奶如此淫浪骚态，“嗯┅┅““老骚货┅┅你的小穴好┅┅好美┅┅我会干得你爽死┅┅”“小刚用力干她，用力插这只母狗的淫穴，！”\n“对！“喔喔┅┅小色狼┅┅你很会插穴┅┅“骚浪的奶奶┅┅你的肥穴真紧┅┅“嗯┅┅大鸡巴孙子┅┅只要你喜欢┅┅来源\n一直不敢置信而在一旁噤声若蝉的琦玉，体内母亲淫乱的遗传因子渐渐发酵，千惠看到妹妹的眼里闪耀着异样的神采，她可以体会妹妹心口那团火的热度，因为现在伦理道德被撕裂，传统的拘束显得多馀，眼前家族的成员原始露骨的进行性交，而她的视线自始至终不曾离开父亲那雄伟骇人的阴茎┅┅来源\n千惠爱怜的将琦玉的头靠紧颈项，被迫眼见父母加入这场淫交的丑陋姿态，她紧紧地想保护虚弱的妹妹。但是，当琦玉的手安静地攀上她柔软的胸部，“喔┅┅琦玉┅┅唔┅┅”淫乱大家庭（１０）来源\n父亲似乎刻意的背对自己，“啊啊┅┅“千┅┅千惠┅┅你看你爸爸正┅┅来源\n千惠脸上一阵涨红，“喔┅┅用力┅┅再用力┅┅喔喔┅┅“好金生┅┅你女儿的嫩穴痒起来┅┅“哼┅┅浪货┅┅贱女人┅┅来源\n被压在底下的琼琳像妓女般放浪，一旁的爷爷不甘被媳妇就这么含弄射精，“来源\n“啊啊┅┅好痛┅┅啊┅┅不行┅┅\n后庭狭窄紧缩的嫩肉包覆着阴茎，爷爷不顾琼琳凄厉的惨叫，缓缓地抽送着，“啊┅┅\n啊┅┅好痛┅┅不要┅┅喔┅┅喔┅┅”\n““不┅┅喔┅┅喔┅┅爷爷和金生的肉棒分别在琼琳的肉穴及屁眼里抽插，小刚见妈妈被两人奸淫，小刚在奶奶身上占尽优势，“好┅┅好孙子┅┅你饶了奶奶┅┅我子宫快被┅┅你干穿了┅┅喔┅┅来源\n““唔┅┅来源\n“来源\n“喔┅┅龟头经过激烈的摩擦仍然敏感异常，来源\n“二伯母┅┅我我┅┅没这样过┅┅我┅┅“露华吻着琦玉，香舌探入她的口腔，琦玉渐渐的闭起双眼，在花园骚弄的手指让她心神荡漾，她不由自主的伸手握住露华的乳房，柔软坚挺的浪奶入手充满弹性，“来源\n“来源\n“唔┅┅嗯┅┅哼┅┅好舒服┅┅“妹妹骚浪的表情感泄了身旁的千惠，她的手在裙里压着两腿根处，来源\n““骚货┅┅很快的，金生响应般一声咆哮，接着把琼琳两腿大分，深深地把肉棍埋进阴道，“唔唔┅┅射进来┅┅“嗯┅┅哼┅┅好美┅┅琼琳无力倒在沙发椅上任其精液自肉洞、肛门流出，千惠盯着父亲尚未垂软的阴茎，来源\n“嗯嗯┅┅好舒服┅┅大鸡巴爸爸┅┅你干得女儿好爽┅┅“好女儿┅┅你┅┅”\n尽管额头渗着斗大的汗珠，火旺双手紧紧掐着淑倩的趐胸，淑倩蹙紧双眉，双手揪紧父亲强而有力的双臂，阴唇随着抽插翻进翻出，“爸┅┅“来源\n“乖女儿┅┅爸爸要┅┅“好┅┅好┅┅来源\n不知什么时后躺在沙发上喘息的金生，“千┅┅“爸爸，既然大家都抛弃了世俗伦理，现在就让女儿服侍你吧！”“金生是个粗人，千惠嘴里带来的快感令人难以把持，女儿小心而温柔的舔弄香菇帽，马眼不禁溢出淫液，顿时唾液和淫液混合，千惠的口里““来源\n千惠光溜溜的下体谨慎对着金生耸立的阴茎，““喔┅┅“期待已久的性交，来源\n丽英吸吮着小刚的鸡巴，当然也注意到女儿和丈夫的性交，“喔┅┅三伯母┅┅你的口交技术真┅┅来源\n“喔喔┅┅千惠的浪臀动作越来越快，阴户因撞击阴囊“啪滋”“哼┅┅唔┅┅爸爸我┅┅好舒服┅┅“女儿激烈的叫浪，金生听在耳里仿佛是最好的催情剂，腰部不时上挺，千惠的双乳上下摆动着，“唔唔┅┅喔┅┅好舒服┅┅金生双手抓着女儿的屁股，“啊┅┅爸爸┅┅亲爸爸┅┅你真会干穴┅┅女儿的穴好爽┅┅啊┅┅好舒服┅┅千惠忘形的浪叫，“干我┅┅她真想把他完全吞噬，汗水从她晃动的身体涌出，来源\n““爸爸┅┅“好┅┅千惠尖叫着，“我要射了┅┅来源"
    }
  ],
  "tags": [
    "其他"
  ]
}