{
  "id": "book_2788",
  "title": "游魂",
  "author": "未知",
  "cover": "",
  "description": "病假期间，承蒙各位前辈、读友热情关怀，殷切慰问，实不胜感激。现石膏既拆，伤势已愈，除再次申致谢意外，当快马加鞭，以偿文债。前曾允诺，尝试改编倪匡作品，唯通篇改写工程浩大。为节省篇幅，干脆自己掰上一段，...",
  "sourceId": "jisge",
  "sourceName": "集书阁",
  "chapters": [
    {
      "id": "ch1",
      "title": "游魂",
      "index": 0,
      "url": "",
      "content": "病假期间，来源 \n前曾允诺，尝试改编倪匡作品，来源  \n来源 \n行刑的枪兵，卡喳一声拉下了枪机。来源 \n咦！我不是被铐住了吗？来源 \n吴义发觉自己，竟然到了市区大街的马路上。他诧异的东张西望，此时，一辆巴士突如其来的迎面撞来，他闪避不及，被撞个正着，来源 \n愣在当场的吴义，心中闪过一个念头，难道我已经死了？接二连三的车子，不停的穿过他的身体，证明了这个事实。来源 \n来源  \n警察总监张杰，拖着一身疲惫回到了家中，妻子方华殷勤的递上拖鞋。吴义这个案子把他给累惨了，来源 \n望着娇美的妻子，来源  \n来源  \n来源 \n方华作了个怪梦，梦中那恐怖的强奸杀人魔，正粗暴的侵袭她。他大力的捏着方华饱满的乳房，来源  \n来源  \n后庭传来一阵剧痛，来源 \n来源  \n连续几起杀妻疑案，震惊了整个社会，其中又以警察总监张杰的案件，最受人注目。这些案件都有共同的特征，来源 \n但经过精密的体液分析却证明，死者体内仅有嫌犯之分泌物，来源  \n卫斯理、来源 \n卫斯理与白素深知，张杰方华夫妻感情良好，绝不可能有杀妻的情事。但各种证据却又显示，来源  \n黄堂走后，俩人分别出门集相关资料，来源 \n卫斯理对一般刑案，本就没什么兴趣，此次冲着张杰勉为其难的参与，来源 \n白素翻阅案卷，将资料分门别类整理好，已是午夜时分。来源  \n常年练武的白素，赤裸的胴体于柔媚中，另有一种刚健婀挪的特殊风味。来源 \n只见她白嫩饱满的双乳，丰润坚挺；修长结实的双腿，圆润光滑；香臀丰耸浑圆，来源  \n沐浴中的白素，忽然感到身后有人窥视，她一个回旋转过身来，来源 \n白素斥道∶“来源 \n满脸充满猥亵淫秽的卫斯理，暧昧的笑了笑并不回答，来源 \n白素见他阴阳怪气的模样，心中又好气又好笑，当下佯怒道∶“来源 \n来源 \n来源 \n卫斯理的动作大异平常，显得粗暴而鲁莽，但在习于过去模式的白素而言，却感到有种另类的煽情滋味。卫斯理一边抚摸亲吻，一边将她拦腰抱起，来源 \n情欲渐起的白素，闭目仰卧在床，来源 \n来源 \n卫斯理一反常态，大展口舌之技，这是以往从来没有过的情形。灵活的舌头，游移在方寸之地，竟是花样百出，推陈出新。白素一向淡然的欲情，如今却像火上加油一般，猛的燃烧了起来。她双手紧紧的拽住卫斯理的头发，下体也无意识的扭动挺耸，保守的她，难得的发出了愉悦的呻吟。\n突地她全身一颤，娇躯紧缩；卫斯理竟然舔 她的肛门，这是从所未有的全新经验。她既感奇怪，来源 \n卫斯理凶猛粗暴的，来源  \n阳具划开娇嫩的阴唇，来源 \n此时卫斯理忽地叹息道∶“小 真是又嫩又紧！来源 \n白素闻言大吃一惊，这根本不是卫斯理的声音与口气，可是却又明明出自卫斯理之口，来源 \n她惊道∶“你是什么人？”来源 \n白素见情况危急，也顾不得自己的动作，会加速阳具的进入。来源 \n白素只觉火热粗壮的肉棒，贯穿下腹，那股趐趐、痒痒、来源  \n。\n来源 \n来源  \n眼前一亮之下，只见白素赤裸身体，正全神戒备的望着他；而他手中扯下的东西，竟是白素的粉红三角裤。他莫明其妙的愣了会，愤愤的道∶“来源 \n来源 \n卫斯理火冒三丈的道∶“来源 \n折腾了半天，终于搞清楚状况，卫斯理不禁暗暗心惊。这是什么鬼玩艺，竟能占用自己的身体，意图奸淫白素，并且还几乎得逞。来源 \n来源 \n卫斯理慎重其事的道∶“素，在这件事未了结前，来源 \n白素见他醋劲十足的模样，心里不觉甜丝丝的感到温馨，当下俏皮的道∶“来源  \n卫斯理急吼吼的道∶“那怎么行？来源 \n白素就想看他吃醋的样子，于是又笑逐颜开的道∶“你倒说说看，来源 \n来源 \n游魂〈来源 \n吴义发觉自己，越来越需要依赖人体，来源 \n他知道自己已经死亡，但却丝毫感受不到死亡的滋味；他除了没有实际的形体外，来源 \n但是寻找人体寄宿，却也并不简单；他一定要趁对方昏迷或沉睡时方能进入，对方一清醒，他立即会被一股大力弹出。他也试过侵入清醒状态的人体，来源  \n不过有一点却让吴义相当的满意，那就是再多的警察，也捉不住他，而他却可利用鬼的特长，来源 \n“嘿嘿！象那个警察总监张杰，现在就很惨，被当成杀妻嫌犯。来源 \n但不一会，他又感到十分的懊恼。“来源 \n原来这鬼也和人一样，没见到的事，他同样也不知道。那天白素一招“来源 \n来源 \n卫斯理、白素夫妻二人，将自身遭遇及推测结论告知黄堂，黄堂大为惊讶。他耽心的道∶“来源 \n吴义对白素迷人的身体，确实无法忘情。那棉软坚挺的双乳、浑圆润滑的美腿、来源  \n那天濒临突破边缘时，他透过卫斯理的下体，来源 \n卫斯理、白素与警方密切配合下，虽对吴义的状况有相当的了解，但面对这个虚无缥缈的游魂，却仍是不知从何下手，当前唯一的办法，来源 \n但俩人的个性，都不是甘于被动的；因此连袂拜访了，来源 \n来源 \n钟馗道∶“以捉鬼而言，最困难的就是游魂。人有户籍，鬼有鬼籍，阴间也和人世一样。而游魂就如阳间的无户籍人口一般，来源  \n来源 \n钟馗道∶“其实你们也不用太过耽心，来源  \n吴义这两天藏匿在浴室之内，可真是眼福不浅。白素如厕、沐浴的妙姿，来源  \n他试图上去搂抱抚摸白素，但却都穿过白素的身体，而无法如愿。他心想∶“来源  \n机会果然来了，这晚白素沐浴，她的宠物北京狗花妞，在浴室门边呜呜的直叫。白素开门放它进来，花妞兴奋的直往她身上磨蹭。白素爱怜的抚摸它，来源  \n来源 \n白素蹲下替花妞洗澡，赤裸的下阴正对着花妞，花妞在本能驱使下，自然的向发出异香的部位舔 。来源 \n她娇声斥道∶“小坏蛋！来源 \n花妞凭着兽性的直觉，知道主人并未生气，来源  。它越舔越来劲，面泛桃红的白素，也逐渐领略到个中滋味。\n白素一向疼爱花妞，简直就当它是子女一般，就是晚上就寝，也经常搂着它一块睡。由于卫斯理经常赴世界各地，寻怪访异，花妞实质上已成为白素最亲近的伴侣。平日里，花妞也会往白素下体嗅嗅闻闻，但像这般贴近，来源  ，那还是头一遭。\n白素那里知道，此刻眼前的花妞，来源  \n化身为花妞的吴义，一面舔着那娇嫩的下体，一面在心中赞不绝口；他真是从来没见过，来源 \n白素的阴唇，来源  ，他以高超的技巧，配上狗儿粗糙的舌头，使白素全身，起了一阵阵的快意颤抖。\n飘飘欲仙的白素，一方面耻于自己，放纵的让花妞舔 ；另一方面，来源 \n来源 \n他心中不禁暗骂∶“他妈的！来源   大概比牙签也粗不了多少，他妈的┅┅。”\n端庄正经的白素，岔开嫩白的大腿，放任的让花妞舔着。她从来没想到狗儿的舌头，来源  \n白素起身清洗下体，见花妞仍是紧挨着她磨蹭，不禁斥道∶“来源  \n花妞咿咿呜呜的低声哼着，似乎在说∶“来源 \n白素不再理它，来源 \n来源 \n白素心想，卫斯理不知又发现什么怪事，走得如此匆忙。来源  \n这几天吴义的游魂，来源  \n她开了冷气，来源 \n白素晕倒在书桌旁，花妞惊疑的嗅着她的面庞，此时管家老蔡走了进来。花妞冲着他直吼，老蔡一脚将它踹的老远，来源 \n他低呼∶“小姐，来源 \n来源 \n由于白素居家并未穿着胸罩，来源  \n老蔡伸手揉捏了起来，那股滑腻棉软的触感，来源 \n毫无疑问，吴义又附在老蔡身上了。他贪婪的猥亵白素丰美的乳房，又揉、又捏、又搓、又吻，舔舔唆唆的弄了一阵，来源 \n他拉下白素的长裙，那双浑圆洁白，丰润匀称的美腿，便裸露在他的眼前。此时白素身上，仅馀一条棉质的白色三角裤，遮掩住诱人的私处。美腿玉足再次吸引住吴义，他目标一转，来源 \n白素醒了过来，但是全身酸软，无法动弹。来源  心，又奇怪，也说不出是难过还是舒服。她勉强挪动头部，看见老蔡正津津有味的，舔着自己的足部。她啊的惊呼出声，老蔡抬头露出邪恶的眼神，缓缓的站了起来。\n一向熟悉亲切的老蔡，如今在白素眼中，显得可怕万分。他一面狰狞的冷笑，一面脱下裤子两腿分开，站在白素上方。六十多岁的老蔡，来源 \n有意羞辱白素的吴义，蹲了下来，那根庞然大物，也瞄准了白素的樱唇。来源 \n吴义一听，倒也不敢造次，他嘿嘿一笑，将白素两手上提压住，来源 \n来源  \n此时吴义扶着老蔡的北方大肉棒，来源  \n来源 \n来源   心。她不由自主的张嘴欲呕，吴义顺势便向她口中顶了进去。\n龟头接触到温暖的口腔，来源 \n吴义一见兴奋万分，他哈哈大笑的道∶“你前面既然不肯让老子搞，来源  \n来源 \n来源  \n白素只觉火热硕大的肉锤，不停的撞击自己的后庭，来源  \n来源  \n屡攻不下的吴义焦躁无比，来源  \n此时白素亦已恢复了行动能力，她翻身而起，来源 \n她心想∶“来源 \n来源 \n钟馗听了白素的叙述，开口道∶“照你的说法，来源  \n俩人进入屋内，这钟馗东嗅西闻，一下就锁定了浴室。他在门窗上都贴了符，来源  \n卫斯理一面抚摸白素柔嫩的乳房，一面说道∶“你也真是鬼灵精，来源 \n白素笑着道∶“这又有什么想不到的？你们男人到最后，来源 \n来源 \n白素娇媚的道∶“来源 \n《来源"
    }
  ],
  "tags": [
    "其他"
  ]
}