{
  "id": "book_2572",
  "title": "猛上女友的朋友",
  "author": "未知",
  "cover": "",
  "description": "由于我们在学校外，离宿舍还比较远，所以晶晶提议晚上就送到她在学校外租的地方去睡一晚。晶晶大二上半学期就嫌宿舍太闹，在外面租了房子。有时候在宿舍住，有时候到外面住。我一想也好，于是就把妍妍抱到了晶晶家了...",
  "sourceId": "jisge",
  "sourceName": "集书阁",
  "chapters": [
    {
      "id": "ch1",
      "title": "猛上女友的朋友",
      "index": 0,
      "url": "",
      "content": "由于我们在学校外，离宿舍还比较远，来源\n\n在路上，来源\n开了热水器，来源\n我进去一看，不由傻了，妍妍全裸着躺在浴池里。而晶晶的薄衬衣基本上也全湿了，来源 \n我 因为衣服上被弄脏了，所以也已经在客厅里脱去了，只留下了内裤。当时我也酒喝多了，看到妍妍的身体，立刻受不了，来源\n\n过了一分钟，来源\n两个人把妍妍扶到晶晶的房间躺下。来源 \n因为要等衣服搅干，所以我和晶晶两个人就在客厅里看电视，来源 \n碰巧那天，来源  说什么。来源  乳房，来源 \n女孩终于啊的一声，张开小咀，伸出舌头，来源\n\n这是第一次，来源 \n平时我一般要陪妍妍上晚自习到十点多，然后送她回宿舍。来源 \n所以，有时候，晶晶会在八点多的时候，离开自习室，然后回头给我一个眼色，来源 \n然后跑到楼下，来源\n\n有时候，我会在七点后，来源\n\n这样的话，来源\n\n有时候，来源\n\n我感觉和晶晶愉情的时候，来源\n\n每周六，我要参加学校的乒乓球队的训练。这个时候，妍妍一般是会上街买点东西。于是我有时候会和让晶晶到我们训练的地方来找我。来源 \n一般情况下，我们一个星期能一起偷偷做四到五次。来源\n我提出我们到郊外的青山公园走走。晶晶同意了。来源 \n我们打车到了青山公园。这里离学校比较远，由于还没有开学，来源 \n今天我才有时间仔细的看着这个伴侣。女孩和妍妍差不多高。大约也有170左右， 大约九十八斤左右。抱在怀里，又柔软又轻巧，当然对我这个体形，来源\n\n女孩的三围非常诱人，来源 \n拉着女孩到面对夕阳的那面山坡，钻进了树林。看看左右无人，就找了一块干净的石头坐下，来源\n\n因为假期的原因，我有一个多月没有做过爱了，所以这一次非常快就射了出来。来源 \n不 到十分钟，由于感觉到了女孩没有穿内裤的大腿和臀部在自己大腿上的磨擦，我的下身再次立了起来，于是我对准位置，来源  于位置的原因，只能进去一半左右，就是这样。女孩也已经坚持不住。来源  插我啊。\n听到这里，我没有办法坚持了，一翻身，让女孩趴在了石块上，而我从后面开始进攻。这下好了，位置放好后，我就可以深深的把阴睫全 部插到女孩的阴道里。来源  力的插了两三下，女孩就到了高潮，啊啊的叫着，来源\n\n手，伸过前去，一下子握住了女孩的一个软软的乳房。用力的捏起来了，不到二分钟，女孩身体再次恢复了欲望。来源  孩的屁股上，发出很大的声音，最后，我们两个人一起达到了高潮，抱在一起，一起瘫在了石块上。\n收拾好，休息了一会儿，我们两个打车回学校，来源\n\n那 天晚上，我们试了所有的姿式做爱。试了乳交，让女孩用大腿夹着做。来源  龟头。自己用双手不停的挤压着自己的乳房来磨擦我的下身。我感觉好爽。尤其看到女孩动情的忘着我，小咀却在为我口交。\n而晶晶更惨，高潮了十二次。第二天，都起不了床了。来源 \n开学后不久，在有一次在晶晶偷情的时候，不小心被妍妍撞到了，起因是晶晶八点多离开教室的时候，把两本书忘记了，妍妍于是给她送过去，来源\n\n我和妍妍分手后，我还是经常照顾她。她也不太会拒绝我请她出去吃饭和聊聊天的要求。只是我们更自由了，来源\n在这样的关系。我想她是离不开我给她的美好感觉吧，于是我可以半公开的和两个女孩交往了。"
    }
  ],
  "tags": [
    "其他"
  ]
}