{
  "id": "book_1595",
  "title": "控诉",
  "author": "未知",
  "cover": "",
  "description": "本文源自九四年香港某色情杂志，真实程度非经证实。我叫做阿萍，写本文时廿三岁。在大陆，我都算得是个知识分子，读过高中，离开学校之后，亦做过几份不同的职位，可惜每份职业都是赚不到多少钱，对我来说，的确与理...",
  "sourceId": "jisge",
  "sourceName": "集书阁",
  "chapters": [
    {
      "id": "ch1",
      "title": "控诉",
      "index": 0,
      "url": "",
      "content": "本文源自九四年香港某色情杂志，来源 \n我叫做阿萍，来源 \n在大陆，我都算得是个知识分子，来源  \n来源 \n上海嘛！是中国最有名气的大都市，很少有人不知道的，而我生长在上海，来源 \n不过，来源 \n虽然说，来源 \n近年来，上海姑娘做“来源 \n来源 \n当然，要出国，来源 \n正所谓有钱能使鬼推磨嘛，在一片“向钱看”声中，来源 \n我算是幸运，一九九二年，我获得“来源 \n不怕讲，我们名义上是“留学”，骨子里是借留学日本之便，来源 \n原来日本男人对东方女性很感兴趣，来源 \n而这些娱乐场所，是集中在东京的新宿，那里的酒吧、来源 \n在日本，女性是没有地位的，来源 \n至于我，是在一家歌舞厅当“来源 \n那家歌舞厅生意旺盛，来源 \n他们袋子里有的是钞票，就随便可以召“歌舞女郎”来源 \n来源 \n你可以想象得到，“出钟”当然不是吃吃喝那么简单，来源 \n作为一个知识分子，来源 \n一则，我来自上海，言语不通，又无亲无故；二则是个“黑户”，即是说，我并无居留证，是个“来源  \n在这种情形之下，来源 \n我已经二十三岁了，对于男女间的事，来源 \n第一次同“日本男人”出街时，来源 \n这是个中年的日本男人，外表也颇斯文的， 说他是个出入口商人，和他见面时，他还是彬彬有礼的，来源 \n他叽叽咕咕一番，然后粗暴地撕破了我的衣服，来源 \n跟住他发出狞笑，用力捏着我的乳房，来源 \n进一步，他竟然一声不响的，来源  \n这时候，他爬在我的身上，用他又硬又钝的家伙，向着我最敏感的地方冲进去，这一阵子，来源 \n“救命！救命呀！”我叫着痛！来源 \n来源  \n来源 \n来源 \n从此之后，来源 \n直到有一个晚上，来源 \n我们这一批有几个来自中国的女孩子，来源  \n来源 \n“来源 \n就在这时候，一个凶神恶煞的警察走过来，不由分说，就一巴掌把我打得跌倒在地上，然后又将我揪起来，打了一拳，我面部流血，我忍着痛，没有求饶，来源 \n那警察就变得更凶了，他大力用皮靴狂踢我的腹部，令我痛得口吐自泡，来源 \n来源  \n来源  \n来源 \n来源 \n来源 \n天呀，来源 \n我的律师有向日本当局要求赔偿，并追究刑事责任，来源 \n有人私下对我说∶“中国人在日本被欺负、被殴打，来源 \n令我心痛的是∶在声声中日友好声中，中国人受到这种待遇却得不到保护，来源 \n– 来源  –"
    }
  ],
  "tags": [
    "其他"
  ]
}