{
  "id": "book_434",
  "title": "淫魔大都市",
  "author": "未知",
  "cover": "",
  "description": "“呀啊啊!!”少女的惨叫声响彻新东京的暗夜，使我不由得停下脚踏车，回头一望。   “达夫！去为我买东西！”当母亲叫我出去，就在骑脚踏车到药房的途中。那天晚上．．．我见到了超乎想像的可怕景象。从少...",
  "sourceId": "jisge",
  "sourceName": "集书阁",
  "chapters": [
    {
      "id": "ch1",
      "title": "淫魔大都市",
      "index": 0,
      "url": "",
      "content": "“\n少女的惨叫声响彻新东京的暗夜，使我不由得停下脚踏车，\n“达夫！去为我买东西！”当母亲叫我出去，\n从少女的声音判断，她目前的遭遇可能很糟，\n双脚就像被地面吸住一样，\n少女被露着奸虐目光的男人围住的样子，\n“哈啊！\n害怕到极点的少女，\n“救我….\n“哎呀！是应兰学园的千金小姐耶！\n相对于我这种吊车尾考上的苯男生，学校的女孩子们，每个都长得又聪明又可爱，\n“得去救她！”我热血沸腾，\n“至少要为她做些什么！”\n我放眼四周，想寻找能充当武器的东西，\n新东京近年来变得越来越科技化，\n贫富差距明显扩大，\n这些男人，\n“如是逃不掉的啦！\n“嘿嘿嘿！\n“不要！\n“\n“不、不要！\n“唔畦！\n如同捏挤软糖般，男人用力搓揉乳房，\n“\n她的脸颊因心中的羞耻而涨红，\n美里的裸体，\n她摇动的洁白乳房，\n“受不了了！\n“啊，\n粉红色的小乳头，\n“啊啊啊….\n男人们的舌头来回一撩一撩地舐，\n“啊啊！\n男人的舌头，\n“不行！啊啊！\n男人似乎不能满足于光粗暴地吸吮美里胸部，\n美里被压住不能动弹，\n“\n一个男人由后方架住美里的肩膀，\n“\n然后，另一个男人用手指翻开美里的秘贝，\n“呀！\n“啊，\n“\n“这次的还是处女耶！可是看看，\n舔着美运秘贝的男人一说完，另一个男人马上拉下长裤的拉链，\n“\n“来源  ”\n美里拼命闭紧嘴摇头抵抗，但是男人抓住她长长的头发，\n“\n“叫啊，真舒服！\n男人推动着腰部，肉棒在美里的双唇内抽插，美里的唾液，\n“\n“\n粗大的肉棒在嘴中穿刺，\n“\n美里再次拼命用力抵抗，\n“啊，不要….\n美里吐出口中的肉棒并且大叫，\n“\n男人把高翘的肉棒，\n“噫呀～痛痛、好痛啊….\n“啊啊，\n“哈哈哈哈哈！怎么样?\n“\n“啊啊啊啊….请，\n每当男人激烈突刺，\n“啊啊啊….\n美里的下半身被抱住，\n“湿成这样，就算是第一次也能顺利插进去哪！\n“啊，\n每一抽插，\n“啊啊，\n美里不但嘴里含着肉棒，秘贝被插入钢棒，\n“嗯咕，\n“啊啊….嗯咕，\n“\n“\n“我要疯狂的插到射精为止，\n“呀啊！啊，\n“啊啊….\n“唔噫….\n这时，\n“呀啊！嗯咕，\n“哇塞!\n男人将屹立的钢棒，\n“不、不要！那里是….\n男人把坚挺膨胀的肉棒，\n“\n“\n“嗯咕，\n美里难过的含着男人的肉棒，没多久，\n看得出来，\n“唔唔….受不了了！给我全部喝进去！\n“呜咕咕咕！\n无法承载的多量精液，\n“\n“哦，我也….\n躺在下方，被美里跨坐着的男人，\n“不、不要！\n美里摇着腰抵抗，\n“呀啊….\n同时，\n“\n几乎被美里后仰的洁白背部覆盖住的男人，\n多量的白浊精液，\n美里的全身，\n“拜、\n“\n美里的抗拒毫无作用，\n“叫啊，\n沾满男人精液及自己黏液的秘唇，\n“嘻嘻嘻….\n“那、\n由于发生了许多被不寻常方式所杀害的事件，\n脚就像被钉住般，\n原先胀痛勃起的股间，\n“呀啊啊！\n美里运动着僵硬的身体，拼命想逃离，\n“会让你更爽的！”美里的脸上，\n“\n美里身上全祼，\n“\n妖怪们抓着美里的脚，以像蛇一样的肉棒，\n“啊咕！啊，\n“嘻嘻嘻….怎么样？\n怪物们蜿蜒扭曲的大肉棒，每在美里的秘壶内出入，\n“\n和我的肉棒不断缩小正好相反，\n“啊、啊啊….哈啊、\n“噫….\n我的脑海运浮现出这种无聊的想法，\n“嗯，差不多可以了，\n一个怪物这么说的同时，从其他怪物的口中，\n怪物们想要得到人类在达到快感时，脑里渗出的内生性蛋白价，\n“\n“\n“唔呼呼呼….\n“等一下！”\n抬头一看，\n“你这小鬼想干什么….\n怪物们望着美少女，\n“也乖乖地献出你的蛋白质吧！\n她拿掉帽子，脱掉大衣的身上，\n为挺的乳房及全身的肌肤，\n冷酷的眼神，\n完美的曲线，\n“\n“哦，\n“好像很可口嘛！\n“既然是妖怪，\n“什么！！\n“有本事就来吧！\n“\n“呜嘎嘎嘎!!”\n“\n“咕叽叽叽叽!!”淫魔们的眼珠也散落一地，\n“\n“\n“\n说着说着，\n“你、\n“没错！\n一说完，美少女眼睛灿燃一闪，\n“想舔我，\n“\n青光的能量瞬间炸开，卷起一阵巨大爆风，\n“你一直躲在那边吗？”\n“算了！对方是淫魔，\n说完后，\n我有如大要初醒，\n只有一轮皎洁的明月，\n与淫魔战斗的美那，\n转开莲蓬头的开关，\n舒服的感觉，\n“唔，工作后冲个澡，\n“\n“算了，\n“美那姐姐，\n同样为吸血鬼一族，美那的干妹妹．\n爱音非常倾慕美那，\n“\n“\n美那连忙摇摇手。“\n爱音不理美那，\n“啊，爱音，不要….\n“哎呀，\n“\n充满蒸气的浴室中，\n“啊啊，\n“美那姐姐的奶奶，果然比背部还疲劳呢！\n爱音边吸美那的乳头，\n“嗯，\n“爱音….\n“\n“\n要音仿佛很兴奋，\n“啊，\n“\n“\n美那的秘贝更突出，\n“\n爱音的手指深入秘贝的最深处，\n“\n“哈啊….\n“嗯嗯，\n“爱音….哈啊、哈啊….”\n“\n美那仰躺在地上，秘贝被爱音以手指分得更开，并伸入舌头，\n“\n“\n爱音的舌头撩开美那的花瓣，\n卷起的舌头，\n“啊啊！\n“啊、爱音….\n黏液不断不断滴落，\n美那的背部更加后仰，忍受不住舒服的感觉，\n“哈啊….\n“啊，\n“所以，我说不要….\n美那想叫爱音停下来，\n“\n“那、\n“\n“\n“那、那是….你….\n“可是，未免也太湿了，\n爱音把莲蓬头的水量开得更大，\n“来吧，\n“啊啊….\n“\n“\n秘贝上小小的颗粒逐渐充血，\n“\n“\n“\n“不、不行….\n美那潺潺流出的黏液，在爱音手指的抽括下，\n“要去了吗？美那姐姐！”爱音手指更用力，\n“\n美那秘壶最深处的粗糙肉壁，\n“这里，\n“\n美那已无力抵抗，\n“\n“\n“我….我也….\n可是，她所有的行动，\n美那看到暗音，心想终于得救了，\n“啊，暗音！你、\n“帮我把这家伙….\n美那难受的对暗音说着：直到这时，\n“嗯唔….”\n“\n“暗音，给她一点教训….”\n“\n“就是这样！\n但是，\n“呀….”\n“暗音！干得好!!”\n“\n“噫呀….\n巨大的马达声回响在浴室中，\n“\n“哎哟！暗音真是的!\n“\n“啊啊….\n“暗音！\n“叫啊，啊啊….\n暗音更用力的以电动阳具搅弄自己的秘贝，\n“啊啊啊，\n“那么，我也来帮个小忙….”\n暗音大声哀嚎。“\n爱音回头望着美那，\n“\n明显的看得出来，\n“会很舒服的唷！”\n“不、\n“不要这样说嘛！\n“住、\n“唉，\n“\n爱音边舔着冰淇淋，\n“\n美那正觉得惊讶之时，\n（\n“美那姐姐的那里有血的味道嘛！\n爱音兴奋的舐着嘴唇说道，\n“他们，给我差不多一点！”\n“\n“\n“可是….\n“\n“\n“啊啊，真是拿你们没办法！\n“\n爱音和暗音两人手牵手，\n“\n“\n“黑暗之力，\n“\n“\n爱音精神奕奕地回答，三只蝙蝠振动翅膀，\n远无边际的黑云满布天空，使得眺望这儿的人，\n淫魔以大量饮用抽取自人类在得到高度快感时（特别是性交），脑中产生的内生性蛋白质，\n从他纤细而俊酷的侧面来看，\n“\n“来源  ”\n一位穿着紧陷入股间的皮制内裤的女仆，\n她的脸庞细削而匀称，\n“\n女仆走到卡尔马面前，\n“\n“\n“\n“\n光是暴露在卡尔马的眼前，女仆丰腴的肉缝中，\n“\n“\n卡尔马露出奸虐的笑容，\n“啊啊啊….啊啊….”\n“\n卡尔马发着命令，并用手掌在女仆的丰臀上重重打了两下，女仆马上用两手撑住桌子，\n“\n“卡、卡尔马大王….我….\n女仆抵受不住快感的冲击，自己拉起黑色的漆皮胸罩，\n“\n卡尔马用两根手指，更加深入的侵入女仆的秘壶中，\n“哈啊….卡、\n“\n卡尔马轻蔑地问着女仆，\n“没错！唔咕咕咕….”\n“\n很快地，\n“\n卡尔马命令女仆，\n女仆缩起脸颊强力向上吸起，\n“\n她的左手，轻柔而体贴地握住另一根肉棒，\n“技巧不错嘛！\n“\n女仆的脸上被卡尔马的分泌液，及自己的唾液弄得滑滑黏黏的，\n每当重覆上下吸吮粗大肉棒时，\n卡尔马也回应了女仆的兴奋，他紧绷起血管，让手指涨大成为阳具状，\n“\n“啊，啊嗯嗯啊….\n女仆的身体，\n“\n卡尔马说完后站起身，\n他拿起旁边的细皮鞭，\n“\n受到卡尔马鞭打的女仆，\n“啊啊！\n女仆将双腿张得更开，\n“哼哼，\n“\n“\n女仆的火烫肉壁溢出蜜汁，\n“啊，\n也许是女仆的秘壶太紧了，当卡尔马每一强力突刺时，\n肉唇吞进肉棒，\n“唔唔….\n“你也变成我们的同伴了….\n“啊….\n“啊啊，卡尔马大王的..肉棒..插到..\n“啊啊啊啊!!\n“啊，\n“还有另外一根，\n“卡尔马大王..另一根肉棒..\n卡尔马将另一根阴茎，\n“\n“噫呀呀～\n女仆的身体，\n卡尔马的两只肉棒，在女仆扩张得快裂开的秘唇，\n“啊啊….\n“\n“\n水晶中映照出卡尔马的丁级淫魔们，正在街上强奸女孩子，\n“哈哈哈哈哈!!\n淫魔们平时化身为人类，巧妙地接近女孩子，\n“我要征服全世界，只是时间早晚而已….\n淫魔们以强奸为手段，\n“\n水晶中，\n“这是….可恶!!”\n“她、\n卡尔马的眼睛闪烁了一下。“\n水晶接着映照出美那痛宰淫魔后，\n“\n“来源  ”卡尔马的脸色阴沉起来。\n与卡尔马身体连结着的女仆颤抖着，\n“\n“卡、卡尔马大王….请….不要停….\n状似中毒患者的女仆，\n水晶中仍然映照出不断杀死卡尔马的走狗淫魇，\n“\n卡尔马的眼睛怒睁，\n“\n“\n只见卡尔马的钢棒体积瞬间暴涨，女仆一声哀嚎，\n“\n“呀啊啊！\n“\n卡尔马的火红瞳孔，\n“\n直到卡尔马的心腹赛鲁曼开口，\n“啊啊啊….\n“\n“\n“\n女人们的呻吟及喘息声，\n“呼呼呼呼呼….真是美妙的景象….”\n“卡尔马大王，\n在漫长石头尽头处的房间中，\n“卡、卡尔马大王….请饶过我….\n麻绳深陷进女人的肌肤中，\n“\n“\n卡尔马一问，赛鲁曼立刻举起皮鞭，\n“哈啊….”\n“\n“\n“我要马上就能使用的….”\n男女共七人的淫魔，\n“\n“抽出这女人的蛋白质，\n“不、不要！\n“卡尔马大王！\n“让她舒服一点！\n“\n满是赤红肿痕的身上，\n“\n“\n“神圣的淫魔，\n卡尔马将雪茄丢掉，\n“\n调教室中，\n“\n“\n“啊，啊啊啊!!”\n“\n“啊啊啊….\n“呜呜唔唔….\n“咿咿….\n淫魔们陆续现身，\n“啊啊….\n“\n当女人因淫魔的魔力而开始得到快感时，\n“要想办法….\n“唔唔….\n卡尔马将自己深深埋进由一群裸体女人所架成的椅子中，\n“我要….\n“美那姐姐，\n化身为蝙蝠的爱音，\n“你别管！\n满天的星星，\n“\n美那向爱音两人使了个眼色，从房间的窗户外头，\n“\n“哇哦!!好像很好吃!!”\n“看吧，\n“可是，\n“嗯….算是有点缘份吧….”\n“\n“唔….\n“啊，\n“\n“\n“呃….窗户有开吗？”\n达夫房间的窗户，\n“\n“\n“有男生的味道….”\n房里有布满灰尘的书桌，\n墙上贴着海报，\n在这七张塌塌米左右大小的房中，\n“嘿！”\n“嗯….\n“\n“\n“虽然是吸血鬼，也是有梦想啊！\n爱音的眼睛望着远方，\n“然后，然后….\n“受不了….有完没完哪！\n美那冷冷的讽刺着，\n“\n“\n“嗯嗯….”\n“你怎么了？\n书内满满的，\n“呜呀！”\n“\n爱音的眼中不只冒出满天星星，\n“笨蛋！\n“哈啊，\n“来吧！\n“\n“\n“什么嘛!\n“\n“啧….\n美那使劲站起身。“\n“是的!!”\n美那拔开小罐子的软木塞，让达夫吸入里头的烟，\n爱音张开双腿跨坐在达夫脸上，\n暗音则坐在地上，\n已经兴奋的秘壶内，\n“\n“暗音，\n美那拉开熟睡中的达夫双腿，\n“\n“啊嗯….\n“啊啊….\n暗音也摇摆着腰，\n“\n暗音的秘贝中流出的黏液，\n含着宝贝的美那，\n“嗯咕，嗯咕….差不多百分之四十了….\n逐渐胀大的阴茎上，沾满了美那的唾液，\n“嗯嗯….啊….嗯啊….\n美那将龟头整个套进口中，\n“唔嗯….”\n“\n“\n“唔….”\n“嗯嗯….\n美那将达夫的肉棒含到根部，运抵喉咙深处，并用唾液上下滑动，达夫的肉棒变得赤黑而坚挺，\n美那缩起脸颊，以小小的双唇用力向上吸起肉棒，\n“嗯咕…嗯咕…嗯嗯….勃起率百分之一百二十….\n“嗯哈嗯哈….\n“\n“\n“\n“\n美那一放开嘴，\n啾叭一声，\n“真美味！”\n“\n爱音与暗音犹自兴高采烈，\n“这也不只是好喝，\n“美那姐姐，喝完也后还有事吗？\n“真是的！\n“\n“\n“啊，肚子好饱，来源  GO！”\n“\n不知为何，\n“\n爱音戴上大帽子和太阳眼镜，\n“呀，\n“美那姐姐，已经早上了，\n爱音一边在穿衣镜前换衣服，\n“嗯啊….\n“你干嘛!?\n“\n“废话！我又不是瞎子！\n“\n“姐姐，我们穿上制服，\n“\n“\n“吸血鬼干嘛去上学？\n爱音愣了一下，\n“\n爱音脱掉帽子，\n“\n“\n“\n“你看吧！\n“\n爱音垂头丧气的咕哝着，\n“\n“早啊！\n“….”\n“暗音，我们大概是不可能了….我们是夜行性动物，\n“\n“你、\n“\n“\n“哇!\n“\n对走进应兰学园大门的爱音与暗音来说，\n三三两两的学生们边走边谈笑，\n“\n“\n“这就是我梦寐以求的！虽然身为吸血鬼，\n不过，\n“\n“啦啦啦….\n“\n二人一面拖着沉重的步伐，\n“\n“哈啊，\n“\n“……..!!”\n“\n“\n“\n“\n“不、\n本来可爱的爱音却伸出尖锐的獠牙，\n“\n爱音怒瞪着校舍顶端的十字架，\n“\n“\n“\n可是爱音好像什么也听不见，高举双手，\n“\n“\n“\n突如其来的爆炸，\n“\n“\n学生们围着两人，\n“\n暗音一反沉默寡言的个性，\n“啊哈哈哈哈……..没、没什么啦！不要紧啦！\n虽然学生们议论纷纷，\n“\n“爱音，我、\n暗音再次撑开大阳伞，\n“喂……..暗、\n“等一下再”好好地”\n“\n“\n“\n接着，\n这时候，美那则身穿长大衣，头戴宽边帽，\n“\n“\n“\n“\n少女的嘴角流着唾液，\n“\n“\n为了避免引起注意，\n巷内笼罩着妖异的气息，\n“可恶的怪物….\n“\n“\n“\n“\n“\n“鸣叽－!!\n“\n年轻人忍不住原形毕露，\n“\n“\n美那全身只剩皮真的内衣裤，翩翩飞舞在空中，\n“太好了..进来吧！再里面一点，\n淫魔们浑然不觉，\n“呜叽叽叽….\n“\n“\n“\n“\n美那从微扬嘴角中，\n“哦呵呵呵！\n美那冷笑一下，\n“\n“呜叽叽….\n“\n“\n在淫魔碎尸所堆起的小山前，\n“哼哼！\n“\n“\n“难、难道….\n“大王说的….\n美那的指甲闪出一道寒光，\n“\n“\n随着巨大的爆炸声，\n“\n“\n“\n“\n赛鲁曼皮笑肉不笑，\n“\n“嗯？\n两个女学生，\n“啊，\n“\n“\n“不管什么事都可以告诉老师，\n转过身去的赛鲁曼，\n“什么嘛，原来是这件事啊，\n赛鲁曼明朗地大笑，\n二位少女，理奈与小满，\n“\n“对不起，对不起….不过，\n“\n“\n赛鲁曼已得到学生普遍的信赖，\n“喂，可是….哎，算了，\n“\n“\n理奈与小满，\n“\n“\n“\n理奈的验孔仍残留几分稚气，\n她有着一头俏丽的短发，\n摇动着水手服裙摆，手脚趴在地上的二位少女，\n赛鲁曼斜视着二人，\n“\n二人认真地在纸上涂着颜料，\n“\n“\n“理奈和小满，\n涂完颜色后，\n“\n“啊….嗯…这个，好像有些….\n“呃….\n二人停下画笔，\n“\n“\n“老师，\n“\n“\n“\n“老师，\n“因为这样，我们才可以集中精神….你们二个，\n“\n“\n理奈和小满红着脸颊，\n“可是….\n“没关系，快脱吧！\n一向温柔的赛鲁曼突然尖声命令，\n“\n“\n“\n“\n理奈忍着泪解开水手服的大蝴蝶结，\n“不好脱的话，\n理奈的手发着抖，\n“\n“\n“\n小满与她相反，\n“衣服….\n“\n“可，可是，\n“如果不为我的话，你们是回不了家的……\n赛鲁曼低沈的嗓音，\n“\n“\n小满雪白的肌肤上，\n“\n“\n“\n小小的乳房，\n“\n“\n“\n“啊啊….老，\n小满被他拉的更近，\n“啊，啊，老，\n“\n“啊….\n“哼哼！\n“\n“\n二人被他一吼，不得不张开双腿，\n“\n切断的内裤落到地面，\n“\n“\n“\n“\n“他们二个，躺在上面舐对方的小洞，哈哈哈哈！\n理奈与小满震颤着身体，\n“要，\n“\n“\n海报纸上的颜料，\n理奈躺在下方，\n“\n“\n“啊，啊啊，哈啊….\n二人的肌肤上渗出汗滴，\n“\n“啊，\n大量的黏液，使理奈张大了嘴，\n“理，\n小满用手指拨开理奈粉红色的秘唇，\n“\n“\n“理，理奈，\n“\n躺在下方，把脚大张成Ｍ字型的理奈，\n“啊….\n只有赛鲁曼，\n“继续，\n理奈一面吸吮小满滴流出蜜汁的肉缝，\n“\n理奈以中指抽插，\n“啊啊，\n“\n“啊啊，\n二人因为害羞而赤红的脸颊上垂着泪，\n“尽情的体验快感吧！\n赛鲁曼清秀的侧脸，\n眼珠向外突出，\n“啊，\n惊吓的理奈与小满，\n“再叫也没用！\n“救，救命！\n“有，\n“说我们是妖怪，太失礼了嘛….\n“互相舐这么久了，该很有快感了吧？\n“呀呀！….\n“\n“不行….\n赛鲁曼的肉棒沿着二人的黏液，\n“\n赛鲁曼咧嘴一笑，\n“\n“好痛….啊….好痛….不行了….\n赛鲁曼的肉棒激烈进出，使二人的裂缝中，\n“\n“\n“小满的那里也是….啊，\n“\n虽已为淫液所滑顺，\n“啊，\n“不行了….\n“\n赛鲁曼左右裂开的嘴中，\n“\n“\n“\n“\n“不，不要！\n这时理奈已倒在地上，\n“啊….\n赛鲁曼抬起头来，\n“哈哈哈！\n“真奇怪….\n手臂来回转了二圈，\n“大概是最近….\n“\n达夫从走廊下，\n“\n“\n“嘻嘻嘻！\n“而且，有那种帅气的美少女耶！\n这时，\n“\n“\n从小不管什么事，\n因此，\n“喂，你干嘛！\n“因为要和达夫一起回家嘛，所以才找你啊！走吧，\n“干嘛啦，放开我啦！\n“什么嘛！一天到晚小薰小薰的！\n阿惠也不认输，\n“\n“第一，那个小薰才不会把你看在眼里！她是峭壁上的孤寒花朵，\n“唔….做什么时候是我的女朋友了！别擅自决定好不好？\n“哎哟！不知道那个流着鼻涕，像白痴一样哭着求我说，\n“那种几百年前的陈年往事，\n“对你来说这可能是陈年往事，\n“什么话嘛！\n“真是的，吵死人了！爱情果然是纠葛不清的啊，\n“暗音，\n“\n“\n“上次承蒙你提供新鲜的血液，\n“\n“\n“受到你的帮助，\n“达夫，\n“\n“\n“\n“\n“\n“\n“\n“\n暗音一把抢过洋伞，\n“已经黄昏了，\n“啊，我，我们的体质很弱，只要皮肤一照到紫外线，\n“\n“\n“那，\n“哈啊、哈啊、\n“\n在图书馆专心看资料的小薰，\n静静翻书的模样，简直就像雾中的花一样清秀脱俗，\n“ＭＩＳＳ应兰学园，\n二颗眼珠几乎要变成红、\n“啊，哈啰！\n“\n小薰冷冷地回话，并没将视线从资料上移开，\n受到冷淡待遇的达夫，\n“虽然方向不同，不过如果可以的话，我们一起回家好吗？或者，\n“\n“不喜欢去海边的话，那我们去游乐园，\n“\n小薰耐着性子，一个字一个字像抽响皮鞭似的，\n“\n“\n“\n“像你这种没格调的低级男生，\n“\n“而且….今天我要上茶道课，家里的车会来接我….\n只剩下傻了眼，\n“\n“\n愉快的呼唤声，\n“小薰果然是峭壁上的孤寒花朵，\n“\n“\n“\n“\n“你，\n“\n“\n“\n“可恶！\n“\n“我要和他绝交！\n对达夫来说，\n“\n“可，\n“阿，\n“我….\n“\n“\n“\n“可是，人家，\n阿惠的声调，\n同时，\n….\n“\n“\n“既然是我的女朋友，\n“没错，就是自慰！\n阿惠咬着唇，\n“\n“….好，\n“\n达夫、\n“\n“喂，\n阿惠脱下鞋子，\n“达夫….\n阿惠下定决心，\n鼓胀的耻丘，\n“阿惠….\n但是，\n“\n“\n虽然学生们都已放学，周围一个人也没有，\n“喂，可，\n“不行，你要好好的….\n“阿，\n湿淋淋的秘贝，\n“啊….啊啊，啊….啊….\n手指夹住肉壁的沟缝，\n“嗯咕….\n“啊啊，\n“啊啊，达夫….\n手指每一滑过秘贝，\n“啊啊….\n“哈啊….\n左手转动着粉红色的乳头，\n“啊啊，\n阿惠几乎忘了达夫的存在，\n“哈啊….\n“不，不行了….\n阿惠后弯着的背部，\n“啊，啊啊….已经，\n黏液并未在阿惠的秘唇中停住，而是不断垂流出来，\n“啊啊，\n阿惠忍受不住，\n“呜….啊，\n中指开始微颤的活塞运动后，\n“\n中指弯成ㄑ字型来回抚弄着Ｇ点，\n“\n手指噗滋噗滋地插送，\n“啊，已经….\n二根手指压入最深处，\n“\n太过强烈的高潮，\n“\n瘫软的阿惠坐起来，\n阿惠回到现实，\n“\n“\n似乎当阿惠专心自慰的时候，\n“\n“\n“\n赛鲁曼从容不迫的样子，\n“你，\n“\n这时，\n“\n“\n“不，\n“\n赛鲁曼粗暴地压住阿惠的上半身，\n“不要啊！\n阿惠的内裤，\n“\n尽管双脚还紧密合拢着，\n“\n赛鲁曼用自己的双脚压住阿惠的双脚，\n“\n“你已经被那个达夫甩了，还叫他干嘛？\n“\n“噫呀呀….\n虽然身体被压住，\n“哈哈哈….\n“啊，\n赛鲁曼抓住阿惠的头发，阿惠才刚被收进胸罩内的白皙乳房，\n“不要，不要….\n“啊啊….\n阿惠的粉红色乳头，\n“啊啊，\n“\n“\n被肉棒穿入的阿惠，\n“\n“还早呢！现在才刚开始而已….\n“\n“\n“哼哼….\n“\n二条眼镜蛇在阿惠的秘壶和臀部的花蕾中旋转抽插，\n“\n被满满塞入二条粗大肉棒的肉唇，\n“怎么样啊？\n“啊，啊啊，\n“\n“怎么样呢？\n“啊啊….更用力….更激烈的插到阿惠的肉洞….\n“\n“\n“这么一来，\n赛鲁曼的瞳孔，\n“对不起，\n雅致整洁的庭院中飘来的高尚空气，\n换穿过和服的小薰，\n“\n“\n“各位，\n“….”\n“\n“嗯，\n“很好，\n“\n“是内裤….因为今天时间不够，而且，\n“\n“\n“\n从大开的二条腿间，\n“他是个坏学生！\n“小薰，\n“\n“\n“\n“\n“\n连股沟的部份都被仔细地刮除，没多久，\n“\n“啊….\n“\n老师的手指，\n“\n“再来，为了表现茶艺家的风雅，\n“\n“\n从捆住身体的绳子之间，\n突出乳晕的小粒乳头呈现淡红色，\n“啊….啊….啊啊….哈啊….\n“啊，嗯啊，\n“\n即使被老师指责，\n“\n“啊啊….\n老师们的笔尖触上秘贝的核桃，\n“啊啊….\n“小薰！\n“\n打开盒子，里头摆着一枝乌黑发光的粗大电动阳具，\n“不，不要！那个不要，\n“\n“来吧，\n“啊！\n老师充耳不闻小薰的尖叫声，\n“\n“呃….啊….啊啊，\n“真惊人哪！\n“\n在秘壶里头，\n“啊，\n“哈啊….哈啊，\n强烈的麻痹快感传递体内，\n“\n“\n“啊….\n小薰的黏液，\n“哼哼，用这个贴住吧….\n老师撕开一块大纸胶布，\n“啊啊….\n“拜托….请原谅我….\n“\n一位老师，\n“\n“\n在小薰的唇中，\n“\n“\n“啊啊，\n赤黑的肉棒，\n“嗯咕….\n“嗯咕….啊啊….\n碗型的白嫩乳房，被用力握住，\n“\n敏感的小薰，\n“\n把嘴唇从吸吮的乳头上放开，\n“\n“\n“\n“\n“嘿嘿，\n这时，\n“\n“可恶！你、\n“口中吐出最后的几个字，\n“哎！\n“不过，\n跨过死尸堆叠成的小山，\n“….不管杀掉他们再多人，杀人事件还是天天发生….\n“\n“\n走着走着，\n“\n“\n“\n“\n“你….\n“呵呵呵～看来你也不简单嘛！\n“\n“\n赛鲁曼的嘴裂到耳际，\n“\n“\n“\n“\n“\n“\n美那丢掉手套，\n“\n“\n“你不知道不信邪的人，下场通常会很凄惨的吗？\n目光像回力镖一样放射出来，\n“嘎….\n“可、可恶，\n“啰啰嗦嗦的，\n“\n“\n“走吧！\n趴!!\n“呀啊！\n“真可恶！最近连想好好喝个蕃茄汁都不顺利！\n“\n暗音也擦拭着身上的泥巴，\n“\n“\n“那个、\n“\n“\n“\n“阿惠姊姊，\n“\n“是吗？可是….\n“\n“\n“\n“阿、\n“\n“\n等发觉时，原本根本没人的街道上，\n“\n“\n“\n虽觉得阿惠真的很烦，\n“大概….真的是我不对，她从小时候就和我玩在一起….\n达夫自言自语，\n“\n“啊！好、好….\n眼神涣散，\n“再来….\n“\n“\n小薰险些跪倒，\n“拜托….\n“小薰….\n“啊哈！\n“嗯嗯，\n呛鼻的淫魔体味，\n“你、\n“\n“\n“\n“\n对于达夫的惊异，\n“\n“\n“你就是那天晚上那个不可思议的美少女，我不会认错人！\n“\n“\n“\n“\n“没错！\n“……!?”\n“带她去医院吧！\n“她暂时需要住院一阵子；\n护士小姐温柔地对达失说道，\n“不过….我的个性也太随和了，\n小薰被用皮带固定在病床上，\n“无情的话，\n“抱歉！\n“好吧！虽然还有点担心！\n“\n“请你不用担心！\n“\n“\n“\n“夜晚的医院真安静哪！\n“\n“\n“\n“\n“\n像蜈蚣一样，\n“别说这种话….\n那个护士，\n“\n原为医生的怪物，\n“救救命!!\n达夫拚命闪躲，\n“\n全无任何反应的小薰，\n“\n“\n怪物的胴体瞬时暴长，眼看着就要抓住达夫，\n“\n“我不是来救你的，只是来杀淫魔而已….\n“\n只能像那时候的梦境一样，\n“\n“\n“嘻嘻嘻！\n“\n“\n“\n美那轰开手掌，随着剌眼的青光，\n“\n“所以我说，\n裸着身体，头部朝下被捆绑吊起，\n“\n卡尔马坐在由裸女架成的椅子上，\n“哼哼哼！\n“\n在卡尔马的身后，\n“卡尔马大王！\n“嗯，好吧！因为你抓来这二个，\n放在爱音肉缝上的水晶球，\n“\n“是的，\n“\n在水晶中，\n“吸血鬼的贱女人，终于出现了1虽然你的所作所为，\n“\n冰冷的岩石感触，\n“\n“\n“\n“\n“\n达夫的面色苍白，\n“卡尔马….大王？难道，\n“\n“\n腿间的肉缝，\n“\n“\n“\n“来吧！我们永远在这里，\n胸前可爱的小粒乳头也伸得长长的，\n“\n“等、\n一片黑暗的石头中，\n“等一下！\n“\n“\n阿惠想得到达夫的爱….\n“因为….人家喜欢你….\n“开什么玩笑！\n在黑暗中，\n“\n“小薰….\n“\n“\n“\n“小薰！\n“让我为你做这种事，\n“\n“\n“\n“\n达夫的身体产生与意志背道而驰的反应，\n“\n“\n小薰一面说着，\n“要上了….\n“\n随着噗滋的水声，\n“\n达失似乎也耐不住舒服的感觉，\n“这样不行……..\n“啊，太舒服了….\n小薰丰腴的臀部每一上抬，\n“啊啊….用力！达夫，\n“\n“\n达夫使尽吃奶的力气，\n“\n“\n小薰的身体也痉挛抽搐，\n“哈啊！哈啊！\n在达夫还没来得及抽出肉棒时，\n“唔唔….\n“\n嘴角浮现浅笑，小薰夹着达夫的肉棒，\n“\n“\n“呀….\n“来吧！\n小薰的淫幼虫，\n“\n达夫拼命想爬起身体，\n但是他的肉棒，\n“\n“\n“\n“阿、\n“\n“\n随着噗滋的声音，\n“哈啊！\n“达、\n“\n“唔….\n“\n“\n“哈啊！哈啊！\n“\n耸立在黑暗之中的城堡上方，\n“这里就是虐杀人类，\n进入大门后，\n“快点来吧！\n“\n“\n美那皱起鼻子微笑，\n“\n“\n“\n淫魔喽啰们，\n“\n走进城内深处后，\n“\n“\n“\n无数颗巨眼发出无数道红光，\n“吸血鬼的贱女人….\n“\n“\n“人类被杀或被强奸，\n“\n“\n“\n卡尔为巨大的眼睛像块磁石股，\n美那迈开步伐，\n“哼哼….\n“\n“\n“\n“\n“\n美那望向空中的爱音和暗音，\n“唔….\n“\n无数颗巨大的眼睛一瞬间消失，\n“\n与之前的下等淫魔完全不同，\n“喔哦哦！喔哦哦！\n红色的瞳孔闪闪发光，\n可怕的烟雾卷起，\n“竟然敢对爱音和暗音……\n“\n“时光流逝，赤红的邪念在静肃假面具之下，\n“\n黄色的锐利指甲，\n“\n美那露出獠牙，\n“\n“哈啊！哈啊！\n“我们之间的战斗，\n卡尔马击出的巨拳，\n“\n“\n“正因为愚蠢，\n“不过，\n眼镜蛇的淫毛，\n“\n“\n“哼哼哼哼哼….\n“\n阴茎贴附在美那的身上，\n“\n“嘻嘻嘻嘻….\n“住手！我….\n“\n“不要！\n“\n“\n“卡尔马大王….\n“\n“\n“纵使….\n“\n阿惠的苦恼,\n“\n身体被卡尔马击中，\n“\n“\n卡尔马的尾巴，\n“被这种东西夺走处女贞操的话，\n不知是因美那的秘贝太紧，\n“\n卡尔马使尽全身力气，拚命要插入美那的秘贝之时，\n“\n赤红色的月亮，\n“……..！”\n处于濒死状态的爱音与暗音，\n“美那姊姊有危险!!\n“\n“\n这时，比平常更为勇猛的爱音，\n“\n“美那姊姊！\n“\n受到撞击，\n“\n“\n姗姗来迟的暗音，\n“暗音，你也来了！\n“\n“保护吸血鬼族唯一仅存的公主，美那姊姊，\n“\n但是，\n“\n“\n“\n“\n“\n“\n“\n“\n这时，\n“\n“\n“嗯唔….\n当啾吧啾吧地吸达夫的血时，\n“为什么呢？\n就如一种信号，\n“\n背对着赤月的美那，\n“\n但是，月光为愤怒所燃，\n“\n“\n“什、\n“\n“\n深陷颈内的獠牙上，\n“\n叫苦挣扎的卡尔马全身失去力量，\n“\n“\n“怎、\n“\n“\n“抓到了！现在还不迟！\n“\n美那的双颊泛红，\n“\n“你的处女….\n“\n“\n“\n美那把压在卡尔马脸上的光球急剧变换，\n“\n“\n“\n“没有用的….吸血鬼的笨女人….淫魔大帝….\n“淫魔大帝的….\n“美那姊姊，\n她也没注意到，\n美丽的敌人，\n“哼哼哼哼哼！\n托爱音与暗音使出治愈力量的福，达夫、\n“\n美那一如往常，\n“他们只是被淫魔所利用，一时丧失心智而已嘛！\n爱音及暗音手掌发出的能量，\n“ LUCKY！\n“\n美那翻了个身，\n“\n“\n“\n眺望着明亮的街灯，\n“因为我是….\n我的脑中，\n我一个人躺在床上，\n当我得到有如接触达夫的肌肤，\n我在图书馆中，按理说，\n但是，就连这件事，\n仔细回想，那或许是梦时，\n我的头与上半身，\n我的下体已经裸露，\n我那才刚成为大人的小肉洞，被赛鲁过份粗大的肉棒撑紧，\n即使我百般地厌恶，即使心里想的是达夫，我的小洞中仍啾啾地滴出甘美的液体，\n赛鲁曼似乎明了我的感受，\n我的腰及乳房都被用力抓住，不知自己是想要他住手，还是要他更用力抽插，\n随即，我双臀间，连达夫都没摸过的小花蕾，\n同时被从背后贯穿时，我的胸口痛苦得难以呼吸，\n我叫的是“\n我的肉洞中会像小孩尿床般，发出哔啾哔啾的水声，流泄出来的蜜汁，\n还有，\n可是我的身体，\n但是，我、心中在意着一件事，\n“你会成为继承淫魔大帝血液，\n来源  LOVE．QUEEN？不可能的！\n因为我又没有什么别的力量，\n不过….昨晚做的梦，是个让我今天早晨起床时，\n黑云完全遮蔽月光时，我的下部被从未有过的感觉所笼罩：\n“\n早上，我环顾四周，\n虽说是梦，但我的、\n“阿惠，起床了！"
    }
  ],
  "tags": [
    "都市",
    "现代",
    "都市生活"
  ]
}