{
  "id": "book_1507",
  "title": "老姐、老妈和我的观星记",
  "author": "未知",
  "cover": "",
  "description": "今天，是蛮特别的一天，对我来说是如此，老爸临走前丢一卷录象带给我，片名是女孩第一名，就有单单黑盒子，封面连一个图案都没有，听老爸说他是从家里阁楼找的，不过他可没空看，他刚接到电话要去新达港出差，看来四...",
  "sourceId": "jisge",
  "sourceName": "集书阁",
  "chapters": [
    {
      "id": "ch1",
      "title": "老姐、老妈和我的观星记",
      "index": 0,
      "url": "",
      "content": "今天，是蛮特别的一天，对我来说是如此，老爸临走前丢一卷录象带给我，片名是女孩第一名，就有单单黑盒子，来源  \n来源 \n在电视机出现的女人，不是别人，是我老妈，打死我也都认得出来。来源 \n漂亮竟然从我嘴里说出来，来源 \n但……但这实在是太夸张了，来源 \n年轻的妈妈就坐在沙发上，旁边一位高大俊俏的白人很亲昵地跟她东聊西聊的。来源  \n妈的，不会吧，来源 \n虽然我心底说了一万次不可能不可能，是在普通聊天对话，来源  \n不过，来源 \n哇操，来源 \n年轻妈妈，与可恶白人说了几句话，就蹲在地上，很骚媚的脱去她的内裤，露出金黄色的阴毛。来源  \n来源 \n你老师的，真是够，白人还真舔啊，来源 \n不过，来源 \n来源 \n平常看太多Ａ片，来源  \n所以说，各位道友，来源  \n接下来，来源 \n妈的，星崎未来算什么。长得一点可爱罢了，胸部又假，哪像我老妈，胸前那两个咪咪，晃啊晃，水嫩嫩的，那死白人还在　来源 　啃的不停。更何况年轻妈妈出色的长相；月儿弯的细眉，大大的双眼，高挺的秀鼻，以及性感的小嘴，来源 \n来源  \n来源 \n来源 \n最后，来源 \n哼哼，妈，来源 \n＊＊＊\n＊＊＊\n＊＊＊\n＊＊＊\n来源 \n老实讲，我睡得不太安稳，妈那部影片我看了好几次，每次看都有不同的感受。当然都是令我老二翘得老半天，来源 \n来源  \n当然，早晨起来，来源 \n来源 \n镜子里的我，一副睡不饱的模样，眼袋极深。一晚的折腾，令我有点适应不过来，来源 \n来源 \n以前都没认为妈妈的声音是这样……来源 \n来源  \n来源 \n妈妈大卷蓬蓬的金发，随风飘逸，来源 \n来源 \n母亲白色Ｔ恤下沉甸甸的双乳　之欲出，想不到妈妈将近四十岁的女人，胸脯还是如此尖挺，尤其黑色紧身裤下浑圆翘臀，来源 \n靠，来源 \n妈，来源 \n来源 \n我坐在沙发等时间慢慢过去，想到母亲等会就到厨房煮菜，而待会要对妈妈所做的事，来源 \n妈的，不管了，就趁此机会来威胁母亲，来源 \n终于，来源 \n我鼓起勇气，来源 \n身子以极快的动作，来源 \n轻轻的在母亲耳边吹一口气，妈妈还以为我在和她开玩笑，轻笑的微微挣扎我对她亲密动作说∶“来源 \n“来源 \n我双手紧搂着母亲的小蛮腰，来源 \n“来源 \n“来源 \n来源 \n“来源 \n“有事就说啊，来源 \n听完母亲说完后，我反而更用我的肉棒摩擦妈妈的臀沟。来源 \n“来源 \n我不在乎妈妈生气的神情，反而以一种平淡的语气说∶“妈妈，来源 \n“来源 \n来源 \n“我看到一部片子，女主角长得跟妈妈很像。是她比较年轻吧。但是他跟男主角做的事，来源 \n“啊啊！……马弟你在说什么。来源 \n来源  \n“啊，不……不用打给你爸。来源 \n来源 \n我满脸堆笑看着妈咪说∶“妈……你也不想这片子被爸看到，来源 \n“来源 \n“来源 \n“来源 \n“呵呵！其实很简单，来源 \n“来源 \n在我怀抱的母亲，身子用力一震，似乎还不能接受听到的事实，而嘴巴张的大大，表情看不出妈妈在想什么？唉……毕竟这是乱伦，我会不会太心急呢？一下子就说出来。其实我是挺担心的，害怕母亲不答应，来源  \n“妈妈……来源 \n我带有点撒娇的语气，并用身体磨蹭着妈妈。母亲似被我孩童似的声音惊醒，继而笑起来，对我说∶“来源 \n见妈妈似乎没有反对的意思，我高兴的说∶“来源 \n“来源 \n母亲有点害羞的点点头。来源 \n“那……来源 \n接下来，我心底可没主意，毕竟我是个二楞子，连女孩的手都没牵过，可不知下一步怎样实行，来源  \n“嘻……马弟，你想在厨房做啊！来，来源 \n不知道是否母亲想通什么，突然开朗年轻很多，来源 \n来源 \n此时的我宛如一个小姑娘害起臊来，妈妈落落大方牵着我的手，来源 \n来源  \n母亲缓缓的转过身来，来源  \n呆头鹅的我，来源 \n“嘻嘻……马弟，来源 \n只见母亲娇笑的模样，来源 \n母亲看我急色模样，更笑得更严重，温柔对我说∶“儿子不要急，来源 \n我傻笑了几声∶“来源 \n来源 \n来源 \n母亲一副平常语气说∶“来源 \n“没……没有……来源 \n“嗯。”母亲似乎挺满意我的回答，来源 \n“那么，来马弟……来源 \n来源 \n牙齿轻咬白嫩嫩胸脯上如葡萄般的奶头，来源 　丢的肌肤。含住母亲的双乳，有种重温旧梦的感觉。已经阔别多年了，亲爱的奶奶，近来过得好吗？没有我的滋润，你也不复以往那样鲜嫩有味。\n来源 \n“来源 \n耳听到母亲娇嫩的声音，来源 \n妈妈双手刻意的挤压双乳，在灵巧的手指变化下，雪白的胸脯呈现种种不同造型，母亲娇笑说∶“来源 \n“来源 \n白晰的胸脯上都留下母亲挤压过的痕迹，来源 \n来源 　是乐团的指挥者般，正在安排上演一幕幕的好戏，灵巧的秀指慢慢越过洁白如瑕的小腹，在浓密的金毛上停息半刻。\n“来源 \n母亲纤细的手指交缠着柔软细毛，仿似一位位仙女，来源  \n来源 　看到珍宝般，齐聚在一起拨弄那颗快滴出水的宝贝。来源 \n“好漂亮啊！”我情不自禁的赞美道。母亲双手仿　刻意展示妙处给我欣赏般，特地的指点这是女人的蜜处。还夸张的大大翻开粉嫩的肉唇，来源 \n“哇！这就是生出我的地方吗？来源 \n母亲双手掰开两片肉瓣，方便我的手指进入阴道，来源 \n真想不到，来源 \n“妈，来源  \n我抬头想说什么时，来源  \n“啊……妈妈……我……来源 \n来源 \n我激动不已，大嘴贴住母亲的肉，来源 \n闻着母亲淫穴独特气味，使我有点迷失在里面，我贪婪如野兽般，非吸舔到没有一滴蜜汁出来为止，但这是不可能，淫靡的肉穴仿　来源  \n母亲羞红娇嫩的脸上双瞳似乎有点迷茫，但能忍住情欲般说∶“马弟，不要再吸，来源  \n我只能傻傻的点点头，来源  \n我满脸的淫汁听从妈妈的指示，来源 \n来源 \n母亲的双手爱怜的抚摸着我的大肉棒，对我说∶“来，马弟，把这插进这里面。”母亲一边用手牵引着我的肉棒，另一只手，来源 \n来源 \n肉棒缓缓插进沾满蜜汁的肉穴。只觉肉棒进入到紧窄却又湿润温暖的地方，这就是生育我的地方，啊……有好多年没有回来了，你还记得吗？当初你也是从这降临这世上的。通过幽静湿温的甬道，来源 　遇到老朋友一样的激动高兴。因为此刻的他是如此颤抖不已。\n嗯……这软软又硬硬的软骨，是什么？我张开口想问妈妈，但见母亲早已闭上眼，激动不已，我也不好打扰。啊……难不成那就是子宫颈，想不到，来源 　被温暖的甬道收缩，一波波的刺激着，来源 \n“啊……来源 \n我　着气，来源 \n母亲娇羞着看我，很特别地，来源 　更加美丽动人。来源 \n我湿漉漉的肉棒从母亲体内抽出，来源 \n我很不舍得地轻抚淫穴，来源 \n母亲温柔看着我，轻轻说∶“马弟，来源 \n我不解的看着母亲，来源 \n来源 \n来源 \n不到片刻，母亲右手拿着一罐东西，回到房间，但我只注意到，被插红的阴部此刻的精华仍微微流出，顺着大腿往下滑，随着母亲的步伐来来去去，来源 \n“马弟，来源 \n母亲就这样蹲在我面前，双脚大大张开，来源   .母亲滑腻的舌头，仿　具有无数只小手，再抚摸着我的棒槌。更何况当嘴唇亲吻着龟头上的马眼，我的灵魂似被抽走。\n正当我以为母亲的淫乱小穴指的就是嘴巴。母亲动人的小嘴却离开了我的肉棒，使我不由得讶异问道∶“来源 \n来源 \n不愧是经验丰富的妈妈，来源 \n来源 \n只见母亲拿着罐子往手上倒些膏状物，来源 \n接着母亲将罐子递给我，来源 \n我听到惊讶道∶“来源 \n来源 \n母亲趴在地板上，高高抬起屁股，如一个犯贱的母狗。来源  \n我把罐子上的润滑油，来源  \n看着母亲雪白的翘臀，忍不住想对她凌虐似的，大手毫不留情的拍打屁股，母亲除了唉唉哼叫痛外，来源 \n虽然被打得红通通的圆臀，但手底下的触感还是很滑嫩。来源  \n妈的，骚货！来源 　来源 \n我双手抓紧母亲的柳腰，低喝一声，来源 \n“来源 \n来源 　被套进极小的瓶子急需要挣开解脱。\n母亲也在忍受着痛苦，插入的一瞬间，听到极大喊叫声，那并不是快乐的声音，而是撕痛的惨叫。不过母亲也在适应，我能感觉到直肠壁里的信道正渐渐扩张，来源 \n伴随着我肉棒更深的插入，母亲也就更加痛苦的喊叫。我不理会母亲唉叫说痛得受不了的要求，来源 \n“来源 \n……！”\n来源  \n虽然看不见母亲的表情，但每每听到随着抽动肛门的动作，母亲唉叫痛声，来源 \n来源  \n“妈，你这贱货，以后你只能给我干！来源 \n“嗯，来源 \n“大声点，说你是儿子的贱货，来源 \n我自己都为我说出来的话，来源 \n来源 \n我仿　有种错觉，来源 \n“啊……！来源 \n我大叫一声，来源 \n＊＊＊\n＊＊＊\n＊＊＊\n＊＊＊\n来源 \n“达令！来源 \n啊，来源 \n“妈妈，来源 \n我吹着一口热气在母亲的耳旁，看母亲一手艰难拿着电话讲电话，来源  \n“来源 \n母亲圆滚滚的大奶可是百抓不厌，“妈，来源 \n“来源 \n妈妈似乎受不了我底下大肉棒的攻击，来源 \n来源 \n因为，来源 \n（来源 \n小时候，来源 \n我的头放在妈妈胸前，老姐就拿妈妈的大腿当枕头。听着妈妈温柔的声音，不久，来源 \n因此，对天上的星星，我从小种下深深的兴趣。国一时，耗尽存了几年的压岁钱、生日红包。来源 \n原本好好的观天文，来源  \n我看完了那一段，回过头来只见到老姐不坐在椅子上观星，来源  \n我们住２２楼，是这大楼的顶楼。周围全是十七、来源 \n那天是暑假以来最热的一天。姐弟两在家里头都穿得甚单薄。来源 \n老姐两条白白的腿，一条小内裤露着雪圆的两半片屁股，高翘着。来源  \n来源 \n“来源 \n“来源 \n“来源 \n心想，前晚我看到有人在客厅互相抚摸、接吻，该不是……看她脸颊晕红，眼波流转，来源 \n老姐急着说∶“没什么好看的！来源 \n来源 \n望远镜已经被老姐锁定了一个目标。那是一间卧室，落地窗的窗帘边缘没拉好。来源 \n焦距一拉，连那女人流满白色泡沫状淫水、来源 \n我正看到那男人提着粗黑的大家伙，把那女人的双腿架上肩头，要插进流满淫水、毛茸茸的阴户时。头上啪！来源 \n“哎！好痛！”转过头来，来源 \n“给我下来！”她老大，来源 \n“来源 \n“来源 \n我嘀咕着∶“来源 \n我站在老姐后面等着，底下顶了高高的一支棍棒，来源  \n“姐！该我了，姐！”我推推她，顺势把裤里硬梆梆的小弟弟，撞撞她高翘的屁股缝、顶顶她分开的两腿间。喔！来源  \n我感觉到老姐震了一下，好像双腿发软要往前屈。听她低低哼了一声。然后转过来，满脸赤红，来源 \n“你看吧！”老姐声音娇娇软软的，对刚才我顶她屁股的动作，来源 \n我大乐，凑上去一瞧。那女人跪在床上，那男人半站着在她屁股上。我看到一条巨大的鸡巴，来源 \n来源 \n这时候，我闻到一股熟悉的幽香，来源 \n“该我了，来源 \n“来源 \n望远镜里，那条巨大的鸡巴继续在抽动。我看到冒白泡的两片阴唇，来源 \n看到这里，我内裤里头的小弟弟已经快爆炸了，好痒，又难受。来源  \n我摸了又摸，老姐“啪”的把我手打掉，揪住我耳朵∶“来源 \n“可是涨得好难过！姐！”我离开望远镜，来源  \n我一听，唰的就拉下内裤，因为小弟弟挺得高高的，还扯了两次，来源 \n老姐红着脸低声骂说∶“来源 \n我壮着胆子，来源 \n我看到老姐左揣右详了一阵子，来源 \n“来源 \n“姐！来源 \n“这样是不是？”来源 \n“对！对！就是这样！就是这样！”来源 \n老姐细腻的手，摸了半响，来源 \n“来源 \n“姐！来源 \n“来源 \n“哎唷！痛耶！”来源 \n来源 \n“来源 \n我以为在作梦，来源 \n当我的手，隔着裤子触到老姐的阴部时，她浑身颤了一下。来源 \n我好兴奋，来源 \n老姐的裤子很薄，来源 \n挖着挖着，来源 \n“弟！来源 \n来源 \n我飞快的想了一下，老爸和老妈后天才回来。现在家里老姐最大，但也只管我和菲佣阿咪而已，来源 \n轻轻把老姐的裤子往底下搓、来源 \n老姐“劈哩啪啦”左打右打，来源 \n没两下子，来源 \n我把浑身软软的老姐“来源  \n来源 \n我轻轻扳开她的双手，老姐“啪！”来源 \n我再扳一次，她终于松了。两个乳房比老妈拜拜用的“发糕”还小，不过好白、好圆。两个乳头，像极了老妈送给阿铃表姐的珊瑚玉。粉红色的，来源  \n哎！真没想到我的姐姐，来源 \n我每天和她在一起，对她缠东缠西的，怎么会没注意到呢？来源 \n我硬着脑袋也硬着快要涨死人的小弟弟，来源 \n老姐的大腿又白又嫩，她稍微紧夹一下就张开了。来源 \n哗！眼前一片白光，来源 \n那个白色的大理石长得很像馒头，很可爱。来源 \n来源 \n来源 \n没关系，我还有一根小指头可以活动，来源 \n我用小指头在那道缝的上端乱抠乱揉，老姐颤抖起来，喘着气。张开眼楮，低声说∶“不要！不要……来源  \n两个年轻、早熟，毫无性经验却又好奇的裸体贴在一起。那两个“来源  \n来源 \n“再揉揉刚才那地方。”来源 \n“来源 \n“来源 \n“来源 \n“来源 \n“姐！我忘了是哪个地方，来源 \n话才说完，“啪！”的一声，来源 \n“人家真的忘记确实的位置了！你怎么一点都不疼惜自己的亲弟弟！来源 \n来源  \n我要找阴核，我知道阴核的位置应该在哪里。来源 \n我用中指去揉她，老姐又震了一大下。来源 \n来源 \n我看着眼前圆润发亮的屁股，忍不住轻啃了一下，还亲了亲。开始抚摸、挖弄那圆臀、沟缝及顺延下去的阴部。\n来源 \n来源 \n“来源 \n“你又胡说八道了！不跟你弄了！”来源  \n“来源 \n“姐！那……你会不会吸……吸？来源 \n我感到小弟弟一阵温暖、来源 \n我想，既然老姐吸我、舔我。我好像也应该投桃报李才是。何况，老姐雪白的屁股、如阴丘纯白大理石的阴户，我早想舔她们、来源 \n我继续刚才的舔、来源 \n老姐的阴水越舔越多，来源 \n“来源 \n“来源 \n来源 \n我搂着老姐，边摸她乳房，同时在她耳旁问着∶“姐！你几时看到的？”我另一手伸到底下，来源  \n老姐“咭！”的笑了一声，“你又胡说八道了，来源 \n“姐！快告诉我！他们是怎么弄的？”来源 \n老姐拿枕头塞在屁股底下，把阴部挺高，并且把双腿张得大开。“来源  \n老姐一手掰开阴唇，来源 \n我看着老姐半张的小嘴巴，圆白的乳房。她越磨淫水越多，哼声越高，我们两人越来越兴奋。来源  \n有两次龟头无意“吱！”来源 \n手一挡，我觉得小弟弟发痛，她弱声哀叫∶“不能插进去！来源 \n我越弄越想戳进去。第三次就是故意的，暗暗摆好姿势，又快又重，“吱”的顶进了大半个龟头。老姐“哎唷！”大叫一声，抓住小弟弟，“啵”的微声，来源  \n“死小孩！你居然给我插进来？你插进多深了？”来源 \n“一个……一个龟头而已，来源 \n我看老姐的状况，铁定和我一样，\n来源 \n是“欲火焚身”。也到底是自小疼爱我的姐姐。因为她不生气了之后，搂着我，把我的脸轻压在她胸前，并排躺在床上，柔软的手抚摸着我的小弟弟。又开始问我，用望远镜“观”过几处好镜头？\n“来源 \n“来源 \n“来源  \n“我们再来磨！”来源 \n“嗯！”来源 \n这次，我磨擦到眼看老姐差不多要昏迷了，小洞口的淫水也流得一蹋糊涂。来源  \n她“来源  \n我只好紧抱着她，一个大龟头也够她受的了，来源 \n“好痛！是不是裂开流血了？”来源 \n“没有，来源 \n来源 \n“来源 \n老姐还用两根指头配合大指抓着小弟弟，来源 \n我开始轻轻的、来源 \n老姐轻叫着∶“弟！来源 \n“来源 \n“来源 \n“来源 \n“来源 \n“来源 \n“来源 \n“来源 \n“我看过他们姐弟两人，来源 \n“啊！真的！来源 \n“真的，来源 \n“啊！……来源 \n来源 \n“说不定他们现在正在玩？”老姐和我相视一眼，来源 \n来源 \n来源 \n我看了好几次，她们应该是没装冷气，窗户都开着，来源 \n透过纱窗，来源 \n虽然不亮，来源 \n我把望远镜定好，来源 \n老姐看了几分钟后，突然又“咭！”来源 \n我急忙问∶“什么？来源 \n“来源 \n“什么套子？怎么戴？来源 \n“来源 \n“这样好吗？”来源 \n“来源 \n“唔！”我心想，来源 \n“啊！……啊！插……插进去了！来源 \n“刚才不是告诉过你他们干的事吗？”大惊小怪！我一哂，来源 \n又静了一阵，老姐奶头越来越硬，在两腿间动的手，来源 \n虽说是舒舒服服的坐着吸吮老姐的乳头，狎玩她的乳房。来源 \n我说∶“姐，来源 \n“我保证不会全部插进去的！”来源 \n来源 \n“好吧！但记得不能给我插进来！来源 \n“是！是！我发誓！”来源 \n来源 \n老姐身躯有些发抖，来源 \n来源 \n铁硬的小弟弟，在她阴唇里外磨磨擦擦，老姐高翘的白屁股跟着摇摆。磨了几下，老姐突然低下头，不再“观”了，口里还“啊！来源 \n月光照在她一丝不挂，来源 \n来源 \n我又“非常不小心的”来源 \n老姐静了下来，没有抬头，低声说∶“轻轻的，温柔点，来源 \n我没说话，“轻轻的，温柔的”把小弟弟推进了小肉洞内。这中间，尽管是“来源 \n来源 \n刚开始抽插时，来源 \n“不知道有没有人用天文望远镜窥我们？”我心想，来源 \n“来源 \n“来了！来源 \n“来源 \n“这一支叫做鸡巴，你老弟的这一支，你应该叫他做大鸡巴。什么这一支这一支的，真不懂礼貌。”来源 \n老姐“来源 \n来源  \n把鸡巴举得高高的，第一道白色液体直射到老姐发上，来源 \n再射！来源 \n我用手指抹了一把，来源 \n来源 \n“弟！来源 \n“来源 \n“来源 \n“来源 \n“哼！哼！”老姐咬唇哼了几声说∶“来源 \n我的中指“吱吱噗噗”在老姐小洞的嫩肉上刷，来源 \n“来源 \n来源 \n来源 \n我看了口干舌燥，全身冒火，压在她身上，来源 \n老姐吓了一跳，推开我，“慢……慢慢来……”抓住鸡巴顶在小洞口，“好了，来源 \n我屁股一沉，来源 \n来源  \n我一下一下的插，老姐的小手也伸到底下，来源 \n老姐越搂越紧，身体抖起来。鼻子夹着哼声开始喘气，嘴唇离开了，来源  \n来源 \n老姐的力气好大，屁股狠命往上顶，来源 \n老姐尖尖的指甲抓在我背上，“对！对！用力！啊！啊！好棒！来源  \n我快要爆炸了，继续猛冲猛插。老姐小啾被插得“噗噗”的响，好紧，来源 \n越冲越快，也越用力，老姐急促的声音在耳旁响起∶“来源 \n“好！来源 \n“啊！怎么这么多！”来源 \n那一晚，姐弟两人，有一个醒来，就会去撩拨对方。用嘴巴、来源 \n我们的秘密一直保持着，直到有一晚∶来源  \n我拿起枕巾嗅了又嗅，确定老妈在我床上睡过。来源  \n老妈嘴里念念有词，还是开门放她进去了。来源 \n我却是满腹疑云！来源 \n我暗中注意了几次，老姐看妈妈的那种眼神，来源 \n有两天没见到老爸，晚饭时我问妈妈。来源  \n老妈又用筷子敲我的头，说∶“屏东分院开张，来源 \n老妈百般无奈的摇摇头，自言自语说着∶“唉！来源 \n来源 \n晚饭后，我打电话给死党阿山，叫他十分钟之后打过来，来源 \n来源 \n不久，我听到电话铃声，响了几声，来源 \n“弟！来源 \n来源 \n“看电影？来源 \n放下话筒，心想，死阿山，话剧、来源 \n“妈！来源 \n“你又要出去了？功课一蹋糊涂，我看你高中怎么考得上好学校！？来源 \n“算了！早点回来，来源 \n“来源 \n我在电玩店浸了约半个钟头，然后回家。静悄悄的开锁进门，我已预设碰见老妈或老姐，应有的说词。阿咪一个朋友生孩子，最近晚餐后，收拾干净、洗完碗筷，就跟老妈请假，去医院照顾她朋友。来源 \n我没看见老妈和老姐。客厅的灯亮着，老妈和老姐的房间，来源  \n我悄无声息躲在墙边看，客厅的灯射进了我的房间。来源  \n老妈一丝不挂，正压低望远镜在观“星”。来源  \n我赶快缩起脖子，整个人背贴着墙壁，来源 \n来源 \n“那大女孩……来源 \n老妈的声音在发抖，来源 \n老妈又说，“乖女儿……乖女儿……你也用舌头……用指头……来源 \n来源 \n我听了老妈那“啊……啊！”的浪叫声，心里实在痒得难受。又偷偷探头看去，老妈丰腴雪白的身子，来源 \n老妈手扶着姐的头，屁股一顶一顶，“来源 \n来源 \n来源 \n“啊！弟！你……你不是和阿山去看电影了？”老姐尖叫一声，来源 \n“我……我……”要命！预设的说词呢？来源 \n对了，想起来了，“阿山……阿山他……他叔叔，来源 \n“小非你给我滚进来！”来源  \n“妈！我……我……”真想转身就跑，可是看到妈妈那漂亮却又凶巴巴的脸孔，脚都吓软了。我晚上开水要是喝多的话，来源 \n“来源 \n“我……我在干什么事了？来源 \n来源 \n“来，告诉妈妈，”来源 \n来源 \n“看见什么？……看见……”我如何敢说，来源 \n“嗯？来源 \n“我什么也没看见，您们也没开灯，来源 \n“可是，可是什么？”来源 \n“可是，我听见，妈妈您叫姐姐，用舌头用指头，戳戳妈妈的洞洞……”来源 \n“啊！来源  \n（来源 \n老妈搂着我们两人，来源 \n“来！先说说你们的事给妈妈听，不许隐瞒。”老妈看着老姐一丝不挂的身子，说道∶“来源  \n老姐连耳根都红了，吞吞吐吐说∶“暑假开始的前一个星期，来源 \n天啊！这小荡女把我两人的秘密，来源 \n我心里如有十五个桶子吊在那边，来源  \n我怕老妈骂，等老姐一说完，马上壮起胆来，来源 \n老妈脸更红了，把手从床单底下抽出来，来源 \n老姐扭扭身体，撒娇的说∶“妈……来源 \n老妈“好像”此时才发现她全身上下，寸缕不着。随手在床头抓了一条大浴巾，来源 \n老姐把那条大浴巾学着老妈扎在腋下，却露出大半的两个乳房，只差奶头没跑出来。微光里，来源 \n我很觉得奇怪，为什么，老姐这样子要露不露的，来源 \n有一晚，来源  \n她门也不锁上，老妈拿我的衣裤进来，来源  \n看完了，老姐就缠着老妈东问西问（我猜当时老姐也是怕挨骂，故意夹缠不清）。来源  \n来源 \n转头看我一眼，继续说∶“那种场面，你问那些问题，来源 \n我说∶“来源 \n来源  \n来源 \n老姐扭了扭身体，夹了一下双腿，来源 \n来源 \n老姐垂着头，低声说∶“当时，来源  \n“然后……然后……我就要妈妈讲讲母的和母的，如何亲热、做爱……给我听。”老姐声音越来越低，来源 \n这时老妈又转头看我，接口说∶“你姐姐要妈妈讲解是小事，来源  \n来源 \n来源 \n我和老姐的事，终于在一次老妈要进来“观”时，在门外被她听到老姐的浪叫声，而“破功”来源 \n老妈当时也不拆穿，却经常有意无意的暗示老姐，她知道我和老姐的一些秘密。来源  \n两人第二次一起“来源 \n有一就有二，以后，在我的房间、浴室或老妈、老姐的房间，来源 \n来源  \n老妈的手，来源 \n来源 \n来源 \n我出神的想着，裤裆里一只肉棒，来源  \n来源 \n来源  \n老妈看到她儿子这硬梆梆的鸡巴，来源 \n老妈和我，演默剧似的，寂静无声。老姐张着双腿，却闭着双眼享受老妈的爱抚。来源  \n我把脸往后仰，藏到阴暗中，来源 \n老妈见我手过来了，放开抓住我鸡巴的手，来源 \n我看不到老妈的阴户，来源  \n我在老妈的阴唇、来源 \n这时，我感觉到有人在看，眼楮往左一瞄，老姐瞪大着眼楮，来源 \n我又怕又窘。那两根指头就插在老妈的旁蚤，来源 \n来源 \n我闻到了一般熟悉的香气，来源  \n老妈的“手艺”比起老姐好太多了。来源 \n“妈！妈……我想……我想……”来源 \n“你想……你想……来源 \n“来源 \n“坏孩子！来源  \n今晚就是被老妈打死了，来源 \n翻身骑上了她雪白丰腴的身子，嘻皮笑脸的说∶“来源 \n老姐“来源  \n我猴急的扯下衣裤，耳朵已经听到老妈低低呻吟的声音了。来源 \n我拨开老姐，站在地板上，来源 \n我看着那珍珠般、湿润的阴核。流出透明淫水、红红的、极为神秘的洞穴，白臣号满的阴阜。光线虽然不足，但是近看却轮廓分明，山是山、水是水。来源 \n老妈“来源 \n我的龟头，来源 \n老妈又挺了上来，这时我也火烧屁股般的，往下顶去。滑溜溜的，来源  \n来源 \n老妈低声呻吟着∶“轻些……轻些……来源 \n来源 \n我边插边看着老妈高高的乳房在跳动。插了也不知几十下，来源 \n老妈的呻吟声也越高。“哎！哎！宝贝，来源 \n我听了不禁越插越起劲，每次都把“木棒似的”来源 \n而每次老妈也总会“啊！”或是“哎！”要不然就是“唷！”的大叫一声。来源 \n我听到老妈叫着∶“宝贝儿子！来源 \n老妈抬起粉腿夹住我的腰，来源 \n又猛力的捅了几百下，来源 \n来源 \n老妈不仅阴道痉挛起来，子宫也痉挛着。我整条鸡巴，从深插在老妈子宫里的龟头，一直到紧凑在她阴道口的阴睫根部，甚至我的睾丸。也莫名其妙的跟着妈妈阴户的痉挛而非常亢奋、来源 \n我和老妈瘫在一块儿，来源 \n好热，我全身是汗，来源 \n“吁！好热！锳！去开冷气，也去拧条毛巾给妈妈擦，来源 \n来源 \n床震动了一下，老姐软软的的乳房碰到我的背。我睁开眼楮，看见老姐那条大浴巾落在床沿，来源  \n抓过老妈的手，来源 \n接着，来源 \n我第一次觉得，来源 \n“女儿帮您舔干净，依照咱们的游戏规则，来源 \n老妈瞧我一眼，满脸通红，“好啦！好啦！来源 \n果然，不光我一个人在讲，来源 \n来源 \n老妈把身体靠在被子上，屁股底下垫了我的枕头和那条大浴巾。张着大腿，把一个原本就高突的阴户，来源 \n来源 \n我看得发愣，鸡巴发烧。来源 \n当我摸进了充血、黏湿、来源 \n来源 \n我把杀气腾腾的鸡巴，顶在老姐红艳艳的阴道口。调了调高度，来源  \n来源 \n正在厮杀激烈之际，老妈娇嗔道∶“你尽管吃你的大餐，可别忘了妈妈的清理工作，来源 \n“知……知……来源 \n这次我干了很久，来源 \n老姐说∶“来源 \n转头叫我∶“弟，姐的膝盖好痛，从后面弄也不舒服，换个姿势再来！”来源 \n来源 \n这小骚女，不猛干狠，来源 \n居然尖叫着∶“弟！用力！用力干！来源 \n我得气喘如牛，来源  \n来源 \n我看了再也忍不住，鸡巴又使劲捅了十几下，睾丸都差点挤进老姐的旁蚤。来源 \n老姐被鸡巴死命的一顶，热精烫了又烫，来源 \n我们两人很美妙的，来源 \n休息片刻之后，来源 \n在浴室内，亮光下看着老妈姣好的容貌、硕大的乳房。来源 \n来源 \n老妈抓着“木棒似的”鸡巴说∶“来源  \n那次之后，避着老爸，大多数是单纯的两人行，内容是，来源  \n来源 \n老妈有一个嗜好，就是看小说。文艺言情、武侠、科幻、无所不包。从女中到大学，来源 \n来源 \n那天放学，进了客厅，看见老妈拿一本书，斜躺在沙发上聚精会神的在看。见我进门，打了一个招呼，来源 \n老妈嗜好看小说，来源 \n来源 \n来源 \n“妈咪！来源 \n老妈“来源 \n我钻到她裙内，“妈咪，来源 \n“唉！你这混小子，来源 \n我听老妈口气松动，马上拉开老妈小内裤一边，露出那只熟悉的鲍鱼肉。我舌头舔了上去，一股香气混着骚味，来源 \n舌、指并用，来源 \n我的舌尖在阴核上打转时，老妈的淫水喷了出来。叫道∶“儿子！儿子！来源 \n我拎起书包，老妈还不忘捡起她的书。我看她跨下沙发时，来源  \n我把门一锁，开灯、来源  \n来源 \n我心里一凉，来源  \n我停了一下，又慢慢插进去，插到一半时，抽出来，立刻又插进一半。如此三四次，来源 \n我不敢吭声，大鸡巴使力一顶到底，来源 \n插得老妈“亲亲儿子、乖儿子、大鸡巴儿子、来源 \n泄了精之后，我抱着老妈休息。迷迷糊糊中，来源 \n我故意“咳！”了一声，老妈见我醒来，娇娇的说∶“亲儿子，来，妈妈看妈妈的书，你赶快来做你的事！”拍拍阴户，来源 \n我轻声问∶“妈！来源 \n老妈阴唇被磨，微抖着声音∶“这本小说应该是翻译自法国的小说，很久以前我看过英文版。可是这本中文译版改了许多，变得粗俗不堪。但是现在来看，却极为刺激，啊！极为刺激！”老妈伸手抓住鸡巴，用力磨擦她的阴唇，来源 \n其实，我早知道老妈看的是哪一本。而那本小说的内容，来源 \n来源  \n老妈殷红的小口张了一下，来源 \n“乖儿！来源 \n我一想，有戏可听，鸡巴瞄准了遍湿、红艳的旁祥，慢慢的插进去。我看见老妈的两片大阴唇，已经忍不住，来源 \n一插进去，阴道壁的摺肉马上包着鸡巴，来源 \n老妈抓着我的肩膀，低声说∶“快动一动！来源 \n“您一边说故事，来源 \n“来源  \n我看老妈情欲高涨的样子，心里实在不忍，来源 \n不再油嘴滑舌，来源 \n我搂着老妈，来源  \n老妈喜欢这样玩，来源 \n鸡巴慢慢加快速度冲刺，来源 \n来源 \n老妈的叫床声，好似各本黄书精华。叫得满床淫味。有两三次，来源 \n来源 \n对面十九楼搬进来一个年轻的单身男子，作风大胆。来源 \n那男子时常带不同的女人回家过夜。窗帘从来不拉上的，一对男女，赤裸裸的，在屋内跑来跑去，嘻笑玩闹。来源  \n有时候，那只色狼还会带两个女人回家，来源 \n自从那只色狼搬来后，我们“观”星越来越热络。每每人家都还在唱前奏曲，老姐或老妈，就哆嗦着声音，来源 \n（来源 \n今年暑假的天气好像比去年热，大人都在唉唉叫，我们却玩得更高兴。来源    \n我怎会不知道两位老人家在房间里干些什么事呢？来源 \n老爸成天干老妈，来源 \n来源 \n有一次，那男子把女人抱在身上搞，老姐见了，来源 \n我看看老姐那高我一大截的身材，摇摇头，“不好！来源 \n她摇动着现在和老妈差不多大的乳房，来源  \n我受不了了，双手抱着她的屁股，来源  \n老姐屁股沉下来，放开一手，来源  \n我喘了一口气，用力往上顶去。才进入半条棒子，老姐的屁股就上上下下，套得“来源 \n我被她上上下下，前前后后，又跳又撞。来源  \n来源 \n老姐改为重而短距离的跳动，来源 \n来源 \n“弟！要走动，要跳啊！”这个小荡女，来源 \n我狼狈的在原地转了两圈，“你太重了，来源 \n老姐又上上下下套了几下，我也努力的往上顶。见她跳动的大奶子，我更加卖力的冲。老姐一直“来源  \n老姐放开手脚，把我推倒，跨在我身上，摇晃着两个乳房，继续“噗！嗤！噗！来源 \n套了几下，来源 \n我正扶着她的腰，来源 \n老姐嘻皮笑脸的说∶“你看，来源 \n来源 \n老姐摸着另一边的奶头，说∶“来源  \n“哈！你看看那些色情书刊，女人被插到快乐时，来源 \n“来源 \n“你起来，来源 \n老姐翻到另一边，说话之间，鸡巴变得半软不硬，脱了出来。来源 \n来源 \n问老姐∶“你念看看，大鸡巴后面接了什么？来源 \n老姐看那色文，跟着念∶“啊……来源 \n翻过一页，又念∶“来源 \n念完，来源 \n来源 \n老姐呻吟一声，满面火红，抱着我，伸手抓住鸡巴。阴道汨出淫液，喘着气说∶“那是小说瞎编的，来源  \n我把舌头伸进她香香的嘴巴里，来源 \n来源 \n“来源 \n我翻起身，架高她双腿，压住她，拿着鸡巴在张开的阴唇上摩蹭了几下，龟头顶了进去。背里还发出“吱！”的一声，老姐白白肥肥的阴户拱上来，来源  \n床铺一阵摇晃，粗长的鸡巴在紧凑湿润的阴道里外，来源 \n老姐两手抓住被单，来源 \n我觉得要喷出来了，赶紧放慢速度，老姐叫着∶“弟！用力！啊……用力！来源 \n我觉得再快一定喷出来。边调息边逗她∶“你应该怎么叫床？叫看看，来源 \n“弟！亲亲弟弟……大……大鸡巴弟弟……快用力插你的亲亲姐姐！拿你的大……大鸡巴用劲插死你的亲姐姐吧……”来源 \n我说∶“才不是这么叫呢！”慢慢“来源 \n“要死了！来源 \n“来源 \n“你明明是我弟弟，我才不那么叫呢！”来源 \n“你不叫，我实在没精神，那我们就这样插了。”来源 \n老姐在底下，蒙住眼楮的双手微抖。来源 \n来源  \n我心里暗笑着，低声说∶“就这样啊！？”来源 \n老姐喘口气又荡叫∶“哥哥！亲哥哥！快来插你的妹妹，用力插你的亲亲妹妹，好吗？”娇喘了一口气∶“来源  \n叫完，放开蒙眼的手，咬牙往我的腰际箝了一把。娇嗔着∶“来源 \n两姐弟干得天昏地暗。老姐的小啾、来源  \n什么大鸡巴哥哥、亲亲哥哥、亲妹妹。如何骚兽死人、流蜜汁的花心等着亲哥哥来采蜜。来源  \n第二天，来源 \n老姐也可以跟去，来源 \n来源 \n临出门前，老姐跑到我房里，“喂！我同学施家凤今晚会来我们家，老妈临时要上街，来源 \n我听到那美女要来，立刻睁大眼楮，坐个端正，裤底也一阵子骚热。老姐敲了我一个“来源  \n“懂了！懂了！”来源 \n又想到，招呼的是一个骚俜美少女，跪着迎接她也可以。裤底那一阵子的骚热，来源 \n来源 \n有人在按门铃，我三步并成两步，抢在阿咪前面接听，来源  \n家凤要找老姐还两张ＣＤ，顺便另借几张。来源  \n她忸怩了一下，说∶“来源 \n施家凤人很和气，来源 \n她的皮肤很白，和望远镜里看起来大大的不一样，美多了。来源 \n那天她穿一条短裤，来源 \n鼓鼓的胸部，被无袖黑短衣紧绷着。她这身衣裤底下的雪白肉体，我经常看见。可是，来源 \n我心怀不轨，但愿她注意到，有一管比她老弟施家豪更粗长、更棒，的大棒子就在她前面，来源 \n来源  \n选片接近尾声，我开了冷气，把话题转到她和施家豪上面。我们两人很“自然”的，来源 \n我说，常听老姐赞美你人长得漂亮，身材好，很有气质。老姐慕得要命。弟弟施家豪也是一样，来源  \n我把小说里，称赞人、巴结人的话，肉肉麻麻的搬了一大堆。施家凤这个女孩看来，也是属于胸大无脑类的。听得兴高采烈，尤其说到施家豪时，就换成她在讲话了。从施家豪如何听话、懂事、体贴。来源 \n来源  \n来源 \n来源 \n我轻抚拍着那光滑、圆圆的肩头，“没关系！没关系！没事！来源 \n来源 \n我低声叫∶“来源 \n施家凤半转过脸来，“来源 \n来源  \n她转回头，睁大眼楮看我，眼泪还在眼眶里。我又说∶“可是它现在还是硬梆梆的，涨得好痛，怎么办？你看！”来源 \n她见到我握着一只硕大的家伙，来源  \n施家凤“啊”了一声，半信半疑的，“姐姐看看！来源  \n她心意相通似的，真的低下头含起龟头，舌尖一卷，来源 \n来源 \n施家豪不在家，她旷了好多天，来源 \n一边口交一边剥衣裤，剥衣服时，小嘴巴离开我的鸡巴，时间之短，我几乎没感觉。来源  \n那两个乳房，就在我眼下，来源 \n家凤吞吐了片刻，我听到细细的鼻喘声，来源 \n抬起头来，来源 \n来源 \n来源 \n躺到床上，倚着被子。抓了一个枕头垫在屁股下，高举双腿，用两手扳着大腿，来源 \n我看得目瞪口呆，家凤如玉似的两腿腿根间，来源 \n那片毛，来源 \n那片毛的尽处裂了微红的一道缝，来源 \n家凤虾起身子说∶“来源 \n我把鸡巴凑上去，假装找不到，来源  \n弄得家凤“呀！来源 \n“来！姐姐帮你弄！”她的手伸下来，来源 \n“好了，来源 \n来源 \n来源  \n她“指导”来源 \n来源 \n就差从头到尾，都是她做主。下次，一定要我做主，来源 \n来源 \n发现他们两人，来源 \n来源  \n来源 \n来源 \n她装不知道，经常邀施家凤来我们家，来源 \n天气逐渐凉了，对面大楼，各家门窗渐渐紧闭。来源 \n老姐、老妈和我转而共同“观赏”各家色情文章，有时仿效其法，跟着干，来源 \n我自己拼命收集，阿山把我取个“色情狂”的绰号，也帮我拼命收集。来源 \n来源 　１００１ｋｍ敬上\n【\n来源 \n全文完】"
    }
  ],
  "tags": [
    "其他"
  ]
}